Workbook
Name ABANGARES: PROVINCIAS!$G$73:$G$76
Name ACOSTA: PROVINCIAS!$L$13:$L$17
Name AGUIRRE: PROVINCIAS!$F$86:$F$88
Name ALAJUELA: PROVINCIAS!$B$3:$P$3
Name ALAJUELA_: PROVINCIAS!$A$28:$A$41
Name ALAJUELITA: PROVINCIAS!$J$13:$J$17
Name ALFARO_RUIZ: PROVINCIAS!$K$28:$K$34
Name ALVARADO: PROVINCIAS!$F$46:$F$48
Name ASERRI: PROVINCIAS!$F$12:$F$18
Name ATENAS: PROVINCIAS!$E$28:$E$34
Name BARVA: PROVINCIAS!$B$61:$B$66
Name BELÉN: PROVINCIAS!$G$61:$G$63
Name BUENOS_AIRES: PROVINCIAS!$C$86:$C$93
Name CAÑAS: PROVINCIAS!$F$73:$F$77
Name CARRILLO: PROVINCIAS!$E$73:$E$76
Name CARTAGO: PROVINCIAS!$B$4:$I$4
Name CARTAGO_: PROVINCIAS!$A$46:$A$56
Name CORREDORES: PROVINCIAS!$J$86:$J$89
Name COTO_BRUS: PROVINCIAS!$H$86:$H$90
Name CURRIDABAT: PROVINCIAS!$R$13:$R$16
Name DESAMPARADOS: PROVINCIAS!$C$12:$C$23
Name DOTA: PROVINCIAS!$Q$13:$Q$15
Name EL_GUARCO: PROVINCIAS!$H$46:$H$49
Name ESCAZÚ: PROVINCIAS!$B$12:$B$14
Name ESPARZA: PROVINCIAS!$B$86:$B$90
Name FLORES: PROVINCIAS!$H$61:$H$63
Name GARABITO: PROVINCIAS!$K$86:$K$87
Name GOICOCHEA: PROVINCIAS!$H$13:$H$19
Name GOLFITO: PROVINCIAS!$G$86:$G$89
Name GRECIA: PROVINCIAS!$C$28:$C$35
Name GUÁCIMO: PROVINCIAS!$F$103:$F$107
Name GUANACASTE: PROVINCIAS!$B$6:$L$6
Name GUATUSO: PROVINCIAS!$O$28:$O$30
Name HEREDIA: PROVINCIAS!$B$5:$K$5
Name HEREDIA_: PROVINCIAS!$A$61:$A$65
Name HOJANCHA: PROVINCIAS!$K$73:$K$76
Name JIMÉNEZ: PROVINCIAS!$D$46:$D$48
Name LA_CRUZ: PROVINCIAS!$J$73:$J$76
Name LA_UNIÓN: PROVINCIAS!$C$46:$C$53
Name LEÓN_CORTES: PROVINCIAS!$T$13:$T$18
Name LIBERIA: PROVINCIAS!$A$73:$A$77
Name LIMÓN: PROVINCIAS!$B$8:$G$8
Name LIMÓN_: PROVINCIAS!$A$103:$A$106
Name LOS_CHILES: PROVINCIAS!$N$28:$N$31
Name MATINA: PROVINCIAS!$E$103:$E$105
Name MONTES_DE_OCA: PROVINCIAS!$O$13:$O$16
Name MONTES_DE_ORO: PROVINCIAS!$D$86:$D$88
Name MORA: PROVINCIAS!$G$13:$G$17
Name MORAVIA: PROVINCIAS!$N$13:$N$15
Name NANDAYURE: PROVINCIAS!$I$73:$I$78
Name NARANJO: PROVINCIAS!$F$28:$F$34
Name NICOYA: PROVINCIAS!$B$73:$B$79
Name OREAMUNO: PROVINCIAS!$G$46:$G$50
Name OROTINA: PROVINCIAS!$I$28:$I$32
Name OSA: PROVINCIAS!$E$86:$E$90
Name PALMARES: PROVINCIAS!$G$28:$G$34
Name PARAÍSO: PROVINCIAS!$B$46:$B$49
Name PARRITA: PROVINCIAS!$I$86
Name PEREZ_ZELEDÓN: PROVINCIAS!$S$13:$S$23
Name POÁS: PROVINCIAS!$H$28:$H$32

Sheet FORMULARIO
A1: MUNICIPALIDAD DE TILARÁN
A2: Proceso de Servicios Ciudadanos y Técnicos
R3: 2026
A4: DECLARACIÓN JURADA DEL IMPUESTO DE PATENTES PARA EL AÑO
A5: =VLOOKUP(R3,PARÁMETROS!D613:E617,2) -> Del 01 de enero 2025al 31 de diciembre de 2025
A9: NOMBRE DEL PATENTADO: | P9: Nº CÉDULA:
A10: REPRESENTANTE LEGAL: | P10: Nº CÉDULA:
A11: LUGAR O MEDIO PARA NOTIFICACIONES: | H11: Correo electrónico | P11: N° CELULAR:
A12: CORREO ELECTRÓNICO:
A13: NOMBRE DEL NEGOCIO: | P13: N° FINCA:
A14: TIPO RIESGO SANITARIO PSF: | I14: HORA APERTURA: | O14: HORA CIERRE:
A15: BAJO LA GRAVEDAD DE JURAMENTO Y CONFORME A LAS CONDICIONES QUE ESTABLECE EL CÓDIGO DE NORMAS Y PROCEDIMIENTOS TRIBUTARIOS Y LA LEY LICENCIAS PARA LAS ACTIVIDADES LUCRATIVAS DEL CANTÓN DE TILARÁN, N° 9505-2018, DECLARO QUE ESTE INFORME Y LOS DOCUMENTOS ADJUNTOS HAN SIDO EXAMINADOS POR MI; CONTIENEN UNA VERDADERA Y COMPLETA DECLARACIÓN, PARA EL CÁLCULO DEL IMPUESTO DE PATENTES.
E19: TILARÁN, | H19: DE | L19: DEL AÑO
A23: FIRMA DEL REPERESENTANTE LEGAL
A24: O PATENTADO
A26: ACTIVO NETO: | P26: ¢
A27: VENTAS O INGRESOS BRUTOS DEL PERÍODO: | P27: ¢
A28: COMPRAS DEL PERÍODO: | P28: ¢
A29: PERSONAL EMPLEADO: | S29: Colaboradores
A33: CANTIDAD ANUAL DE COMBUSTIBLE VENDIDO EN litros
A34: INGRESO ANUAL POR OTRAS ACTIVIDADES | P34: ¢
C35: Continúa al dorso…
A39: 4. REQUISITOS
C41: 1. En el caso de los contribuyentes del Régimen Tradicional, se deberá adjuntar copia del formulario D 101,
C42: IMPUESTO SOBRE UTILIDADES, correspondiente al período fiscal anterior.
C43: 2. En el caso de los contribuyentes inscritos en el Régimen de Tributación Simplificado, deberán presentar copia
C44: del formulario D 105 o DECLARACIÓN JURADA DEL RÉGIMEN DE TRIBUTACIÓN SIMPLIFICADA, correspondiente
C45: a los cuatro trimestres del período fiscal anterior.
C46: 3. Permiso Sanitario de Funcionamiento, o Certificado Veterinario de Operación, VIGENTE. (Verificación por parte
C47: Administración).
A48: 5. RECIBIDO
A50: EL PRESENTE FORMULARIO DEBERÁ SER LLENADO A MÁQUINA O CON LETRA IMPRENTA Y ABSOLUTAMENTE LEGIBLE.
A51: ADEMÁS, DEBERÁ PRESENTARSE EN LA PLATAFORMA DE SERVICIOS ANTES DEL | N51: =VLOOKUP(R3,PARÁMETROS!D613:F617,3,0) -> 46142
A52: PARA CONSULTAS A LOS TELÉFONOS 26 95 24 07, 26 95 24 09, 26 95 24 10 o 26 95 24 12

Sheet CONSTANCIA REQUISITOS
B2: MUNICIPALIDAD DE TILARÁN
B3: Proceso Servicios Ciudadanos y Técnicos
B4: Unidad Plataforma de Servicios
B6: CONSTANCIA DE VERIFICACIÓN DE REQUISITOS
B8: El(la) abajo firmante, funcionaro(a) municipal, hace constar que ante ésta administración se trámita FMT
B9: 021 Declaración de patente para 2021 bajo las siguientes condiciones:
B11: Nombre del patentado: | I11: =+FORMULARIO!F9 -> 0
B12: Cédula de identidad: | H12: =+FORMULARIO!R9 -> 0
B14: Verificado el expediente de la solicitud, se constata la presentación de los siguientes requisitos:
Z16: CUMPLE
B17: Formulario Declaración Jurada del Impuesto de patentes FMT 021 debidamente lleno | Z17: √
B18: Permiso Sanitario de Funcionamiento, emitido por el Ministerio de Salud, o el SENASA, VIGENTE. | Z18: x
B19: Copia Declaración Jurada del Impuesto sobre la Renta D 101 | Z19: √
B20: Copias (4) Declaraciones Juradas del Régimen de Tributación Simplificada D105 | Z20: NA
B21: Se apercibe al solicitante que deberá en el término de DIEZ días cumplir con el(los) requisito(s) pediente(s), caso contrario se ordenará el archivo de la solicitud sin mayor trámite. Tómese en cuenta que según el inciso i) del artículo 7º del Reglamento general de patentes comerciales y similares de la Municipalidad de Tilarán, la municipalidad podrá SUSPENDER la patente, cuando el patentado omita presentar la Declaración jurada de sus ventas brutas e ingresos brutos y de su renta líquida gravable, a que hace referencia el artículo 13 de éste Reglamento. Finalmente, considérese lo establecido en el artículo 22º de la Ley 9505-2018: Los patentados o sujetos pasivos que no presenten dentro del término establecido la declaración jurada del impuesto, con sus anexos, se harán acreedores de una multa equivalente a un cincuenta por ciento (50%) del monto anual del impuesto pagado el año anterior, la cual deberá pagarse conjuntamente con el impuesto del trimestre siguiente a las fechas establecidas en el artículo 20 de esta ley. En ningún caso esta multa será inferior a medio salario base, al día de hoy ¢ 231.100.00. El concepto de "salario base" usado en esta Ley es el establecido en el artículo 2 de la Ley No. 7337, de 5 de mayo de 1993.
B39: Annia Ramírez Rodríguez
B40: =VLOOKUP(B39,PARÁMETROS!E107:H129,4,0) -> PLATAFORMISTA

Sheet TOMA DATOS
C3: MUNICIPALIDAD DE TILARÁN
C4: Proceso de Servicios Ciudadanos y Técnicos
C5: FORMULARIO PARA LA RECALIFICACIÓN DEL IMPUESTO DE PATENTES
C7: A. DATOS DEL PATENTADO
C8: 1) Identificación patentado: | T8: 501930016
K9: =VLOOKUP(T8,ACTIVAS!$A$3:$AK$916,2,FALSE) -> JORGE ARTURO CHAVARRIA MONGE
C10: 2) Actividades autorizadas: | T10: =VLOOKUP(T8,ACTIVAS!A3:AK916,37,FALSE) -> 1
C11: 3) Actividad comercial: | T11: Otros | AE11: 501930016
C12: 4) Horario apertura: | T12: 0.29166667
C13: 5) Horario cierre: | T13: 0.70833333
C14: 6) Cantidad de Trabajadores: | T14: 2
C15: 7) Activo Neto | T15: 4325000
C16: 8) Ingresos brutos del período | T16: 12382000
C17: 9) Compras | T17: 0
C18: D. PARA USO DE LA OFICINA
C19: 10) Verificación de requisitos:
Y20: CUMPLE
C21: Formulario Declaración Jurada del Impuesto de patentes FMT 021 debidamente lleno | Y21: √
C22: Permiso Sanitario de Funcionamiento, emitido por el Ministerio de Salud, o el SENASA, VIGENTE. | Y22: √
C23: Copia Declaración Jurada del Impuesto sobre la Renta D 101 | Y23: NA
C24: Copias (4) Declaraciones Juradas del Régimen de Tributación Simplificada D105 | Y24: √
C50: MUNICIPALIDAD DE TILARAN
C51: Proceso de Servicios Ciudadanos y Técnicos
C52: Recalificación anual de patentes
C54: INFORMACIÓN GENERAL
C56: PATENTADO: | G56: =+'TOMA DATOS'!K9 -> JORGE ARTURO CHAVARRIA MONGE
C58: ACTIVIDADES AUTORIZADAS | Z58: =+'TOMA DATOS'!T10 -> 1
C60: DETALLE DEL CÁLCULO DEL IMPUESTO
C62: A. CÁLCULO DEL IMPUESTO ( Artículo 12, LEY 9505-2018 )
C64: De ¢ 0,00 hasta ¢ 750,000,000,00 | O64: 1.75
C65: De ¢750,000,001,00 hasta ¢ 1,500,000,000,00 | O65: 2.5
C66: De ¢ 1,500,000,001,00 hasta ¢ 3,000,000,000,00 | O66: 3.25
C67: De ¢ 3,000,000,001,00 hasta ¢ más | O67: 4.25
C68: IMPUESTO ANUAL | H68: =+IF(T16<750000000,T16*O64/1000,IF(T16<1500000000,T16*O65/1000,IF(T16<3000000000,T16*O66/1000,T16*O67/1000))) -> 21668.5 | P68: IMPUESTO TRIMESTRAL | V68: =+H68/4 -> 5417.125
C70: B. CALCULO IMPUESTO ( Artículo 125°, inciso b) Código de Normas y Procedimientos Tributarios )
C72: CANTIDAD | F72: PUESTO | N72: SALARIO | Q72: SALARIO GRUPAL | T72: CARGAS SOCIALES 31.36% | W72: COSTO MENSUAL
C73: 1 | F73: Licenciados Universitarios | N73: =VLOOKUP(F73,PARÁMETROS!M335:N344,2,0) -> 796921 | Q73: =+N73*C73 -> 796921 | T73: =+Q73*31.36% -> 249914.43 | W73: =+ROUND(T73+Q73,0) -> 1046835
C74: =+'TOMA DATOS'!T14-'TOMA DATOS'!C73 -> 1 | F74: Trabajadores en Ocupación No Calificada | N74: =IFERROR(VLOOKUP(F74,PARÁMETROS!M335:N344,2,0),"") -> 373092.3 | Q74: =IFERROR(N74*C74,"") -> 373092.3 | T74: =IFERROR(Q74*31.36%,"") -> 117001.75 | W74: =IFERROR(ROUND(T74+Q74,0),"") -> 490094
C75: COSTO ANUAL ESTIMADO POR REMUNERACIONES: | W75: =SUM(W73:AA74)*12 -> 18443148 | AB75: 0.4
C76: OTROS COSTOS ANUALES ESTIMADOS: | W76: =+W75*1.5 -> 27664722 | AB76: =+W76/W77 -> 0.6
C77: TOTAL COSTOS ANUALES ESTIMADOS: | W77: =+W76+W75 -> 46107870
C79: ACTIVO NETO:
C80: Monto | E80: =+'TOMA DATOS'!T15 -> 4325000
C81: Puntaje | E81: =+IF(E80>=10000000,1.15,IF(D31<=5000000,1,1.1)) -> 1
C83: ZONA: | E83: Alrededores distrito
C84: Puntaje | E84: =VLOOKUP(E83,PARÁMETROS!M347:N350,2,0) -> 1
C86: HORARIO:
C87: Apertura | E87: =+'TOMA DATOS'!T12 -> 0.29166667
C88: Cierre | E88: =+'TOMA DATOS'!T13 -> 0.70833333
C89: Horas | E89: - 12 horas
C90: Puntaje | E90: =VLOOKUP(E89,PARÁMETROS!M352:N354,2,0) -> 1
C92: PUNTAJE TOTAL: | H92: =+E90+E84+E81 -> 3 | L92: =+PARÁMETROS!N355 -> 3.25 | M92: 1 | N92: =+H92 -> 3 | O92: X
C93: 3.25 | D93: 1 | E93: =+H92 -> 3 | F93: X
C100: TOTAL GASTOS ESTIMADOS: | N100: =+E93*D93/C93 -> 0.92307692
C101: COSTO ANUAL ESTIMADO * ( 1+PUNTAJE TOTAL/9 ) | W101: =+W77*N100 -> 42561111
C102: ACTIVIDAD COMERCIAL SEGÚN AGRUPACIÓN: | M102: =+T11 -> Otros
C103: FACTOR DE UTILIDAD: | M103: =VLOOKUP(M102,PARÁMETROS!B568:C582,2,0) -> 4.125
C104: FACTOR DE UTILIDAD: | I104: =+M103 -> 4.125 | K104: =+I104-1 -> 3.125 | M104: =100%/K104 -> 0.32 | P104: =100%+M104 -> 1.32 | S104: =+P104/100% -> 1.32
C105: INGRESO BRUTO ANUAL ESPERADO: | W105: =+S104*W101 -> 56180666
C106: INGRESO BRUTO MENSUAL ESPERADO: | W106: =+W105/12 -> 4681722.2
C108: De ¢ 0,00 hasta ¢ 750,000,000,00 | N108: 1.75
C109: De ¢750,000,001,00 hasta ¢ 1,500,000,000,00 | N109: 2.5
C110: De ¢ 1,500,000,001,00 hasta ¢ 3,000,000,000,00 | N110: 3.25
C111: De ¢ 3,000,000,001,00 hasta ¢ más | N111: 4.25
C112: IMPUESTO ANUAL | H112: =+IF(W105<750000000,W105*N108/1000,IF(W105<1500000000,W105*N109/1000,IF(W105<3000000000,W105*N110/1000,W105*N111/1000))) -> 98316.166 | P112: IMPUESTO TRIMESTRAL | V112: =+ROUND(H112/4,0) -> 24579
C114: C. CÁLCULO DEL IMPUESTO (Artículo 15, LEY 9505-2018 Régimen Tributación Simplificado)
C116: IMPUESTO ANUAL | H116: =+O116*T17 -> 0 | O116: =4/1000 -> 0.004 | P116: IMPUESTO TRIMESTRAL | V116: =+H116/4 -> 0
C118: IMPUESTO ANUAL DE PATENTES AÑO ANTERIOR POR ACTIVIDAD | V118: 63208
C120: IMPUESTO TRIMESTRAL DE PATENTES AÑO ANTERIOR POR ACTIVIDAD | V120: =+V118/4 -> 15802
C134: CALCULO IMPUESTO TRIMESTRAL
U136: INGRESO REPORTADO
C137: ARTÍCULO 12 LEY 9505-2018 | U137: =+'TOMA DATOS'!T16 -> 12382000
C138: GASTOS DECLARADOS ( Inciso b) art 125 CNPT ) | U138: =+W105 -> 56180666
C139: AÑO ANTERIOR | U139: =+V120 -> 15802
U141: IMPUESTO TRIMESTRAL
C142: ARTÍCULO 12 LEY 9505-2018 | U142: =V68 -> 5417.125
C143: REGIMEN DE TRIBUTACIÓN SIMPLIFICADO (Art. 15 LEY 9505-2018) | U143: =+V116 -> 0
C144: GASTOS DECLARADOS ( Inciso b) art 125 CNPT ) | U144: =+V112 -> 24579
C145: AÑO ANTERIOR | U145: =+U139 -> 15802
C156: ESTIMACIÓN RELEVANTE | U156: 15802
C157: ACTIVIDADES AUTORIZADAS | Z157: =+Z58 -> 1
C158: IMPUESTO POR ACTIVIDAD COMERCIAL | U158: =U156/Z157 -> 15802
C159: IMPUESTO ANUAL POR ACTIVIDAD AUTORIZADA | U159: =U158*4 -> 63208
C160: TIMBRE ANUAL 2% LEY 7788 ( 119102000000002 ) | U160: =+ROUND(U156*2%,0)*4 -> 1264
O162: =IF(U156<>U139,"Varía","Permanece igual") -> Permanece igual
U164: =+(U145*4)*50% -> 31604
N166: HECHO POR: | Q166: Yamileth Carvajal Manzanares
N169: REVISADO POR: | Q169: José Antonio Rodríguez Herrera

Sheet ACTIVAS
A1: Identificación | B1: Nombre | C1: Nombre Representante Legal | D1: Identificación Representante Legal | E1: Tipo Identificación | F1: Celular | G1: Teléfono | H1: Correo | I1: Actividad Económica | J1: Nombre Comercial | K1: Identificación Propietario BienInmueble | L1: Nombre Propietario BienInmueble. | M1: Tipo Identificación Propietario BienInmueble | N1: Celular Propietario BienInmueble | O1: Teléfono Propietario BienInmueble | P1: Correo Electrónico Propietario BienInmueble | Q1: Actividad Económica Propietario BienInmueble | R1: Finca | S1: Duplicado | T1: Horizontal | U1: Derecho | V1: Provincia | W1: Cantón | X1: Distrito | Y1: Geo-referenciación-Latitud | Z1: Geo-referenciación-Longitud | AA1: Coordenada X | AB1: Coordenada Y | AC1: Dirección Física | AD1: Número Patente | AE1: Tipo Patente | AF1: Tipo Temporalidad | AG1: Monto Impuesto | AH1: Fecha Aprobación Patente | AI1: Fecha Cierre | AJ1: Estado
A2: 1 | B2: =1+A2 -> 2 | C2: =1+B2 -> 3 | D2: =1+C2 -> 4 | E2: =1+D2 -> 5 | F2: =1+E2 -> 6 | G2: =1+F2 -> 7 | H2: =1+G2 -> 8 | I2: =1+H2 -> 9 | ... AK2: =1+AJ2 -> 37
A3: 3101722970 | B3: 3-101-722970 SOCIEDAD ANONIMA | C3: ILEANA SANCHEZ VALVERDE | D3: 206350262 | E3: 1 | F3: 84199031 | G3: 84199031 | H3: arrientos@asesortotal.com | I3: COSMETICOS PERFUMERIA BISUTERIA | J3: FARMACIA DON GERARDO TILARAN | K3: 3101082143 | L3: INVERSIONES NIBELUNGOS SOCIEDAD ANONIMA | M3: N | N3: 88153066 | O3: 26955725 | P3: gwattsong@gmail.com | R3: 00113261 | S3: 0 | T3: 0 | U3: 000 | V3: 5 | W3: 08 | X3: 01 | AC3: FRENTE A GASOLINERA TILARAN | AD3: 0000000992 | AE3: C | AF3: P | AG3: 0 | AH3: 44012 | AJ3: A | AK3: =COUNTIF($A$3:A$917,A3) -> 2
A4: 208270217 | B4: FILANDER ANDRES SOTO CERDAS | F4: 86913093 | G4: 86913093 | H4: soto47916@gmail.com | J4: AMERICAN OUTLET | K4: 3101309683 | L4: AUTOTRANSPORTES JOCEKADI SOCIEDAD ANONIMA | M4: N | N4: 88106600 | P4: yenuro_86@hotmail.com | R4: 00006660 | S4: 0 | T4: 0 | U4: 000 | V4: 5 | W4: 08 | X4: 01 | AC4: FRENTE AL BANCO DE COSTA RICA | AD4: 0000001776 | AE4: C | AF4: P | AG4: 0 | AH4: 45153 | AJ4: A | AK4: =COUNTIF($A$3:A$917,A4) -> 1
A5: 155815120705 | B5: JUANA DEL C RODRIGUEZ VILCHEZ | F5: 61214294 | G5: 88233991 | H5: ciin.rodri@gmail.com | J5: H R BIZCOCHERIA ANTOJITOS DE MI TIERRA | K5: 502970875 | L5: HERNAN ALONSO ROJAS HERRERA | M5: N | N5: 88486482 | P5: alonsorojasharh@hotmail.com | R5: 00057576 | S5: 0 | T5: 0 | U5: 000 | V5: 5 | W5: 08 | X5: 01 | AC5: 50 M OESTE DE LA CRUZ ROJA TILARAN | AD5: 0000001796 | AE5: C | AF5: P | AG5: 0 | AH5: 45176 | AJ5: A | AK5: =COUNTIF($A$3:A$917,A5) -> 1
A6: 502640291 | B6: ORLANDO ALVARADO ARCE | F6: 85366309 | H6: orlandoal044@gmail.com | J6: MINISUPER LA AMISTAD | K6: 502640291 | L6: ORLANDO ALVARADO ARCE | M6: N | N6: 85366309 | P6: orlandoal044@gmail.com | R6: 00084466 | S6: 0 | T6: 0 | U6: 000 | V6: 5 | W6: 08 | X6: 04 | AC6: 200 M NORTE Y 50 OESTE DE LA IGLESIA CATOLICA LOS ANGELES | AD6: 0000001728 | AE6: C | AF6: P | AG6: 0 | AH6: 45086 | AJ6: A | AK6: =COUNTIF($A$3:A$917,A6) -> 1
A7: 155834652505 | B7: TANIA VANESSA ESPINOZA | F7: 61069366 | G7: 64709913 | H7: espinozatania568@gmail.com | J7: RESTAURANTE J & B | K7: 801360226 | L7: BELKIS ONEYDA MARADIAGA FLORES | M7: N | N7: 72630616 | O7: 72630616 | P7: belkisoneymaradiaga@gmail.com | R7: 00224764 | S7: 0 | T7: 0 | U7: 000 | V7: 5 | W7: 08 | X7: 01 | AC7: 1 K CAMINO A LIBANO DEL CEMENTERIO | AD7: 0000001753 | AE7: C | AF7: P | AG7: 0 | AH7: 45139 | AJ7: A | AK7: =COUNTIF($A$3:A$917,A7) -> 1
A8: 502710312 | B8: VIRGITA DEL CARMEN MENDEZ VEGA | F8: 62461759 | G8: 62222581 | H8: virgita17@gmail.com | J8: RESTAURANTE EL SABOR DE NUESTRO PUEBLO | K8: 502710312 | L8: VIRGITA DEL CARMEN MENDEZ VEGA | M8: N | N8: 62461759 | O8: 62222581 | P8: virgita17@gmail.com | R8: 00252904 | S8: 0 | T8: 0 | U8: 000 | V8: 5 | W8: 08 | X8: 02 | AC8: DE LA IGLESIA 300M.NORTE 100M.OESTE QDA.GRANDE | AD8: 0000001744 | AE8: C | AF8: P | AG8: 0 | AH8: 45119 | AJ8: A | AK8: =COUNTIF($A$3:A$917,A8) -> 2
A9: 502780472 | B9: ALEX ANTONIO ARTAVIA CONEJO | F9: 84126109 | G9: 84126109 | H9: artaviaalex01@gmail.com | I9: ABARROTES | J9: PULPERIA LA UNIÓN | K9: 502780472 | L9: ALEX ANTONIO ARTAVIA CONEJO | M9: N | N9: 84126109 | O9: 84126109 | P9: artaviaalex01@gmail.com | R9: 00104267 | S9: 0 | T9: 0 | U9: 000 | V9: 5 | W9: 08 | X9: 07 | AC9: 50 DEL CRUCE DE VENADO CAMINO A FORTUNA, LA UNIÓN | AD9: 0000001230 | AE9: C | AF9: P | AG9: 0 | AH9: 44391 | AJ9: A | AK9: =COUNTIF($A$3:A$917,A9) -> 1
A10: 601490937 | B10: ANA CECILIA DEL SOCORRO MONGE MENDOZA | F10: 85941813 | G10: 26951196 | H10: mainorlp@hotmail.com | I10: ABARROTES | J10: PULPERIA SAN RAFAEL | K10: 601490937 | L10: ANA CECILIA DEL SOCORRO MONGE MENDOZA | M10: N | N10: 85941813 | O10: 26951196 | P10: mainorlp@hotmail.com | R10: 00178832 | S10: 0 | T10: 0 | U10: 000 | V10: 5 | W10: 08 | X10: 04 | AC10: BARRIO SAN RAFAEL LOTE # 41 LOS ANGELES TILARAN | AD10: 0000000498 | AE10: C | AF10: P | AG10: 0 | AH10: 40562 | AJ10: A | AK10: =COUNTIF($A$3:A$917,A10) -> 1
A11: 602340703 | B11: ASVIN ELIZONDO ARIAS | F11: 87895888 | G11: 87895888 | H11: abastecedorlaplaza@gmail.com | I11: ABARROTES | J11: PULPERIA LA PLAZA | K11: 602340703 | L11: ASVIN ELIZONDO ARIAS | M11: N | N11: 87895888 | O11: 87895888 | P11: abastecedorlaplaza@gmail.com | R11: 00183291 | S11: 0 | T11: 0 | U11: 000 | V11: 5 | W11: 08 | X11: 04 | AC11: COSTADO SUR PLAZA DEPORTES QDA AZUL | AD11: 0000000511 | AE11: C | AF11: P | AG11: 0 | AH11: 39615 | AJ11: A | AK11: =COUNTIF($A$3:A$917,A11) -> 1
A12: 111110681 | B12: CARLOS ANDRES HERRERA RIVERA | F12: 85711157 | H12: carlosherrerar81@gmail.com | I12: ABARROTES | J12: PULPERIA LULU | K12: 501620778 | L12: FLOR MARIA DE DOLORES SOTO ELIZONDO | M12: N | N12: 84469153 | P12: florsotoelizondo@gmail.com | R12: 00060850 | S12: 0 | T12: 0 | U12: 000 | V12: 5 | W12: 08 | X12: 01 | AC12: 400 M ESTE DEL SALON COMUNAL BUENOS AIRES | AD12: 0000000056 | AE12: C | AF12: P | AG12: 0 | AH12: 43621 | AJ12: A | AK12: =COUNTIF($A$3:A$917,A12) -> 1
A13: 501710654 | B13: EFRAIN DE LAS PIEDADES ARIAS ZUÑIGA | F13: 88250549 | H13: darias_89@hotmail.com | I13: ABARROTES | J13: ABASTECEDOR DON EFRA | K13: 501050720 | L13: ANAIS MARIA DEL CARMEN LOPEZ ARTAVIA | M13: N | N13: 87904740 | O13: 26955642 | P13: darias_89@hotmail.com | R13: 00106528 | S13: 0 | T13: 0 | U13: 000 | V13: 5 | W13: 08 | X13: 01 | AC13: COSTADO NORTE DE LA CCSS, MINISUPER EFRAIN | AD13: 0000001994 | AE13: C | AF13: P | AG13: 0 | AH13: 45462 | AJ13: A | AK13: =COUNTIF($A$3:A$917,A13) -> 1
A14: 501460976 | B14: GERARDO MANUEL DELGADO CERDAS | F14: 83717783 | H14: gerardodelcer@gmail.com | I14: ABARROTES | J14: PULPERIA MAYNEL | K14: 501920883 | L14: ENA DAMARIS RUIZ ROJAS | M14: N | N14: 84851952 | O14: 84851952 | P14: damariruiz494@gmail.com | R14: 00056496 | S14: 0 | T14: 0 | U14: 000 | V14: 5 | W14: 08 | X14: 06 | AC14: CONTIGUO O IGLESIA CATOLICA DE SABALITO TIERRAS MORENAS | AD14: 0000000199 | AE14: C | AF14: P | AG14: 12611 | AH14: 36662 | AJ14: A | AK14: =COUNTIF($A$3:A$917,A14) -> 1
A15: 502530162 | B15: GERSAN GERARDO CHACON CORELLA | F15: 83375089 | G15: 83375089 | H15: chacon.gaby@hotmail.com | I15: ABARROTES | J15: " MINI SUPER GERSAN" | K15: 3101082143 | L15: INVERSIONES NIBELUNGOS SOCIEDAD ANONIMA | M15: N | N15: 88153066 | O15: 26955725 | P15: gwattsong@gmail.com | R15: 00039313 | S15: 0 | T15: 0 | U15: 000 | V15: 5 | W15: 08 | X15: 01 | AC15: DIAGONAL A LA GASOLINERA TILARÁN. | AD15: 0000000001 | AE15: C | AF15: P | AG15: 128609 | AH15: 36720 | AJ15: A | AK15: =COUNTIF($A$3:A$917,A15) -> 1
A16: 204820469 | B16: GIOVANNI RAMIREZ GAMBOA | F16: 62792322 | G16: 26938189 | H16: fale16cg@hotmail.com | I16: ABARROTES | J16: "MINISUPER CRISS" | K16: 3002066206 | L16: ASOCIACION DESARROLLO INTEGRAL DE CABECERAS DE CAÑ | M16: N | N16: 87134040 | P16: adicabeceras@gmail.com | R16: 00161381 | S16: 0 | T16: 0 | U16: 000 | V16: 5 | W16: 08 | X16: 02 | AC16: 50M N DEL ABAST CABECEREÑO DE CABECERAS (LOCALES COMERCIAL) | AD16: 0000000116 | AE16: C | AF16: P | AG16: 0 | AH16: 41716 | AJ16: A | AK16: =COUNTIF($A$3:A$917,A16) -> 1
A17: 3101590004 | B17: GMG COMERCIAL COSTA RICA SOCIEDAD ANONIMA | F17: 83386185 | H17: gmgcr91@grupomonge.com | I17: ABARROTES | J17: MONGE TILARAN | K17: 3101037575 | L17: ZONA LIBRE GUANACASTECA SOCIEDAD ANONIMA | M17: N | N17: 6690136 | R17: 00008073 | S17: 0 | T17: 0 | U17: 000 | V17: 5 | W17: 08 | X17: 01 | AC17: COSTADO SUR DEL PARQUE DE TILARAN | AD17: 0000001182 | AE17: C | AF17: P | AG17: 0 | AH17: 44307 | AJ17: A | AK17: =COUNTIF($A$3:A$917,A17) -> 3
A18: 204400422 | B18: JORGE ANTONIO HERRERA LOPEZ | F18: 87493502 | G18: 26955911 | H18: jorgeherreralopez68@gmail.com | I18: ABARROTES | J18: PULPERIA RIO CHIQUITO | K18: 500850246 | L18: MIREYA CLAUDINA DEL CARMEN LOPEZ ORTIZ | M18: N | N18: 83566527 | R18: 00900150 | S18: 0 | T18: 0 | U18: 000 | V18: 5 | W18: 08 | X18: 01 | AC18: 50M O ESCUELA RIO CHIQUITO TILARAN GTE | AD18: 0000001180 | AE18: C | AF18: P | AG18: 0 | AH18: 44300 | AJ18: A | AK18: =COUNTIF($A$3:A$917,A18) -> 1
A19: 503130961 | B19: KAROL DE LOS ANGELES MURILLO PICADO | F19: 83177021 | G19: 83177021 | H19: gjsiro@hotmail.com | I19: ABARROTES | J19: LA PULPERIA DE KAROL | K19: 3014042110 | L19: MUNICIPALIDAD DE TILARAN | M19: N | R19: 00053727 | S19: 0 | T19: 0 | U19: 000 | V19: 5 | W19: 08 | X19: 01 | AC19: MERCADO MUNICIPAL | AD19: 0000001987 | AE19: C | AF19: P | AG19: 0 | AH19: 45442 | AJ19: A | AK19: =COUNTIF($A$3:A$917,A19) -> 2
A20: 503840564 | B20: LUIS FERNANDO VILLALOBOS HERNANDEZ | F20: 87514783 | G20: 87514783 | H20: lvillaloboshernandez553@gmail.com | I20: ABARROTES | J20: PULPERÍA MARITA | K20: 502470608 | L20: FLOR IVETH DE LOS ANGELES HERNANDEZ FONSECA | M20: N | N20: 87212086 | P20: maritavh18@hotmail.com | R20: 00094445 | S20: 0 | T20: 0 | U20: 000 | V20: 5 | W20: 08 | X20: 01 | AC20: 25 M SUR QUEBRADA LA CABRA TILARA GTE | AD20: 0000002180 | AE20: C | AF20: P | AG20: 0 | AH20: 45848 | AJ20: A | AK20: =COUNTIF($A$3:A$917,A20) -> 1
A21: 504080854 | B21: MARIA FERNANDA PICADO BLANCO | F21: 71560174 | G21: 71560174 | H21: fer.picado9626@gmail.com | I21: ABARROTES | J21: PULPERIA JAAKOV | K21: 501930766 | L21: JORGE EDUARDO PICADO GONZALEZ | M21: N | N21: 60505906 | O21: 60505906 | P21: picadogonzalezjorge@gmail.com | R21: 00088227 | S21: 0 | T21: 0 | U21: 000 | V21: 5 | W21: 08 | X21: 01 | AC21: 700 ESTE 100 NORTE ESTADIO MUNICIPAL TILARAN | AD21: 0000002108 | AE21: C | AF21: P | AG21: 0 | AH21: 45702 | AJ21: A | AK21: =COUNTIF($A$3:A$917,A21) -> 1
A22: 400930671 | B22: MELITINA LUZ MARINA SEQUEIRA RODRIGUEZ | F22: 88288355 | G22: 88288355 | H22: vianeyelizondosequeira@gmail.com | I22: ABARROTES | J22: EL BUEN PRECIO | K22: 400930671 | L22: MELITINA LUZ MARINA SEQUEIRA RODRIGUEZ | M22: N | N22: 88288355 | O22: 88288355 | P22: vianeyelizondosequeira@gmail.com | R22: 00055512 | S22: 0 | T22: 0 | U22: 000 | V22: 5 | W22: 08 | X22: 07 | AC22: PULP BUEN PRECIO | AD22: 0000000149 | AE22: C | AF22: P | AG22: 0 | AH22: 36538 | AJ22: A | AK22: =COUNTIF($A$3:A$917,A22) -> 1
A23: 102830105 | B23: MISAEL FERNANDEZ ARGUEDAS | F23: 88263072 | G23: 88263072 | H23: misael.fernandez.a@outlook.com | I23: ABARROTES | J23: PULPERIA LA CONFIANZA | K23: 102830105 | L23: MISAEL FERNANDEZ ARGUEDAS | M23: N | N23: 88263072 | O23: 88263072 | P23: misael.fernandez.a@outlook.com | R23: 00115670 | S23: 0 | T23: 0 | U23: 000 | V23: 5 | W23: 08 | X23: 01 | AC23: 300 MTS SUR DEL BANCO DE COSTA RICA. | AD23: 0000000002 | AE23: C | AF23: P | AG23: 0 | AH23: 36544 | AJ23: A | AK23: =COUNTIF($A$3:A$917,A23) -> 1
A24: 502000255 | B24: OLGER ENRIQUE DEL CARMEN RODRIGUEZ MENDEZ | F24: 85203862 | H24: olger1124@gmail.com | I24: ABARROTES | J24: "ABASTECEDOR DIOS ES FIEL" | K24: 502000255 | L24: OLGER ENRIQUE DEL CARMEN RODRIGUEZ MENDEZ | M24: N | N24: 85203862 | P24: olger1124@gmail.com | R24: 00106824 | S24: 0 | T24: 0 | U24: 000 | V24: 5 | W24: 08 | X24: 03 | AC24: LAS PALMAS TRONADORA "ABASTECEDOR DIOS ES FIEL" | AD24: 0000000272 | AE24: C | AF24: P | AG24: 0 | AH24: 41548 | AJ24: A | AK24: =COUNTIF($A$3:A$917,A24) -> 1
A25: 504090023 | B25: PRISCILLA MARIA VILLEGAS JIMENEZ | F25: 86373489 | H25: prismaria1996@hotmail.com | I25: ABARROTES | J25: AZUKEP | K25: 502400197 | L25: ZULAY GERARDINA DE LOS ANGELES JIMENEZ SALAZAR | M25: N | N25: 86088966 | O25: 62616032 | R25: 00082211 | S25: 0 | T25: 0 | U25: 000 | V25: 5 | W25: 08 | X25: 02 | AC25: FRENTE A LA ESCUELA DE LAS NUBES | AD25: 0000001253 | AE25: C | AF25: P | AG25: 0 | AH25: 44454 | AJ25: A | AK25: =COUNTIF($A$3:A$917,A25) -> 1
A26: 204810525 | B26: ROSIBEL GERARDO CRUZ JIMENEZ | F26: 88247872 | G26: 26921174 | H26: yaricr84@hotmail.com | I26: ABARROTES | J26: PULPERIA CLAUDIO | K26: 502490456 | L26: JORGE ALFREDO RUIZ CORDOBA | M26: N | N26: 85292620 | P26: jorgeruizcor68@gmail.com | R26: 00125941 | S26: 0 | T26: 0 | U26: 000 | V26: 5 | W26: 08 | X26: 06 | AC26: 100M O 15M S IGLESIA CATOLICA TIERRA MORENAS TILARAN GTE | AD26: 0000000114 | AE26: C | AF26: P | AG26: 0 | AH26: 43178 | AJ26: A | AK26: =COUNTIF($A$3:A$917,A26) -> 1
A27: 3102898199 | B27: NUCLEO DE SERVICIOS CREATIVOS INTELIGENTES SOCIEDA | C27: JOSE CARLOS SEQUEIRA SEQUEIRA | D27: 503970813 | E27: 1 | F27: 83028219 | H27: jocarucr@gmail.com | I27: ACTIVIDADES DE CONSULTORIA EN GESTION | J27: GESTIONA: ESTRATEGIA Y PROYECTOS | N27: 89966996 | AD27: 0000002256 | AE27: C | AF27: P | AG27: 0 | AH27: 45974 | AJ27: A | AK27: =COUNTIF($A$3:A$917,A27) -> 3
A28: 112870620 | B28: ANDREA DE LOS ANGELES CHAN VIQUEZ | F28: 83262701 | G28: 83262701 | H28: campingazucar@gmail.com | I28: ACTIVIDADES TURISTICAS | J28: CAMPING Y MIRADOR MONTAÑA DE AZUCAR | K28: 800440515 | L28: IOK IO CHAN WONG | M28: N | N28: 88902455 | O28: 88902455 | P28: iokiochanwong@gmail.com | R28: 00016126 | S28: 0 | T28: 0 | U28: 000 | V28: 5 | W28: 08 | X28: 07 | AC28: 11800M E SECUELA UNION DE ARENAL | AD28: 0000000920 | AE28: C | AF28: P | AG28: 6948 | AH28: 43845 | AJ28: A | AK28: =COUNTIF($A$3:A$917,A28) -> 2
A29: 3002257283 | B29: ASOCIACION ADMINISTRADORA DE LA PRODUCCION AGRICOL | F29: 88555876 | G29: 88555876 | H29: cordobaavarcafrancisco@gmail.com | I29: ACTIVIDADES TURISTICAS | J29: PROYECTO ECOTURISTICO EL JILGUERO | K29: 2100042014 | L29: ESTADO MINISTERIO DE AMBIENTE Y ENERGIA | M29: N | R29: 00068046 | S29: 0 | T29: 0 | U29: 000 | V29: 5 | W29: 08 | X29: 06 | AC29: 750M N Y 2600M E DEL ANTIGUO RECIBIDOR DE CAFETIERRAS MOREN | AD29: 0000001110 | AE29: C | AF29: P | AG29: 0 | AH29: 44209 | AJ29: A | AK29: =COUNTIF($A$3:A$917,A29) -> 1
A30: 3101650234 | B30: AVENTURAS PARADICE PARK SOCIEDAD ANONIMA | C30: MAURICIO VARGAS RODRIGUEZ | D30: 602960548 | E30: 1 | F30: 88281809 | I30: ACTIVIDADES TURISTICAS | J30: AVENTURA PARADICE PARK S.A | N30: 83144435 | AD30: 0000000741 | AE30: C | AF30: P | AG30: 0 | AH30: 42969 | AJ30: A | AK30: =COUNTIF($A$3:A$917,A30) -> 1
A31: 501370730 | B31: CARLOS ENRIQUE DE JESUS SIRIAS ARIAS | F31: 87898617 | H31: ca9595395@gmail.com | I31: ACTIVIDADES TURISTICAS | J31: Finca La Colina | K31: 502980830 | L31: CARLOS ANTONIO ARIAS LOPEZ | M31: N | R31: 00122526 | S31: 0 | T31: 0 | U31: 000 | V31: 5 | W31: 08 | X31: 02 | AC31: De la Iglesia Católica, 1KM al sur, Quebrada Grande. | AD31: 0000001794 | AE31: C | AF31: P | AG31: 0 | AH31: 45176 | AJ31: A | AK31: =COUNTIF($A$3:A$917,A31) -> 1
A32: 3102645082 | B32: CHILCOUT TRAIL SOCIEDAD DE RESPONSABILIDAD LIMITAD | F32: 85714518 | G32: 26944667 | H32: bret@crparaiso.com | I32: ACTIVIDADES TURISTICAS | J32: CR PARAISO | K32: 3102645085 | L32: KELLY VALLEY PROPERTY SOCIEDAD DE RESPONSABILIDAD | M32: N | N32: 85714518 | O32: 26944750 | R32: 00050948 | S32: 0 | T32: 0 | U32: 000 | V32: 5 | W32: 08 | X32: 07 | AC32: 2KM.NORESTE DEL PUENTE DOS BOCAS N.ARENAL TILARAN | AD32: 0000000793 | AE32: C | AF32: P | AG32: 0 | AH32: 43672 | AJ32: A | AK32: =COUNTIF($A$3:A$917,A32) -> 1
A33: 3101864092 | B33: CUATRO Y UNO CINCO SOCIEDAD ANONIMA | F33: 88393764 | G33: 40007283 | H33: pablo@grupo415.com | I33: ACTIVIDADES TURISTICAS | J33: TREETOPIA PARK | K33: 3101864092 | L33: CUATRO Y UNO CINCO SOCIEDAD ANONIMA | M33: N | N33: 88393764 | O33: 40007283 | P33: pablo@grupo415.com | R33: 00010691 | S33: 0 | T33: 0 | U33: 000 | V33: 5 | W33: 08 | X33: 08 | AC33: 1.5 km noroeste del cruce entre Santa Elena y Las Nubes, San Gerardo. | AD33: 0000001663 | AE33: C | AF33: P | AG33: 0 | AH33: 44966 | AJ33: A | AK33: =COUNTIF($A$3:A$917,A33) -> 1
A34: 3008071089 | B34: JUNTA ADMINISTRATIVA COLEGIO TEC.AGROPECUARIO DE S | F34: 83030035 | G34: 26455390 | H34: 3008071089@junta.mep.go.cr | I34: ACTIVIDADES TURISTICAS | J34: RESERVA BOSQUE NUBOSO SANTA ELENA | K34: 2000045522 | L34: EL ESTADO | M34: E | N34: 85238964 | O34: 26958490 | R34: 00012833 | S34: 0 | T34: 0 | U34: 000 | V34: 5 | W34: 08 | X34: 03 | AC34: OFICINAS COLEGIO TECNICO AGROPECUARIO DE SANTA ELENA | AD34: 0000001089 | AE34: C | AF34: P | AG34: 43183 | AH34: 44167 | AJ34: A | AK34: =COUNTIF($A$3:A$917,A34) -> 3
A35: 504670767 | B35: MAYI ALEXANDRA NUÑEZ ARIAS | F35: 86928203 | H35: nunezmayi4@gmail.com | I35: ACTIVIDADES TURISTICAS | J35: CATARATAS & SENDEROS VIENTO FRESCO | K35: 3101861319 | L35: SENDEROS VIENTO FRESCO SOCIEDAD ANONIMA | M35: N | N35: 88683134 | O35: 22006836 | P35: jsalas1511@hotmail.com | R35: 00124425 | S35: 0 | T35: 0 | U35: 000 | V35: 5 | W35: 08 | X35: 02 | AC35: COSTADO N QDA LAS VUELTAS QDA GRANDE | AD35: 0000002055 | AE35: C | AF35: P | AG35: 0 | AH35: 45581 | AJ35: A | AK35: =COUNTIF($A$3:A$917,A35) -> 1
A36: 3101476392 | B36: PUENTES COLGANTES AVENTURA DE MONTEVERDE SOCIEDAD | F36: 83567601 | G36: 83567601 | H36: puentesaventura@hotmail.con | I36: ACTIVIDADES TURISTICAS | J36: PUENTES AVENTURA | K36: 203500079 | L36: CARLOS ALBERTO VARGAS RODRIGUEZ | M36: N | N36: 83567601 | O36: 26456413 | P36: puentesaventura@hotmail.com | R36: 00110846 | S36: 0 | T36: 0 | U36: 000 | V36: 5 | W36: 08 | X36: 02 | AC36: 1 KM NOROESTE DEL CANOPY AVENTURA, SAN BOSCO | AD36: 0000001158 | AE36: C | AF36: P | AG36: 0 | AH36: 44280 | AJ36: A | AK36: =COUNTIF($A$3:A$917,A36) -> 1
A37: 501850267 | B37: RAFAEL ANGEL DE GERARDO ARGUEDAS VILLALOBOS | F37: 85305414 | H37: arguedasrafaspc@gmail.com | I37: ACTIVIDADES TURISTICAS | J37: CATARATAS LA ROCA | K37: 3101226773 | L37: GANADERA MONGE ARIAS SOCIEDAD ANONIMA | M37: N | N37: 88664311 | O37: 88664311 | P37: monge.roger05@gmail.com | R37: 00140884 | S37: 0 | T37: 0 | U37: 000 | V37: 5 | W37: 08 | X37: 02 | AC37: 200 M NORTE Y 700 M OESTE DE LA IGLESIA CATOLICA, EL DOS, CABECERAS. | AD37: 0000001903 | AE37: C | AF37: P | AG37: 0 | AH37: 45334 | AJ37: A | AK37: =COUNTIF($A$3:A$917,A37) -> 3
A38: 501850267 | B38: RAFAEL ANGEL DE GERARDO ARGUEDAS VILLALOBOS | F38: 85305414 | H38: arguedasrafaspc@gmail.com | I38: ACTIVIDADES TURISTICAS | J38: DESLIZADOR ARCOIRIS | K38: 502010070 | L38: MARIA ISABEL ARGUEDAS VILLALOBOS | M38: N | N38: 84304418 | O38: 84304418 | P38: maria63isa@gmail.com | R38: 00247587 | S38: 0 | T38: 0 | U38: 000 | V38: 5 | W38: 08 | X38: 02 | AC38: 500 M NORTE DE LA IGLESIA DE LA FLORIDA, QUEBRADA GRANDE | AD38: 0000002047 | AE38: C | AF38: P | AG38: 0 | AH38: 45566 | AJ38: A | AK38: =COUNTIF($A$3:A$917,A38) -> 3
A39: 3102768312 | B39: RUTAS ANCESTRALES MONTEVERDE SOCIEDAD DE RESPONSAB | C39: HEIDY MARIA PEREZ BRAVO | D39: 503300655 | E39: 1 | F39: 84731414 | H39: hp115892@gmail.com | I39: ACTIVIDADES TURISTICAS | J39: RUTAS ANCESTRALES MONTEVERDE | K39: 501650284 | L39: MARTIN AURELIO RODRIGUEZ PEREZ | M39: N | N39: 86583937 | O39: 84108382 | P39: maurenr2311@gmail.com | R39: 00113908 | S39: 0 | T39: 0 | U39: 000 | V39: 5 | W39: 08 | X39: 08 | AC39: 50M.NORTE DE LA ESCUELA DE LAS NUBES | AD39: 0000000806 | AE39: C | AF39: P | AG39: 25859 | AH39: 43419 | AJ39: A | AK39: =COUNTIF($A$3:A$917,A39) -> 3
A40: 504250794 | B40: SABRINA GARCIA RODRIGUEZ | F40: 83201864 | H40: catarataelahora.cr@gmail.com | I40: ACTIVIDADES TURISTICAS | J40: Catarata El Ahora | K40: 501940197 | L40: EDWIN DE JESUS GARCIA CASTILLO | M40: N | N40: 89863179 | R40: 00007262 | S40: 0 | T40: 0 | U40: 000 | V40: 5 | W40: 08 | X40: 05 | AC40: DE LA IGLESIA CATOLICA LIBANO 1.5 KM AL SUR | AD40: 0000001899 | AE40: C | AF40: P | AG40: 0 | AH40: 45329 | AJ40: A | AK40: =COUNTIF($A$3:A$917,A40) -> 1
A41: 3101377358 | B41: SELVATURA PARK DE COSTA RICA SOCIEDAD ANONIMA | F41: 86342664 | H41: conta04@corporacioncsb.com | I41: ACTIVIDADES TURISTICAS | J41: SELVATURA PARK DE COSTA RICA | K41: 4000001021 | L41: BANCO NACIONAL DE COSTA RICA | M41: N | N41: 22122000 | O41: 22122225 | P41: municipalbn@bncr.fi.cr | R41: 00013613 | S41: 0 | T41: 0 | U41: 000 | V41: 5 | W41: 08 | X41: 08 | AC41: 2KM.NORTE DE LA ESCUELA DE SANTA ELENA | AD41: 0000000697 | AE41: C | AF41: P | AG41: 1769250.8 | AH41: 41709 | AJ41: A | AK41: =COUNTIF($A$3:A$917,A41) -> 1
A42: 3102719670 | B42: TLV BALANCED LIFE SOCIEDAD DE RESPONSABILIDAD LIMI | F42: 85164510 | H42: sally.nilsson@outlook.com | I42: ACTIVIDADES TURISTICAS | J42: TULA VIDA | K42: 3102837283 | L42: GRUPO TULA VIDA HORSES SOCIEDAD DE RESPONSABILIDAD | M42: N | N42: 85164510 | P42: sally.nilsson@outlook.com | R42: 00110559 | S42: 0 | T42: 0 | U42: 000 | V42: 5 | W42: 08 | X42: 06 | AC42: 3 KM NORTE DEL RECIBIDOR DE CAFÉ | AD42: 0000002150 | AE42: C | AF42: P | AG42: 0 | AH42: 45806 | AJ42: A | AK42: =COUNTIF($A$3:A$917,A42) -> 2
A43: 503930560 | B43: JOSELYN KARINA RAMIREZ CASTRO | F43: 83807395 | H43: joselynr333@gmail.com | I43: ACUARIO | J43: ACUABLUE | K43: 3101352083 | L43: INVESTMENT RUNNER ACU SOCIEDAD ANONIMA | M43: N | N43: 88288710 | O43: 88288710 | P43: alonsocamposu@gmail.com | R43: 00245036 | S43: 0 | T43: 0 | U43: 000 | V43: 5 | W43: 08 | X43: 01 | AC43: 50 M NORTE DE LA GUARDIA RURAL, TILARAN. | AD43: 0000002231 | AE43: C | AF43: P | AG43: 0 | AH43: 45938 | AJ43: A | AK43: =COUNTIF($A$3:A$917,A43) -> 1
A44: 503380978 | B44: ELVIN ELI VILLALOBOS NOVO | F44: 83040866 | G44: 83040866 | H44: sardinabikes@hotmail.com | I44: AGEN Y REPARAC.BICICLETA | J44: "SARDINA BIKE | K44: 503570575 | L44: LIZA MARIA BONICHE HERRERA | M44: N | N44: 83040866 | O44: 83040866 | P44: lizaboniche_7@hotmail.com | R44: 00012324 | S44: 0 | T44: 0 | U44: 000 | V44: 5 | W44: 08 | X44: 01 | AC44: 100 M ESTE DEL BANCO DE COSTA RICA, TILARAN | AD44: 0000000427 | AE44: C | AF44: P | AG44: 19886 | AH44: 41982 | AJ44: A | AK44: =COUNTIF($A$3:A$917,A44) -> 1
A45: 117690764 | B45: ROBERT ALVARADO ARIAS | F45: 83431050 | H45: raa11769@gmail.com | I45: AGEN Y REPARAC.BICICLETA | J45: CICLO ALVARADO | K45: 500770987 | L45: EDDIE DE JESUS ALVARADO HERRERA | M45: N | N45: 87077836 | O45: 88820400 | P45: rav174r@gmail.com | R45: 00022942 | S45: 0 | T45: 0 | U45: 000 | V45: 5 | W45: 08 | X45: 01 | AC45: 40 MTS NORTE DE LA CRUZ ROJA | AD45: 0000001293 | AE45: C | AF45: P | AG45: 0 | AH45: 44547 | AJ45: A | AK45: =COUNTIF($A$3:A$917,A45) -> 2
A46: 502660456 | B46: ANNIA FRESIA MEDINA GOMEZ | F46: 88972949 | G46: 88972949 | H46: oscarsc16@hotmail.com | I46: AGENCIA DE EQUIPO AGRICOLA | J46: AGENCIA HUSQVARNA TILARAN | K46: 800810688 | L46: AURA PATRICIA ASCENCIO SILVA | M46: N | N46: 83948668 | O46: 83948668 | P46: apascencio@hotmail.com | R46: 00006233 | S46: 0 | T46: 0 | U46: 000 | V46: 5 | W46: 08 | X46: 01 | AC46: COSTADO OESTE DEL GIMNASIO MUNICIPAL | AD46: 0000001623 | AE46: C | AF46: P | AG46: 0 | AH46: 44887 | AJ46: A | AK46: =COUNTIF($A$3:A$917,A46) -> 1
A47: 3105849960 | B47: EQUIPOS AGROFORESTALES CAÑAS EMPRESA INDIVIDUAL DE | F47: 61961980 | G47: 61961980 | H47: eforestales.tilaran@gmail.com | I47: AGENCIA DE EQUIPO AGRICOLA | J47: Equipos Agroforestales Tilarán | K47: 600480988 | L47: ALEJANDRO GONZALEZ VILLEGAS | M47: N | N47: 70244482 | P47: zego03@gmail.com | R47: 00018029 | S47: 0 | T47: 0 | U47: 000 | V47: 5 | W47: 08 | X47: 01 | AC47: 75 NORTE DEL MERCADO MUNICIPAL | AD47: 0000001738 | AE47: C | AF47: P | AG47: 0 | AH47: 45104 | AJ47: A | AK47: =COUNTIF($A$3:A$917,A47) -> 1
A48: 106170094 | B48: ISABEL CRISTINA DE LOS ANGELES ROJAS SIRIAS | F48: 89947698 | G48: 89947698 | H48: isabelrosi60@gmail.com | I48: AGENCIA DE EQUIPO AGRICOLA | J48: Multi Agri | K48: 106170094 | L48: ISABEL CRISTINA DE LOS ANGELES ROJAS SIRIAS | M48: N | N48: 89947698 | O48: 89947698 | P48: isabelrosi60@gmail.com | R48: 00009977 | S48: 0 | T48: 0 | U48: 000 | V48: 5 | W48: 08 | X48: 01 | AC48: 100 M NORTE Y 65 ESTE DE LA CATEDRAL | AD48: 0000002028 | AE48: C | AF48: P | AG48: 0 | AH48: 45539 | AJ48: A | AK48: =COUNTIF($A$3:A$917,A48) -> 1
A49: 503540977 | B49: CARLOS ENRIQUE SOLORZANO ARIAS | F49: 87132488 | G49: 26958163 | H49: carlosen1986@hotmail.com | I49: AGENCIA DE PINTURAS | J49: "PINTURAS TOPO" | K49: 202850977 | L49: CARLOS MANUEL SOLORZANO MOSCOSO | M49: N | N49: 85230464 | O49: 85230464 | P49: notienecorreo@gmail.com | R49: 00056188 | S49: 0 | T49: 0 | U49: 000 | V49: 5 | W49: 08 | X49: 01 | AC49: 200 M NORTE DE LA GASOLINERA TILARAN, URBANIZACION LINDA VISTA, TILARAN. | AD49: 0000000447 | AE49: C | AF49: P | AG49: 0 | AH49: 42068 | AJ49: A | AK49: =COUNTIF($A$3:A$917,A49) -> 1
A50: 3101636442 | B50: LAMINAS Y PINTURAS ARIAS VEGA SOCIEDAD ANONIMA | F50: 88226125 | H50: pinturastegal2@gmail.com | I50: AGENCIA DE PINTURAS | J50: PINTURAS TEGAL | K50: 3101636442 | L50: LAMINAS Y PINTURAS ARIAS VEGA SOCIEDAD ANONIMA | M50: N | N50: 88226125 | P50: pinturastegal2@gmail.com | R50: 00186745 | S50: 0 | T50: 0 | U50: 000 | V50: 5 | W50: 08 | X50: 01 | AC50: 850M N DE LA BOMBA JSM CAMINO A ARENAL | AD50: 0000000735 | AE50: C | AF50: P | AG50: 0 | AH50: 43788 | AJ50: A | AK50: =COUNTIF($A$3:A$917,A50) -> 1
A51: 502110414 | B51: MARIO ENRIQUE LACAYO PANIAGUA | F51: 83999575 | G51: 26955141 | H51: lacayomasis@gmail.com | I51: AGENCIA DE PINTURAS | J51: CENTRO DE COLOR TILARAN. | K51: 3101192871 | L51: DESARROLLOS EMPRESARIALES LAMA DEL NORTE SOCIEDAD | M51: N | N51: 83999575 | P51: lacayomasis@gmail.com | R51: 00006639 | S51: 0 | T51: 0 | U51: 000 | V51: 5 | W51: 08 | X51: 01 | AC51: 30M S DE LA CRUZ ROJA | AD51: 0000000285 | AE51: C | AF51: P | AG51: 0 | AH51: 36599 | AJ51: A | AK51: =COUNTIF($A$3:A$917,A51) -> 1
A52: 206540192 | B52: GERSON MENDIOLA ELIZONDO | F52: 61524791 | G52: 47019454 | H52: gersonmendio@gmail.com | I52: AGENCIA DE REPUESTOS | J52: ALTURA CAR CENTER | K52: 3101558230 | L52: LA CHOZA DEL MAIZ SOCIEDAD ANONIMA | M52: N | N52: 84882101 | O52: 84882101 | P52: jgatrell@gmail.com | R52: 00260195 | S52: 0 | T52: 0 | U52: 000 | V52: 5 | W52: 08 | X52: 01 | AC52: 100 MTS ESTE DE LA ESCUELA DE SAN LUIS DE TILARAN | AD52: 0000001873 | AE52: C | AF52: P | AG52: 0 | AH52: 45279 | AJ52: A | AK52: =COUNTIF($A$3:A$917,A52) -> 2
A53: 503000872 | B53: GISSELLE RODRIGUEZ PICADO | F53: 85846331 | H53: gr1334797@gmail.com | I53: AGENCIA DE REPUESTOS | J53: Motorepuestos San Miguel | K53: 503000872 | L53: GISSELLE RODRIGUEZ PICADO | M53: N | N53: 85846331 | P53: gr1334797@gmail.com | R53: 00060140 | S53: 0 | T53: 0 | U53: 000 | V53: 5 | W53: 08 | X53: 02 | AC53: 100M E DE LA ESCUELA DE SAN MIGUEL | AD53: 0000001877 | AE53: C | AF53: P | AG53: 0 | AH53: 45300 | AJ53: A | AK53: =COUNTIF($A$3:A$917,A53) -> 2
A54: 110690145 | B54: GUSTAVO ADOLFO ZAMORA ALVAREZ | F54: 88456197 | G54: 88456197 | H54: reptavotilaran@hotmail.com | I54: AGENCIA DE REPUESTOS | J54: "REPUESTOS TAVO" | K54: 110690145 | L54: GUSTAVO ADOLFO ZAMORA ALVAREZ | M54: N | N54: 88456197 | O54: 88456197 | P54: reptavotilaran@hotmail.com | R54: 00006203 | S54: 0 | T54: 0 | U54: 000 | V54: 5 | W54: 08 | X54: 01 | AC54: 100 M NORTE DE LA CRUZ ROJA DE TILARAN | AD54: 0000000052 | AE54: C | AF54: P | AG54: 0 | AH54: 39345 | AJ54: A | AK54: =COUNTIF($A$3:A$917,A54) -> 1
A55: 604130192 | B55: JOHNNY STEVE GONZALEZ CAMPOS | G55: 61057060 | H55: johnnymt60413@gmail.com | I55: AGENCIA DE REPUESTOS | J55: ON TURIN | K55: 503830311 | L55: LUIS MIGUEL CHAVES PICADO | M55: N | N55: 72327426 | O55: 72327426 | P55: grupoonccrg@gmail.com | R55: 00069300 | S55: 0 | T55: 0 | U55: 000 | V55: 5 | W55: 08 | X55: 02 | AC55: 25M S DE LA IGLESIA DE TURIN | AD55: 0000001001 | AE55: C | AF55: P | AG55: 0 | AH55: 44035 | AJ55: A | AK55: =COUNTIF($A$3:A$917,A55) -> 2
A56: 112040116 | B56: JOSE JOAQUIN PAYNE MONESTEL | F56: 60779332 | G56: 26958480 | H56: polar.automotrizcr@gmail.com | I56: AGENCIA DE REPUESTOS | J56: Polar Aire Acondicionado Automotriz | K56: 104530291 | L56: LIGIA MARIA MONESTEL MONTOYA | M56: N | N56: 88950123 | O56: 88950123 | P56: kasaligia@gmail.com | R56: 00254957 | S56: 0 | T56: 0 | U56: 000 | V56: 5 | W56: 08 | X56: 01 | AC56: 35 M SUR DE LA GUARDIA RURAL, TILARAN. | AD56: 0000002101 | AE56: C | AF56: P | AG56: 0 | AH56: 45694 | AJ56: A | AK56: =COUNTIF($A$3:A$917,A56) -> 1
A57: 107740967 | B57: OSCAR ALBERTO SALAS LOPEZ | F57: 83328602 | G57: 26955121 | H57: oscarsalas89@hotmail.com | I57: AGENCIA DE REPUESTOS | J57: REPUESTOS LA BODEGUITA | K57: 107740967 | L57: OSCAR ALBERTO SALAS LOPEZ | M57: N | N57: 83328602 | O57: 26955121 | P57: oscarsalas89@hotmail.com | R57: 00039048 | S57: 0 | T57: 0 | U57: 000 | V57: 5 | W57: 08 | X57: 01 | AC57: 75 M SUR DEL MAG | AD57: 0000000027 | AE57: C | AF57: P | AG57: 0 | AH57: 36616 | AJ57: A | AK57: =COUNTIF($A$3:A$917,A57) -> 1
A58: 502390899 | B58: RAFAEL ANTONIO PEREZ ELIZONDO | F58: 88235538 | G58: 88235538 | H58: transperezeli@gmail.com | I58: AGENCIA DE REPUESTOS | J58: SERVICENTRO V ESQUINAS | K58: 3101594400 | L58: GANADERIA HERMANOS PEREZ ALFARO SOCIEDAD ANONIMA | M58: N | N58: 88235538 | P58: transperezeli@gmail.com | R58: 00077164 | S58: 0 | T58: 0 | U58: 000 | V58: 5 | W58: 08 | X58: 01 | AC58: 350 MTS SUR DE SERVICENTRO EL LAGO | AD58: 0000001305 | AE58: C | AF58: P | AG58: 0 | AH58: 44587 | AJ58: A | AK58: =COUNTIF($A$3:A$917,A58) -> 2
A59: 503900876 | B59: ROYVIN OBANDO CARVAJAL | F59: 87311887 | G59: 87311887 | H59: repuestosnuevoarenal@gmail.com | I59: AGENCIA DE REPUESTOS | J59: Repuestos Nuevo Arenal | K59: 204370329 | L59: JOSE ANGEL OBANDO VALVERDE | M59: N | N59: 88176375 | O59: 88176375 | P59: fejoseangelito2010@gmail.com | R59: 00131818 | S59: 0 | T59: 0 | U59: 000 | V59: 5 | W59: 08 | X59: 07 | AC59: DIAGONAL AL GIMNASIO, ARENAL. | AD59: 0000001656 | AE59: C | AF59: P | AG59: 0 | AH59: 44927 | AJ59: A | AK59: =COUNTIF($A$3:A$917,A59) -> 1
A60: 3101169230 | B60: TECNI REPUESTOS TILARAN SOCIEDAD ANONIMA | F60: 88353896 | G60: 26955837 | H60: hondatilaran@gmail.com | I60: AGENCIA DE REPUESTOS | J60: TECNI REPUESTOS TILARAN | K60: 3101169230 | L60: TECNI REPUESTOS TILARAN SOCIEDAD ANONIMA | M60: N | N60: 88353896 | O60: 26955837 | P60: hondatilaran@gmail.com | R60: 00070317 | S60: 0 | T60: 0 | U60: 000 | V60: 5 | W60: 08 | X60: 01 | AC60: 185 MTS NORTE DEL MERCADO | AD60: 0000001441 | AE60: C | AF60: P | AG60: 0 | AH60: 44798 | AJ60: A | AK60: =COUNTIF($A$3:A$917,A60) -> 1
A61: 504670162 | B61: YADER DANIEL ORDOÑEZ GARCIA | F61: 64153183 | G61: 64153183 | H61: yadergarcia230g@gmail.com | I61: AGENCIA DE REPUESTOS | J61: ACCESORIOS Y REPUESTOS ULATE | K61: 502560573 | L61: DAUBE MIGUEL MURILLO NUÑEZ | M61: N | N61: 88111079 | O61: 26954896 | P61: dauve.1969@gmail.com | R61: 00038883 | S61: 0 | T61: 0 | U61: 000 | V61: 5 | W61: 08 | X61: 01 | AC61: 50 MTS SUR DE OFICINAS AYA TILARAN | AD61: 0000002267 | AE61: C | AF61: P | AG61: 0 | AH61: 45993 | AJ61: A | AK61: =COUNTIF($A$3:A$917,A61) -> 1
A62: 602670136 | B62: JULIO CESAR VILLALOBOS MORALES | F62: 88706657 | H62: tallercucatila@gmail.com | I62: AGENCIA Y TALLER DE MOTOCICLETAS | J62: TALLER Y REPUESTOS CUCA | K62: 602670136 | L62: JULIO CESAR VILLALOBOS MORALES | M62: N | N62: 88706657 | P62: tallercucatila@gmail.com | R62: 00195736 | S62: 0 | T62: 0 | U62: 000 | V62: 5 | W62: 08 | X62: 01 | AC62: 100 M SUR Y 25 M OESTE DEL TABERNACULO, TILARAN | AD62: 0000001688 | AE62: C | AF62: P | AG62: 0 | AH62: 45007 | AJ62: A | AK62: =COUNTIF($A$3:A$917,A62) -> 1
A63: 3101761481 | B63: 3-101-761481 SOCIEDAD ANONIMA | C63: MARIA JOSE VARGAS ROJAS | D63: 206970146 | E63: 1 | F63: 88212736 | H63: mariajvarq@outlook.com | I63: ALMACEN.. | J63: US OUTLET | K63: 3101422902 | L63: INVERSIONES PAJIAN DE TILARAN SOCIEDAD ANONIMA | M63: N | N63: 88288710 | O63: 88288710 | P63: alonsocamposu@gmail.com | R63: 00012805 | S63: 0 | T63: 0 | U63: 000 | V63: 5 | W63: 08 | X63: 01 | AC63: COSTADO ESTE DE LA CATEDRAL, TILARÁN | AD63: 0000002007 | AE63: C | AF63: P | AG63: 0 | AH63: 45495 | AJ63: A | AK63: =COUNTIF($A$3:A$917,A63) -> 1
A64: 3101207333 | B64: ALMACEN ZAMORA SOCIEDAD ANONIMA | C64: YARA VANESSA ZAMORA CHACON | D64: 602810495 | E64: 1 | F64: 88193825 | G64: 26954859 | H64: yarazamora1@hotmail.com | I64: ALMACEN.. | J64: ALMACEN SUPER ZAMORA | K64: 503600254 | L64: RAQUEL ALEJANDRA ZAMORA CHACON | M64: N | N64: 87069710 | P64: razach1@hotmail.com | R64: 00262492 | S64: 0 | T64: 0 | U64: 000 | V64: 5 | W64: 08 | X64: 01 | AC64: 100M SUR DE CATEDARL DE TILARAN | AD64: 0000000680 | AE64: C | AF64: P | AG64: 0 | AH64: 36623 | AJ64: A | AK64: =COUNTIF($A$3:A$917,A64) -> 1
A65: 3002377976 | B65: ASOCIACION DE PRODUCTORES DE LECHE DE MONTEVERDE | C65: MARCO ANTONIO ZAMORA ALVAREZ | D65: 502190211 | E65: 1 | F65: 63926747 | G65: 87088410 | H65: mzamora210@hotmail.com | I65: ALMACEN.. | J65: ALMACEN AGRO-FERRETERO APLM | K65: 3002377976 | L65: ASOCIACION DE PRODUCTORES DE LECHE DE MONTEVERDE | M65: N | N65: 63926747 | O65: 85243018 | P65: aplmonteverde@gmail.com | R65: 00216013 | S65: 0 | T65: 0 | U65: 000 | V65: 5 | W65: 08 | X65: 08 | AC65: DIAGONAL AL SALON COMUNAL CABECERAS | AD65: 0000000587 | AE65: C | AF65: P | AG65: 0 | AH65: 42265 | AJ65: A | AK65: =COUNTIF($A$3:A$917,A65) -> 2
A66: 3004045952 | B66: COOPERATIVA DE CAFICULTORES Y SERVICIOS MULTIPLES | C66: LUIS ALEJANDRO GARCIA VILLALOBOS | D66: 503190046 | E66: 1 | F66: 87012075 | H66: alejandro@coopeldos.com | I66: ALMACEN.. | J66: COOP.DE CAFICULTORES Y SER.MULT.CORD.TILARAN RL. | K66: 4000045015 | L66: INSTITUTO NACIONAL DE FOMENTO COOPERATIVO | M66: N | N66: 22562944 | O66: 22562944 | P66: emendez@infocoop.go.cr | R66: 00027811 | S66: A | T66: 0 | U66: 000 | V66: 5 | W66: 08 | X66: 02 | AC66: 200M.NOROESTE DE LA ESCUELA DE EL DOS | AD66: 0000000591 | AE66: C | AF66: P | AG66: 0 | AH66: 36823 | AJ66: A | AK66: =COUNTIF($A$3:A$917,A66) -> 2
A67: 3101268981 | B67: EL COLONO AGROPECUARIO SOCIEDAD ANONIMA | F67: 88603596 | G67: 26955184 | H67: orojas@grupocolono.com | I67: ALMACEN.. | J67: EL COLONO AGROPECUARIO | K67: 3101079006 | L67: BANCO IMPROSA SOCIEDAD ANONIMA | M67: N | N67: 83144435 | O67: 22844000 | P67: FIDImpuestos@grupoimprosa.com | R67: 00006579 | S67: 0 | T67: 0 | U67: 000 | V67: 5 | W67: 08 | X67: 01 | AC67: 50 M OESTE DEL BANCO NACIONAL, TILARÁN | AD67: 0000000668 | AE67: C | AF67: P | AG67: 0 | AH67: 40870 | AJ67: A | AK67: =COUNTIF($A$3:A$917,A67) -> 1
A68: 501360132 | B68: GLORIA DINORAH JIMENEZ SIBAJA | F68: 83631265 | G68: 26955219 | H68: casadelganadero.tilaran@hotmail.com | I68: ALMACEN.. | J68: LA CASA DEL GANADERO | K68: 501360132 | L68: GLORIA DINORAH JIMENEZ SIBAJA | M68: N | N68: 83631265 | O68: 26955219 | P68: casadelganadero.tilaran@hotmail.com | R68: 00006220 | S68: 0 | T68: 0 | U68: 000 | V68: 5 | W68: 08 | X68: 01 | AC68: COSTADO NORTE CATEDRAL DE TILARAN, LA CASA DEL GANADERO. | AD68: 0000000189 | AE68: C | AF68: P | AG68: 69616.5 | AH68: 43294 | AJ68: A | AK68: =COUNTIF($A$3:A$917,A68) -> 1
A69: 117690764 | B69: ROBERT ALVARADO ARIAS | F69: 83431050 | H69: raa11769@gmail.com | I69: ALMACEN.. | J69: NELITA STORE | K69: 500770987 | L69: EDDIE DE JESUS ALVARADO HERRERA | M69: N | N69: 87077836 | O69: 88820400 | P69: rav174r@gmail.com | R69: 00022942 | S69: 0 | T69: 0 | U69: 000 | V69: 5 | W69: 08 | X69: 01 | AC69: 40 MTS NORTE DE LA CRUZ ROJA | AD69: 0000001963 | AE69: C | AF69: P | AG69: 0 | AH69: 45408 | AJ69: A | AK69: =COUNTIF($A$3:A$917,A69) -> 2
A70: 3102886219 | B70: TILARAN BOX SOCIEDAD DE RESPONSABILIDAD LIMITADA | C70: BERNY JOEL SALAS UMAÑA | D70: 503620878 | E70: 1 | F70: 87053358 | G70: 26954919 | H70: bernysalas5@gmail.com | I70: ALMACEN.. | J70: TILA BOX | K70: 3101452679 | L70: TILA SPORT A Y G, SOCIEDAD ANONIMA | M70: N | N70: 88288710 | O70: 88288710 | P70: camposu1975@gmail.com | R70: 00126908 | S70: 0 | T70: 0 | U70: 000 | V70: 5 | W70: 08 | X70: 01 | AC70: 50M SUR DEL BANCO DE COSTA RICA | AD70: 0000001843 | AE70: C | AF70: P | AG70: 0 | AH70: 45240 | AJ70: A | AK70: =COUNTIF($A$3:A$917,A70) -> 1
A71: 3101116146 | B71: VIENTOS DEL GUANACASTE SOCIEDAD ANONIMA | F71: 83832694 | G71: 83832694 | H71: info@ticowind.com | I71: ALQUILER DE ARTICULOS DEPORTIVOS | J71: TICO WIND | K71: 3101156529 | L71: RIO ESCONDIDO SOCIEDAD ANONIMA | M71: N | N71: 83832694 | O71: 83832694 | P71: info@ticowind.com | R71: 00209813 | S71: 0 | T71: 0 | U71: 000 | V71: 5 | W71: 08 | X71: 04 | AC71: 300 M OESTE DE LA ESCUELA PÚBLICA, SABALITO, TIERRAS MORENA | AD71: 0000001378 | AE71: C | AF71: P | AG71: 0 | AH71: 44698 | AJ71: A | AK71: =COUNTIF($A$3:A$917,A71) -> 1
A72: 3101689003 | B72: EL TUCAN DEL ARENAL SOCIEDAD ANONIMA | C72: GILBERTO VARELA MORA | D72: 601340196 | E72: 1 | F72: 83939411 | G72: 83939411 | H72: hotel.mary@yahoo.com | I72: ALQUILER EQUIPO TRANSP VIA ACUATICO | J72: CATAMARAN TOUCAN ARENAL | N72: 88563718 | AD72: 0000000757 | AE72: C | AF72: P | AG72: 0 | AH72: 43591 | AJ72: A | AK72: =COUNTIF($A$3:A$917,A72) -> 1
A73: 503470175 | B73: JEIMY GRACIELA CHAVES SANCHEZ | F73: 89875297 | G73: 89875297 | H73: clubnauticalagoarenal@gmail.com | I73: ALQUILER EQUIPO TRANSP VIA ACUATICO | J73: CLUB NAUTICA LAGO ARENAL | N73: 87077889 | AD73: 0000001692 | AE73: C | AF73: P | AG73: 0 | AH73: 45014 | AJ73: A | AK73: =COUNTIF($A$3:A$917,A73) -> 1
A74: 3102635301 | B74: GTP TORRES CR SOCIEDAD DE RESPONSABILIDAD LIMITADA | F74: 41003540 | H74: contabilidadcostarica@americantower.com | I74: ARRENDA.ANTENAS TELECOMUNI | J74: GTP TORRES CR SRL | N74: 83910269 | AD74: 0000000792 | AE74: C | AF74: P | AG74: 52584.75 | AH74: 42271 | AJ74: A | AK74: =COUNTIF($A$3:A$917,A74) -> 1
A75: 3102559209 | B75: SBA TORRES COSTA RICA LIMITADA | G75: 22883232 | H75: proveedores@sbasite.com | I75: ARRENDA.ANTENAS TELECOMUNI | J75: SBA TORRES COSTA RICA LTDA | K75: 502070524 | L75: MARIA GEOVANNA MEZA LOPEZ | M75: N | N75: 83910269 | O75: 26695070 | P75: gmeza12@gmail.com | R75: 00269316 | S75: 0 | T75: 0 | U75: 000 | V75: 5 | W75: 08 | X75: 01 | AC75: Barrio San Antonio, 50 m. Este, 100 m. Sur y 25 m. Oeste de Mueblería Murillo | AD75: 0000000791 | AE75: C | AF75: P | AG75: 0 | AH75: 40774 | AJ75: A | AK75: =COUNTIF($A$3:A$917,A75) -> 1
A76: 603250919 | B76: NANCY TATIANA VARELA SANCHEZ | F76: 86737167 | H76: fenancyvarela@gmail.com | I76: ARTICULOS DE LUJO | J76: Detallitos | K76: 603250919 | L76: NANCY TATIANA VARELA SANCHEZ | M76: N | N76: 86737167 | P76: fenancyvarela@gmail.com | R76: 00157845 | S76: 0 | T76: 0 | U76: 000 | V76: 5 | W76: 08 | X76: 01 | AC76: 300 MTS NORTE, 300 MTS OESTE DE LA GUARDIA RURAL | AD76: 0000001845 | AE76: C | AF76: P | AG76: 0 | AH76: 45244 | AJ76: A | AK76: =COUNTIF($A$3:A$917,A76) -> 2
A77: 3101665793 | B77: SERVED SOCIEDAD ANONIMA | F77: 85672672 | G77: 26955788 | H77: jptilawa@gmail.com | I77: ARTICULOS DEPORTIVOS | J77: DEPORTIVOS LAKE ARENAL BREWERY | K77: 3102592029 | L77: SECRET POINT LIMITADA | M77: N | N77: 83155234 | O77: 26955050 | P77: jptilawa@gmail.com | R77: 00166127 | S77: 0 | T77: 0 | U77: 000 | V77: 5 | W77: 08 | X77: 04 | AC77: CONTIGUO HOTEL TILAWA, SANTA ROSA. | AD77: 0000000750 | AE77: C | AF77: P | AG77: 0 | AH77: 41558 | AJ77: A | AK77: =COUNTIF($A$3:A$917,A77) -> 7
A78: 501050591 | B78: RAMON ELIAS MENA HERNANDEZ | F78: 88190624 | G78: 88190624 | H78: menaramonspc@gmail.com | I78: ASERRADERO | J78: ASERRADERO TILARÁN | K78: 501050591 | L78: RAMON ELIAS MENA HERNANDEZ | M78: N | N78: 88190624 | O78: 88190624 | P78: menaramonspc@gmail.com | R78: 00133656 | S78: 0 | T78: 0 | U78: 000 | V78: 5 | W78: 08 | X78: 01 | AC78: 1 KM OESTE DEL CEMENTERIO, CAMINO A LIBANO | AD78: 0000000174 | AE78: C | AF78: P | AG78: 20038.5 | AH78: 38288 | AJ78: A | AK78: =COUNTIF($A$3:A$917,A78) -> 2
A79: 3101680765 | B79: ALISIOS HOLDINGS SOCIEDAD ANONIMA | F79: 89303290 | G79: 26699500 | H79: randall.gutierrez@somoscmi.com | I79: ASESORIA MANT. PLANTAS EOLICAS | J79: ALISIOS HOLDING S.A | K79: 3101680765 | L79: ALISIOS HOLDINGS SOCIEDAD ANONIMA | M79: N | N79: 89303290 | O79: 26699500 | P79: randall.gutierrez@somoscmi.com | R79: 00208980 | S79: 0 | T79: 0 | U79: 000 | V79: 5 | W79: 08 | X79: 04 | AC79: 1.5 KM NORTE DEL CRUCE AGUILARES, QDA AZUL, SANTA ROSA | AD79: 0000000755 | AE79: C | AF79: P | AG79: 0 | AH79: 43564 | AJ79: A | AK79: =COUNTIF($A$3:A$917,A79) -> 1
A80: 3101663223 | B80: CR OPERACIONES Y MANTENIMIENTO SOCIEDAD ANONIMA | F80: 89303290 | G80: 26699500 | H80: randall.gutierrez@somoscmi.com | I80: ASESORIA MANT. PLANTAS EOLICAS | J80: CR OPERACIONES | K80: 3101680765 | L80: ALISIOS HOLDINGS SOCIEDAD ANONIMA | M80: N | N80: 89303290 | O80: 26699500 | P80: randall.gutierrez@somoscmi.com | R80: 00208980 | S80: 0 | T80: 0 | U80: 000 | V80: 5 | W80: 08 | X80: 04 | AC80: 1.5 KM NORTE DEL CRUCE AGUILARES, QDA AZUL, SANTA ROSA | AD80: 0000000748 | AE80: C | AF80: P | AG80: 0 | AH80: 41694 | AJ80: A | AK80: =COUNTIF($A$3:A$917,A80) -> 1
A81: 3102794886 | B81: H G & ASOCIADOS TILARAN SOCIEDAD DE RESPONSABILIDA | F81: 84581020 | G81: 88412118 | H81: gherrera@hgwindtec.com | I81: BALNEARIOS | J81: PISCINA PUERTO SAN LUIS | K81: 3101503497 | L81: H G WINDTEC SOCIEDAD ANONIMA | M81: N | N81: 88412118 | O81: 88265388 | P81: gherrera@hgwindtec.com | R81: 00157284 | S81: 0 | T81: 0 | U81: 000 | V81: 5 | W81: 08 | X81: 01 | AC81: HOTEL PUERTO SAN LUIS, TILARAN. | AD81: 0000001190 | AE81: C | AF81: P | AG81: 0 | AH81: 44320 | AJ81: A | AK81: =COUNTIF($A$3:A$917,A81) -> 3
A82: 3101665793 | B82: SERVED SOCIEDAD ANONIMA | F82: 85672672 | G82: 26955788 | H82: jptilawa@gmail.com | I82: BALNEARIOS | J82: BALNEARIO LAKE ARENAL BREWERY | K82: 3102592029 | L82: SECRET POINT LIMITADA | M82: N | N82: 83155234 | O82: 26955050 | P82: jptilawa@gmail.com | R82: 00166127 | S82: 0 | T82: 0 | U82: 000 | V82: 5 | W82: 08 | X82: 04 | AC82: CONTIGUO HOTEL TILAWA, SANTA ROSA. | AD82: 0000001071 | AE82: C | AF82: P | AG82: 0 | AH82: 44127 | AJ82: A | AK82: =COUNTIF($A$3:A$917,A82) -> 7
A83: 503290690 | B83: ANGELICA ELENA DURAN SANTAMARIA | F83: 83130092 | G83: 83130092 | H83: elenangelica07@gmail.com | I83: BAR | J83: CHENY´S | K83: 204400422 | L83: JORGE ANTONIO HERRERA LOPEZ | M83: N | N83: 87493502 | O83: 26955911 | P83: jorgeherreralopez68@gmail.com | R83: 00188576 | S83: 0 | T83: 0 | U83: 000 | V83: 5 | W83: 08 | X83: 02 | AC83: FRENTE A LA GUARDIA RURAL, QUEBRADA GRANDE. | AD83: 0000001916 | AE83: C | AF83: P | AG83: 0 | AH83: 45348 | AJ83: A | AK83: =COUNTIF($A$3:A$917,A83) -> 2
A84: 3002056564 | B84: ASOCIACION CAMARA DE GANADEROS DE TILARAN | C84: JOSE PABLO MURILLO CHAVARRIA | D84: 109250677 | E84: 1 | F84: 89737010 | H84: jpmurilloch@gmail.com | I84: BAR | J84: BAR LA SUBASTA. | K84: 3002056564 | L84: ASOCIACION CAMARA DE GANADEROS DE TILARAN | M84: N | N84: 89737010 | O84: 26955546 | P84: cadeganti@yahoo.es | R84: 00040655 | S84: 0 | T84: 0 | U84: 000 | V84: 5 | W84: 08 | X84: 01 | AC84: 1KM NORTE DEL ICE, CAMINO A NUEVO ARENAL | AD84: 0000001006 | AE84: C | AF84: P | AG84: 14146.2 | AH84: 44047 | AJ84: A | AK84: =COUNTIF($A$3:A$917,A84) -> 4
A85: 501940659 | B85: BERSABE DE LOS ANGELES BARAHONA ORTEGA | F85: 84479379 | G85: 84479379 | H85: b.laamistad2001@gmail.com | I85: BAR | J85: BAR RESTAURANTE LA AMISTAD | K85: 501940659 | L85: BERSABE DE LOS ANGELES BARAHONA ORTEGA | M85: N | N85: 84479379 | O85: 84479379 | P85: b.laamistad2001@gmail.com | R85: 00050822 | S85: 0 | T85: 0 | U85: 000 | V85: 5 | W85: 08 | X85: 06 | AC85: 200M S DEL SALON COMUNAL RIO PIEDRAS | AD85: 0000000259 | AE85: C | AF85: P | AG85: 14089.75 | AH85: 38405 | AJ85: A | AK85: =COUNTIF($A$3:A$917,A85) -> 2
A86: 501810885 | B86: CARLOS LUIS HERRERA CHAVES | F86: 86852207 | H86: herrerachavescarlos18@gmail.com | I86: BAR | J86: "BAR CAVI. | K86: 500820943 | L86: ZOILA ROSA DE JESUS CHAVES ZUMBADO | M86: N | N86: 86852207 | P86: herrerachavezcarlos18@gmail.com | R86: 00024269 | S86: 0 | T86: 0 | U86: 000 | V86: 5 | W86: 08 | X86: 03 | AC86: 70M S DE LA IGLESIA DE VIEJO ARENAL TILARAN | AD86: 0000000239 | AE86: C | AF86: P | AG86: 0 | AH86: 42037 | AJ86: A | AK86: =COUNTIF($A$3:A$917,A86) -> 2
A87: 207700340 | B87: CHRISTOPHER CONEJO PONTEUR | F87: 86143931 | G87: 86143931 | H87: ponteurc@gmail.com | I87: BAR | J87: LE BISTRO | K87: 3101079081 | L87: DESARROLLO TURISTICO Y AGROPECUARIO ARENAL SOCIEDA | M87: N | N87: 86143931 | O87: 86143931 | P87: lamansionarenal@gmail.com | R87: 00025679 | S87: B | T87: 0 | U87: 000 | V87: 5 | W87: 08 | X87: 07 | AC87: HOTEL MANSION INN LA UNION DE ARENAL. | AD87: 0000002204 | AE87: C | AF87: P | AG87: 0 | AH87: 45903 | AJ87: A | AK87: =COUNTIF($A$3:A$917,A87) -> 3
A88: 3101781324 | B88: CORPORACION LOS VILLEGAR DE LA ALTURA SOCIEDAD ANO | F88: 84228931 | G88: 84228931 | H88: anvillegar@hotmail.com | I88: BAR | J88: Bar Restaurante Cadillac´s | K88: 107970412 | L88: WILSON GERARDO SOTO NAVARRO | M88: N | N88: 6958383 | R88: 00008926 | S88: 0 | T88: 0 | U88: 000 | V88: 5 | W88: 08 | X88: 01 | AC88: 25 METROS NORTE DEL B.N.C.R, HOTEL TILARAN - TILARAN | AD88: 0000001803 | AE88: C | AF88: P | AG88: 0 | AH88: 45188 | AJ88: A | AK88: =COUNTIF($A$3:A$917,A88) -> 3
A89: 3102922559 | B89: DOS AMIGAS SOCIEDAD DE RESPONSABILIDAD LIMITADA | C89: TONYA CHRISTINE ASHER | D89: A37298871 | E89: 9 | F89: 87114027 | H89: tonyacasher@yahoo.com | I89: BAR | J89: LOS AMIGOS | K89: 3102852020 | L89: BAR LOS AMIGOS DE ARENAL DOS MIL VEINTIDOS SOCIEDA | M89: N | N89: 89770931 | O89: 70865806 | P89: baramigos45@gmail.com | R89: 00055477 | S89: 0 | T89: 0 | U89: 000 | V89: 5 | W89: 08 | X89: 07 | AC89: FRENTE A LA PLAZA DE DEPORTES, ARENAL | AD89: 0000002126 | AE89: C | AF89: P | AG89: 0 | AH89: 45741 | AJ89: A | AK89: =COUNTIF($A$3:A$917,A89) -> 2
A90: 501900100 | B90: ELADIO DEL CARMEN DELGADO CERDAS | F90: 89967007 | H90: jenndijo83@hotmail.com | I90: BAR | J90: BAR Y RESTAURANTE EQUUS | K90: 3101768867 | L90: XILOE VENTURES SOCIEDAD ANONIMA | M90: N | N90: 83141443 | P90: cdtxiloe@gmail.com | R90: 00023347 | S90: B | T90: 0 | U90: 000 | V90: 5 | W90: 08 | X90: 06 | AC90: BAR EQUUS CAMINO ARENAL TILARAN GTE | AD90: 0000001140 | AE90: C | AF90: P | AG90: 11986 | AH90: 44251 | AJ90: A | AK90: =COUNTIF($A$3:A$917,A90) -> 2
A91: 501580715 | B91: ELBA ISABEL MAYELA DURAN CONEJO | F91: 87642439 | G91: 26955425 | H91: elbaduranconejo@gmail.com | I91: BAR | J91: Bar y Restaurante El Parque | K91: 500940096 | L91: GERMAN ANTONIO VARGAS ALFARO | M91: N | N91: 88634500 | O91: 26955347 | P91: vargasherman40@gmail.com | R91: 00015425 | S91: 0 | T91: 0 | U91: 000 | V91: 5 | W91: 08 | X91: 01 | AC91: 50 M NORTE DEL COMERCIAL TILARAN | AD91: 0000001594 | AE91: C | AF91: P | AG91: 0 | AH91: 44833 | AJ91: A | AK91: =COUNTIF($A$3:A$917,A91) -> 2
A92: 208530874 | B92: FRANCIS DANIELA ARIAS VALLE | F92: 87446799 | G92: 87446799 | H92: francisariasvalle@gmail.com | I92: BAR | J92: RANCHO GIRASOLES | K92: 106650918 | L92: JUAN DIEGO DE SAN GERARDO CABEZAS CALVO | M92: N | N92: 89047218 | O92: 84305887 | P92: losgirasolesdelibano2016@gmail.com | R92: 00254099 | S92: 0 | T92: 0 | U92: 000 | V92: 5 | W92: 08 | X92: 05 | AC92: 1.5 KM OESTE DEL SALON COMUNAL, SOLANIA, RESTAURANTE RANCHO LOS GIRASOLES | AD92: 0000002185 | AE92: C | AF92: P | AG92: 0 | AH92: 45861 | AJ92: A | AK92: =COUNTIF($A$3:A$917,A92) -> 2
A93: 502280708 | B93: JAIME VARGAS SEGURA | F93: 71003181 | H93: prefabricadossegura@gmail.com | I93: BAR | J93: Restaurante El Mirador Los 80´s | K93: 3101167907 | L93: GANADERA MARICEL SOCIEDAD ANONIMA | M93: N | N93: 57150721 | P93: silvajosespc@gmail.com | R93: 00007985 | S93: 0 | T93: 0 | U93: 000 | V93: 5 | W93: 08 | X93: 06 | AC93: 1.680KM.ESTE DEL PUENTE RIO PIEDRAS TIERRAS MORENAS TILARAN | AD93: 0000001636 | AE93: C | AF93: P | AG93: 0 | AH93: 44909 | AJ93: A | AK93: =COUNTIF($A$3:A$917,A93) -> 3
A94: 503560655 | B94: JAVIER GERARDO ESPINOZA CERDAS | F94: 61458204 | H94: javierespinoza2320@hotmail.com | I94: BAR | J94: Bar Los Angeles | K94: 502950167 | L94: JOSE ALEXANDER ULATE CUBERO | M94: N | N94: 87305066 | O94: 87305066 | P94: aulatecubero@gmail.com | R94: 00007437 | S94: 0 | T94: 0 | U94: 000 | V94: 5 | W94: 08 | X94: 04 | AC94: COSTADO SUR IGLESIA CATOLICA LOS ANGELES | AD94: 0000001848 | AE94: C | AF94: P | AG94: 0 | AH94: 45252 | AJ94: A | AK94: =COUNTIF($A$3:A$917,A94) -> 1
A95: 502350359 | B95: JORGE EDUARDO DEL SOCORRO CONEJO SALAS | F95: 83227699 | G95: 26956238 | H95: jorgeconejos01@gmail.com | I95: BAR | J95: BAR RESTAURANT TILAWA | K95: 3101200362 | L95: COMERCIAL COSA SOCIEDAD ANONIMA | M95: N | N95: 83227699 | O95: 83227699 | R95: 00012305 | S95: 0 | T95: 0 | U95: 000 | V95: 5 | W95: 08 | X95: 01 | AC95: 175 M SUR DEL BCR, TILARAN | AD95: 0000000995 | AE95: C | AF95: P | AG95: 19281.75 | AH95: 44020 | AJ95: A | AK95: =COUNTIF($A$3:A$917,A95) -> 2
A96: 155805445627 | B96: JOSE NAPOLEON GARCIA LOPEZ | F96: 62767833 | G96: 62767833 | H96: frutera92@gmail.com | I96: BAR | J96: BAR Y RESTAURANTE LA FRUTERA | K96: 900930592 | L96: JOSE LUIS GONZALEZ ROJAS | M96: N | N96: 71394741 | O96: 71394741 | P96: jenngongut1305@gmail.com | R96: 00113256 | S96: 0 | T96: 0 | U96: 000 | V96: 5 | W96: 08 | X96: 02 | AC96: 500 M NORTE DE LA PLAZA DEPORTES, CABECERAS. | AD96: 0000001198 | AE96: C | AF96: P | AG96: 5139.3333 | AH96: 44335 | AJ96: A | AK96: =COUNTIF($A$3:A$917,A96) -> 2
A97: 204300170 | B97: JUAN CARLOS CONEJO CASTILLO | F97: 84606938 | H97: restaurantechafis1967@gmail.com | I97: BAR | J97: BAR RESTAURANTE CHAFIS | K97: 3101511764 | L97: LA TEJONA DEL LAGO ARENAL SOCIEDAD ANONIMA | M97: N | N97: 85353671 | O97: 85353671 | P97: marisa.mirancho@hotmail.com | R97: 00088472 | S97: 0 | T97: 0 | U97: 000 | V97: 5 | W97: 08 | X97: 01 | AC97: 2.5 KM NORTE DE LA AGENCIA ICE, TILARAN | AD97: 0000001983 | AE97: C | AF97: P | AG97: 0 | AH97: 45441 | AJ97: A | AK97: =COUNTIF($A$3:A$917,A97) -> 2
A98: 3101130626 | B98: LA PEQUEÑA HELVECIA SOCIEDAD ANONIMA | C98: SILENA MONCADA BELLO | D98: 302020824 | E98: 1 | F98: 88139607 | H98: smonbe@pequenahelvecia.com | I98: BAR | J98: RESTAURANTE LOS HEROES | K98: 3101130626 | L98: LA PEQUEÑA HELVECIA SOCIEDAD ANONIMA | M98: N | N98: 88139607 | O98: 26928013 | P98: smonbe@pequenahelvecia.com | R98: 00182053 | S98: 0 | T98: 0 | U98: 000 | V98: 5 | W98: 08 | X98: 07 | AC98: HOTEL LOS HEROES, LA UNIÓN, ARENAL. | AD98: 0000000626 | AE98: C | AF98: P | AG98: 10960 | AH98: 42033 | AJ98: A | AK98: =COUNTIF($A$3:A$917,A98) -> 3
A99: 502050442 | B99: LUIS ANGEL DE SAN GERARDO RODRIGUEZ CORDOBA | F99: 87883996 | G99: 26952303 | H99: luisangel@gmail.com | I99: BAR | J99: LA CASONA DE LIBANO | K99: 502050442 | L99: LUIS ANGEL DE SAN GERARDO RODRIGUEZ CORDOBA | M99: N | N99: 87883996 | O99: 26952303 | P99: luisangel@gmail.com | R99: 00007290 | S99: 0 | T99: 0 | U99: 000 | V99: 5 | W99: 08 | X99: 05 | AC99: 50 M.NORTE DE LA IGLESIA CATOLICA, LIBANO | AD99: 0000001372 | AE99: C | AF99: P | AG99: 0 | AH99: 44692 | AJ99: A | AK99: =COUNTIF($A$3:A$917,A99) -> 3
A100: 501461316 | B100: MARGARITA ISABEL RAMIREZ RODRIGUEZ | F100: 87159981 | G100: 83199956 | H100: ramirez13margarita@gmail.com | I100: BAR | J100: MACO´S BAR RESTAURANTE Y SALON | K100: 204760692 | L100: HENRY RAFAEL MEJIAS ESQUIVEL | M100: N | N100: 89237401 | O100: 89237401 | P100: rmejiase13@gmail.com | R100: 00038317 | S100: 0 | T100: 0 | U100: 000 | V100: 5 | W100: 08 | X100: 03 | AC100: FRENTE A LA PLAZA DE DEPORTES, TRONADORA | AD100: 0000001769 | AE100: C | AF100: P | AG100: 0 | AH100: 45145 | AJ100: A | AK100: =COUNTIF($A$3:A$917,A100) -> 3
...

Sheet PARÁMETROS
U2: TIPO DE ZONA
B3: SI | C3: X | D3: CONDICIÓN | E3: MEDIOS DE NOTIFICACIÓN | I3: CUMPLE | J3: APLICA O NO | K3: USOS | P3: GESTIÓN | Q3: Permiso que señala la Ley General de Salud | U3: Habitación.
B4: NO | D4: Apoderado | E4: Fax | I4: SI | J4: Aplica | K4: USO CONFORME | N4: 1 | Q4: Certificado Veterinario de Operación requerido en la Ley General del Servicio Nacional de Salud Animal. | U4: Servicios de oficina.
D5: Representante Legal | E5: Correo electrónico | I5: NO | J5: No aplica | K5: USO NO CONFORME | N5: 0 | U5: Servicios para el comercio y abasto.
E6: Dirección representante o apoderado | I6: No aplica | U6: Servicios para la salud.
I7: MINISTERIO DE SALUD | Q7: Simplificación de Trámites | U7: Servicios para la educación.
B8: PROVINCIA-CANTON-DISTRITO | C8: PROVINCIA | D8: PROVINCIA-CANTÓN | F8: HORARIO | I8: Sección | J8: División | K8: Grupo | L8: Clase | M8: El Permiso Sanitario de Funcionamiento se otorga a los establecimientos que albergan las siguientes actividades | N8: Equivalencia al CIIU 3 | O8: Riesgo Sanitario Ministerio de Salud | Q8: Actividades de Comercialización y Servicios del SENASA | U8: Servicios religiosos.
F9: 00:00 am | U9: Servicios para la cultura y el deporte.
B10: SAN JOSE | C10: SAN JOSÉ | D10: San José | F10: 01:00 am | Q10: Columna2 | R10: Columna12 | U10: Servicios de alojamiento y turismo.
B11: SAN JOSE | C11: ALAJUELA | D11: SAN JOSE | F11: 02:00 am | Q11: Venta al por mayor de carne y productos cárnicos | R11: 40201 | U11: Instalaciones para la seguridad.
B12: El Carmen | C12: CARTAGO | D12: ESCAZU | F12: 03:00 am | Q12: Recibo, clasificación y primera venta de productos pesqueros. | R12: 40202 | U12: Servicios funerarios.
B13: Merced | C13: HEREDIA | D13: DESAMPARADOS | F13: 04:00 am | Q13: Venta al por mayor de productos lácteos | R13: 40203 | U13: Transporte y comunicación.
B14: Hospital | C14: GUANACASTE | D14: PURISCAL | F14: 05:00 am | Q14: Venta al por mayor de huevo fresco | R14: 40204 | U14: Industria.
B15: Catedral | C15: PUNTARENAS | D15: TARRAZU | F15: 06:00 am | Q15: Envasado y Venta al por mayor de miel y productos apícolas (polen, propóleo, jalea real) | R15: 40205 | U15: Instalaciones para la infraestructura.
B16: Zapote | C16: LIMÓN | D16: ASERRI | F16: 07:00 am | Q16: Venta al por mayor de productos pesqueros | R16: 40206
B17: San Fco.de Dos Ríos | D17: MORA | F17: 08:00 am | Q17: Envasado y venta al por mayor de jarabes | R17: 40207
B18: Uruca | D18: GOICOECHEA | F18: 09:00 am | Q18: Venta al por mayor de medicamentos veterinarios | R18: 40301
B19: Mata Redonda | D19: SANTA ANA | F19: 10:00 am | Q19: Venta al por mayor de productos afines | R19: 40303
B20: Pavas | D20: ALAJUELITA | F20: 11:00 am | Q20: Venta al por mayor de medicamentos veterinarios de medicina alternativa | R20: 40304
B21: Hatillo | D21: VASQUEZ DE CORONADO | F21: 12:00 m.d | Q21: Venta al por mayor de productos afines de medicina alternativa | R21: 40305
B22: San Sebastián | D22: ACOSTA | F22: 01:00 pm | Q22: Venta al por mayor de alimentos, mezclas y premezclas para animales | R22: 40401
B23: ESCAZU | D23: TIBAS | F23: 02:00 pm | Q23: Venta al por mayor de materias primas para alimentación animal | R23: 40402
B24: Escazú | D24: MORAVIA | F24: 03:00 pm | Q24: Reempaque de alimentos destinados a la alimentación animal | R24: 40403
B25: San Antonio | D25: MONTES DE OCA | F25: 04:00 pm | Q25: Venta al por menor de mascotas o animales domésticos | R25: 40501
B26: San Rafael | D26: TURRUBARES | F26: 05:00 pm | Q26: Venta al por menor de animales acuáticos ornamentales | R26: 40503
B27: DESAMPARADOS | D27: DOTA | F27: 06:00 pm | Q27: Venta al por menor de animales silvestres autorizados | R27: 40504
B28: Desamparados | D28: CURRIDABAT | F28: 07:00 pm | Q28: Expendio de carne y productos cárnicos | R28: 40601
B29: San Miguel | D29: PEREZ ZELEDON | F29: 08:00 pm | Q29: Expendio de productos pesqueros | R29: 40602 | U29: 4. Servicios para la salud.
B30: San Juan de Dios | D30: LEON CORTES | F30: 09:00 pm | Q30: Expendio de lácteos | R30: 40603
B31: San Rafael Arriba | F31: 10:00 pm | Q31: Expendio de huevos | R31: 40604 | U31: 4.1 Consultorios médicos.
B32: San Antonio | D32: Alajuela | F32: 11:00 pm | Q32: Expendio de miel y productos apícolas | R32: 40605 | U32: 4.2 Clínicas y centros de salud.
B33: Frailes | D33: ALAJUELA | F33: 11:59 pm | Q33: Reempaque de productos de origen animal con fines de venta minorista | R33: 40606 | U33: 4.3 Hospitales, sanatorios, maternidades, y centros de rehabilitación.
B34: Patarrá | D34: SAN RAMON | Q34: Expendio de carne de caballo | R34: 40607
B35: San Cristóbal | D35: GRECIA | F35: CONICIÓN DEL LOCAL | Q35: Venta al por menor de medicamentos veterinarios | R35: 40801 | U35: 5. Servicios para la educación.
B36: Rosario | D36: SAN MATEO | Q36: Venta al por menor de productos afines | R36: 40802
B37: Damas | D37: ATENAS | F37: Excelente | Q37: Venta al por menor de medicamentos de medicina alternativa | R37: 40803 | U37: 5.1 Educación preparatoria y educación primaria.
B38: San Rafael Abajo | D38: NARANJO | F38: Buena | Q38: Venta al por menor de productos afines de medicina alternativa | R38: 40804 | U38: 5.2 Educación media: académica, de artes y oficios y tecnológicas o vocacionales.
B39: Gravilias | D39: PALMARES | F39: Regular | Q39: Venta al por menor de productos destinados a la alimentación animal | R39: 40901 | U39: 5.3 Educación superior, institutos técnicos, centros de capacitación, academias profesionales, colegios universitarios y universidades.
B40: PURISCAL | D40: POAS | F40: Deficiente | Q40: Reempaque de productos destinados a la alimentación animal en punto de venta | R40: 40902 | U40: 5.4 Educación física y artística: escuelas de natación, música, baile, artes marciales, modelos, pintura, escultura, actuación y fotografía.
B41: Santiago | D41: OROTINA | Q41: Servicio de hospitalización veterinaria | R41: 60101
B42: Mercedes Sur | D42: SAN CARLOS | F42: POSESIÓN INSTALACIONES | Q42: Servicio de clínica y cirugía veterinaria | R42: 60102 | U42: 6. Servicios religiosos.
B43: Barbacoas | D43: ALFARO RUIZ | Q43: Servicio de laboratorio y diagnóstico | R43: 60103
B44: Grifo Alto | D44: VALVERDE VEGA | F44: Propio | Q44: Servicio de consulta y cirugía menor | R44: 60104 | U44: 6.1 Instalaciones religiosas: templos y lugares de cultos, conventos y edificaciones para la enseñanza religiosa.
B45: San Rafael | D45: UPALA | F45: Arrendado | Q45: Servicio de clínica veterinaria ambulante | R45: 60105
B46: Candelarita | D46: LOS CHILES | F46: Concesionado | Q46: Estética de mascotas | R46: 60301 | U46: 7. Servicios para la cultura y el deporte.
B47: Desamparaditos | D47: GUATUSO | F47: Otro (especifique): | Q47: Estética de mascotas móvil | R47: 60302
B48: San Antonio | Q48: No aplica | R48: No aplica | U48: 7.1 Centros de espectáculos y recreativos: auditorios, teatros, cines, salas de música, salas de video juegos, “café Internet” y similares.
B49: Chires | D49: Cartago | F49: SENASA | U49: 7.2 Centros culturales: bibliotecas, museos, galerías de arte, filmotecas, cinematecas, casas de cultura, centros comunitarios.
B50: TARRAZU | D50: CARTAGO | F50: Subsistencia | U50: 7.3 Instalaciones para la recreación y el deporte: gimnasia, “squash”, billares, salas de juegos de mesa.
B51: San Marcos | D51: PARAISO | F51: Pequeña | U51: 7.4 Instalaciones para deportes de exhibición al aire libre: estadios, hipódromos, autódromos, velódromos, plaza de toros, polígonos y similares.
B52: San Lorenzo | D52: LA UNION | F52: Mediana | U52: 7.5 Clubes, instalaciones campestres, campamentos y paraderos turísticos.
B53: San Carlos | D53: JIMENEZ | F53: Grande | U53: 7.6 Parques, jardines, juegos infantiles.
B54: ASERRI | D54: TURRIALBA | F54: No aplica
B55: Aserrí | D55: ALVARADO | U55: 8. Servicios de alojamiento y turismo.
B56: Tarbaca | D56: OREAMUNO | F56: MES | H56: DIA
B57: Vuelta de Jorco | D57: EL GUARCO | F57: Enero | H57: 1 | U57: 8.1 Hoteles, moteles, albergues, casas de huéspedes, orfanatos, asilos.
B58: San Gabriel | F58: Febrero | H58: 2 | U58: 8.2 Atracciones turísticas.
B59: Legua | D59: Heredia | F59: Marzo | H59: 3
B60: Monterrey | D60: HEREDIA | F60: Abril | H60: 4 | U60: 9. Instalaciones para la seguridad.
B61: Salitrillos | D61: BARVA | F61: Mayo | H61: 5
B62: MORA | D62: SANTO DOMINGO | F62: Junio | H62: 6 | U62: 9.1 Instalaciones para la seguridad pública: estación de bomberos, cruz roja, protección civil, policía.
B63: Colón | D63: SANTA BARBARA | F63: Julio | H63: 7
B64: Guayabo | D64: SAN RAFAEL | F64: Agosto | H64: 8 | U64: 10. Servicios funerarios.
B65: Tabarcia | D65: SAN ISIDRO | F65: Septiembre | H65: 9
B66: Piedras Negras | D66: BELEN | F66: Octubre | H66: 10 | U66: 10.1 Funerarias y salas de velación.
B67: Picagres | D67: FLORES | F67: Noviembre | H67: 11 | U67: 10.2 Cementerios, panteones y crematorios.
B68: GOICOECHEA | D68: SAN PABLO | F68: Diciembre | H68: 12
B69: Guadalupe | D69: SARAPIQUI | H69: 13 | U69: 11. Transporte y comunicación.
B70: San Francisco | F70: AÑO | H70: 14
B71: Calle Blancos | D71: Guanacaste | F71: 2018 | H71: 15 | U71: 11.1 Estacionamientos.
B72: Mata de Plátano | D72: LIBERIA | F72: 2019 | H72: 16 | U72: 11.2 Garajes de buses y terminales de transporte de carga y pasajeros.
B73: Ipís | D73: NICOYA | F73: 2020 | H73: 17 | U73: 11.3 Atracaderos turísticos.
B74: Rancho Redondo | D74: SANTA CRUZ | F74: 2021 | H74: 18 | U74: 11.4 Centrales telefónicas, torres de transmisión, antenas y torres de radio, líneas de transmisión.
B75: Purral | D75: BAGACES | F75: 2022 | H75: 19
B76: SANTA ANA | D76: CARRILLO | F76: 2023 | H76: 20 | U76: 12. Industria.
B77: Santa Ana | D77: CAÑAS | F77: 2024 | H77: 21
B78: Salitral | D78: ABANGARES | F78: 2025 | H78: 22 | U78: 12.1 Industria inofensiva y producción artesanal: industria y talleres localizados dentro de las viviendas y que no son contaminantes.
B79: Pozos | D79: TILARAN | F79: 2026 | H79: 23 | U79: 12.2 Canteras, tajos, caleras y similares.
B80: Uruca | D80: NANDAYURE | F80: 2027 | H80: 24
B81: Piedades | D81: LA CRUZ | F81: 2028 | H81: 25 | U81: 13. Instalaciones para la infraestructura.
B82: Brasil | D82: HOJANCHA | F82: 2029 | H82: 26
B83: ALAJUELITA | F83: 2030 | H83: 27 | U83: 13.1 Planta, estación, subestación de infraestructura básica: bombas, pozos, captaciones, tanques reguladores, lagunas de control y regulación, subestaciones eléctricas, líneas de transmisión y distribución, líneas de distribución telefónica, televisión e Internet.
B84: Alajuelita | D84: Puntarenas | F84: 2031 | H84: 28 | U84: 13.2 Depósito de desechos sólidos, plantas de tratamiento, basureros, rellenos sanitarios, tuberías de distribución: agua
B85: San Josecito | D85: PUNTARENAS | F85: 2032 | H85: 29 | U85: potable, pluvial y sanitario.
B86: San Antonio | D86: ESPARZA | F86: 2033 | H86: 30
B87: Concepción | D87: BUENOS AIRES | H87: 31
B88: San Felipe | D88: MONTES DE ORO
B89: VASQUEZ DE CORONADO | D89: OSA
B90: San Isidro | D90: AGUIRRE
B91: San Rafael | D91: GOLFITO
B92: Dulce Nombre de Jesús | D92: COTO BRUS
B93: Patalillo | D93: PARRITA
B94: Cascajal | D94: CORREDORES
B95: ACOSTA | D95: GARABITO
B96: San Ignacio
B97: Guaitíl | D97: Limón
B98: Palmichal | D98: LIMON
B99: Cangrejal | D99: POCOCI
B100: Sabanillas | D100: SIQUIRRES
B101: TIBAS | D101: TALAMANCA
...

Sheet PROVINCIAS
A1: PROVINCIA | B1: CANTON
A2: SAN_JOSE | B2: SAN_JOSE | C2: ESCAZÚ | D2: DESAMPARADOS | E2: PURISCAL | F2: TARRAZU | G2: ASERRI | H2: MORA | I2: GOICOCHEA | J2: SANTA_ANA | K2: ALAJUELITA | L2: VASQUEZ_DE_CORONADO | M2: ACOSTA | N2: TIBAS | O2: MORAVIA | P2: MONTES_DE_OCA | Q2: TURRUBARES | R2: DOTA | S2: CURRIDABAT | T2: PEREZ_ZELEDÓN | U2: LEÓN_CORTES
A3: ALAJUELA | B3: ALAJUELA_ | C3: SAN_RAMON | D3: GRECIA | E3: SAN_MATEO | F3: ATENAS | G3: NARANJO | H3: PALMARES | I3: POÁS | J3: OROTINA | K3: SAN_CARLOS | L3: ALFARO_RUIZ | M3: VALVERDE_VEGA | N3: UPALA | O3: LOS_CHILES | P3: GUATUSO
A4: CARTAGO | B4: CARTAGO_ | C4: PARAÍSO | D4: LA_UNIÓN | E4: JIMÉNEZ | F4: TURRIALBA | G4: ALVARADO | H4: OREAMUNO | I4: EL_GUARCO
A5: HEREDIA | B5: HEREDIA_ | C5: BARVA | D5: SANTO_DOMINGO | E5: SANTA_BÁRBARA | F5: SAN_RAFAEL | G5: SAN_ISIDRO | H5: BELÉN | I5: FLORES | J5: SAN_PABLO | K5: SARAPIQUÍ
A6: GUANACASTE | B6: LIBERIA | C6: NICOYA | D6: SANTA_CRUZ | E6: BAGACES | F6: CARRILLO | G6: CAÑAS | H6: ABANGARES | I6: TILARAN | J6: NANDAYURE | K6: LA_CRUZ | L6: HOJANCHA
A7: PUNTARENAS | B7: PUNTARENAS_ | C7: ESPARZA | D7: BUENOS_AIRES | E7: MONTES_DE_ORO | F7: OSA | G7: AGUIRRE | H7: GOLFITO | I7: COTO_BRUS | J7: PARRITA | K7: CORREDORES | L7: GARABITO
A8: LIMÓN | B8: LIMÓN_ | C8: POCOCI | D8: SIQUIRRES | E8: TALAMANCA | F8: MATINA | G8: GUÁCIMO
A10: SAN JOSE
A12: SAN_JOSE | B12: Escazú | C12: Desamparados | D12: Santiago | E12: San Marcos | F12: Aserri | G12: MORA | H12: GOICOECHEA | I12: SANTA ANA | J12: ALAJUELITA | K12: VASQUEZ DE CORONADO | L12: ACOSTA | M12: TIBAS | N12: MORAVIA | O12: MONTES DE OCA | P12: TURRUBARES | Q12: DOTA | R12: CURRIDABAT | S12: PEREZ ZELEDON | T12: LEON CORTES
A13: El Carmen | B13: San Antonio | C13: San Miguel | D13: Mercedes Sur | E13: San Lorenzo | F13: Tarbaca | G13: Colón | H13: Guadalupe | I13: Santa Ana | J13: Alajuelita | K13: San Isidro | L13: San Ignacio | M13: San Juan | N13: San Vicente | O13: San Pedro | P13: San Pablo | Q13: Santa María | R13: Curridabat | S13: San Isidro de El General | T13: San Pablo
A14: Merced | B14: San Rafael | C14: San Juan de Dios | D14: Barbacoas | E14: San Carlos | F14: Vuelta de Jorco | G14: Guayabo | H14: San Francisco | I14: Salitral | J14: San Josecito | K14: San Rafael | L14: Guaitíl | M14: Cinco Esquinas | N14: San Jerónimo | O14: Sabanilla | P14: San Pedro | Q14: Jardín | R14: Granadilla | S14: General | T14: San Andrés
A15: Hospital | C15: San Rafael Arriba | D15: Grifo Alto | F15: San Gabriel | G15: Tabarcia | H15: Calle Blancos | I15: Pozos | J15: San Antonio | K15: Dulce Nombre de Jesús | L15: Palmichal | M15: Anselmo Llorente | N15: Trinidad | O15: Mercedes | P15: San Juan de Mata | Q15: Copey | R15: Sánchez | S15: Daniel Flores | T15: Llano Bonito
A16: Catedral | C16: San Antonio | D16: San Rafael | F16: Legua | G16: Piedras Negras | H16: Mata de Plátano | I16: Uruca | J16: Concepción | K16: Patalillo | L16: Cangrejal | M16: León XIII | O16: San Rafael | P16: San Luis | R16: Tirrases | S16: Rivas | T16: San Isidro
A17: Zapote | C17: Frailes | D17: Candelarita | F17: Monterrey | G17: Picagres | H17: Ipís | I17: Piedades | J17: San Felipe | K17: Cascajal | L17: Sabanillas | M17: Colima | S17: San Pedro | T17: Santa Cruz
A18: San Fco.de Dos Ríos | C18: Patarrá | D18: Desamparaditos | F18: Salitrillos | H18: Rancho Redondo | I18: Brasil | S18: Platanares | T18: San Antonio
A19: Uruca | C19: San Cristóbal | D19: San Antonio | H19: Purral | S19: Pejibaye
A20: Mata Redonda | C20: Rosario | D20: Chires | S20: Cajón
A21: Pavas | C21: Damas | S21: Barú
A22: Hatillo | C22: San Rafael Abajo | S22: Río Nuevo
A23: San Sebastián | C23: Gravilias | S23: Páramo
A25: ALAJUELA
A27: ALAJUELA | B27: SAN RAMON | C27: GRECIA | D27: SAN MATEO | E27: ATENAS | F27: NARANJO | G27: PALMARES | H27: POAS | I27: OROTINA | J27: SAN CARLOS | K27: ALFARO RUIZ | L27: VALVERDE VEGA | M27: UPALA | N27: LOS CHILES | O27: GUATUSO
A28: Alajuela | B28: San Ramón | C28: Grecia | D28: San Mateo | E28: Atenas | F28: Naranjo | G28: Palmares | H28: San Pedro | I28: Orotina | J28: Quesada | K28: Zarcero | L28: Sarchí Norte | M28: Upala | N28: Los Chiles | O28: San Rafael
A29: San José | B29: Santiago | C29: San Isidro | D29: Desmonte | E29: Jesús | F29: San Miguel | G29: Zaragoza | H29: San Juan | I29: Mastate | J29: Florencia | K29: Laguna | L29: Sarchí Sur | M29: Aguas Claras | N29: Caño Negro | O29: Buenavista
A30: Carrizal | B30: San Juan | C30: San José | D30: Jesús María | E30: Mercedes | F30: San José | G30: Buenos Aires | H30: San Rafael | I30: Hacienda Vieja | J30: Buenavista | K30: Tapezco | L30: Toro Amarillo | M30: San José o Pizote | N30: El Amparo | O30: Cote
A31: San Antonio | B31: Piedades Norte | C31: San Roque | E31: San Isidro | F31: Cirrí Sur | G31: Santiago | H31: Carrillos | I31: Coyolar | J31: Aguas Zarcas | K31: Guadalupe | L31: San Pedro | M31: Bijagua | N31: San Jorge
A32: Guácima | B32: Piedades Sur | C32: Tacares | E32: Concepción | F32: San Jerónimo | G32: Candelaria | H32: Sabana Redonda | I32: Ceiba | J32: Venecia | K32: Palmira | L32: Rodríguez | M32: Delicias
A33: San Isidro | B33: San Rafael | C33: Río Cuarto | E33: San José | F33: San Juan | G33: Esquipulas | J33: Pital | K33: Zapote | M33: Dos Ríos
A34: Sabanilla | B34: San Isidro | C34: Puente de Piedra | E34: Santa Eulalia | F34: Rosario | G34: Granja | J34: Fortuna | K34: Brisas | M34: Yolillal
A35: San Rafael | B35: Angeles | C35: Bolívar | J35: Tigra
A36: Río Segundo | B36: Alfaro | J36: Palmera
A37: Desamparados | B37: Volio | J37: Venado
A38: Turrúcares | B38: Concepción | J38: Cutris
A39: Tambor | B39: Zapotal | J39: Monterrey
A40: La Garita | B40: Peñas Blancas | J40: Pocosol
A41: Sarapiquí
A43: CARTAGO
A45: CARTAGO | B45: PARAISO | C45: LA UNION | D45: JIMENEZ | E45: TURRIALBA | F45: ALVARADO | G45: OREAMUNO | H45: EL GUARCO
A46: Oriental | B46: Paraíso | C46: Tres Ríos | D46: Juan Viñas | E46: Turrialba | F46: Pacayas | G46: San Rafael | H46: El Tejar
A47: Occidental | B47: Santiago | C47: San Diego | D47: Tucurrique | E47: La Suiza | F47: Cervantes | G47: Cot | H47: San Isidro
A48: Carmen | B48: Orosi | C48: San Juan | D48: Pejibaye | E48: Peralta | F48: Capellades | G48: Potrero Cerrado | H48: Tobosi
A49: San Nicolás | B49: Cachí | C49: San Rafael | E49: Santa Cruz | G49: Cipreses | H49: Patio de Agua
A50: Aguacaliente o San Fco. | C50: Concepción | E50: Santa Teresita | G50: Santa Rosa
A51: Guadalupe o Arenilla | C51: Dulce Nombre | E51: Pavones
A52: Corralillo | C52: San Ramón | E52: Tuis
A53: Tierra Blanca | C53: Río Azul | E53: Tayutic
A54: Dulce Nombre | E54: Santa Rosa
A55: Llano Grande | E55: Tres Equis
A56: Quebradilla
A58: HEREDIA
A60: HEREDIA | B60: BARVA | C60: SANTO DOMINGO | D60: SANTA BARBARA | E60: SAN RAFAEL | F60: SAN ISIDRO | G60: BELEN | H60: FLORES | I60: SAN PABLO | J60: SARAPIQUI
A61: Heredia | B61: Barva | C61: Santo Domingo | D61: Santa Bárbara | E61: San Rafael | F61: San Isidro | G61: San Antonio | H61: San Joaquín | I61: San Pablo | J61: Puerto Viejo
A62: Mercedes | B62: San Pedro | C62: San Vicente | D62: San Pedro | E62: San Josecito | F62: San José | G62: Rivera | H62: Barrantes | J62: La Vírgen
A63: San Francisco | B63: San Pablo | C63: San Miguel | D63: San Juan | E63: Santiago | F63: Concepción | G63: Asunción | H63: Llorente | J63: Horquetas
A64: Ulloa | B64: San Roque | C64: Paracito | D64: Jesús | E64: Angeles | F64: San Francisco | J64: Llanuras del Gaspar
A65: Vara Blanca | B65: Santa Lucía | C65: Santo Tomás | D65: Santo Domingo | E65: Concepción | J65: Cureña
B66: San José de La Montaña | C66: Santa Rosa | D66: Purabá
C67: Tures
C68: Pará
A70: GUANACASTE
A72: LIBERIA | B72: NICOYA | C72: SANTA CRUZ | D72: BAGACES | E72: CARRILLO | F72: CAÑAS | G72: ABANGARES | H72: TILARAN | I72: NANDAYURE | J72: LA CRUZ | K72: HOJANCHA
A73: Liberia | B73: Nicoya | C73: Santa Cruz | D73: Bagaces | E73: Filadelfia | F73: Cañas | G73: Juntas | H73: Tilarán | I73: Carmona | J73: La Cruz | K73: Hojancha
A74: Cañas Dulces | B74: Mansión | C74: Bolsón | D74: Fortuna | E74: Palmira | F74: Palmira | G74: Sierra | H74: Quebrada Grande | I74: Santa Rita | J74: Santa Cecilia | K74: Monte Romo
A75: Mayorga | B75: San Antonio | C75: 27 de Abril | D75: Mogote | E75: Sardinal | F75: San Miguel | G75: San Juan | H75: Tronadora | I75: Zapotal | J75: Garita | K75: Puerto Carrillo
A76: Nacascolo | B76: Quebrada Honda | C76: Tempate | D76: Río Naranjo | E76: Belén | F76: Bebedero | G76: Colorado | H76: Santa Rosa | I76: San Pablo | J76: Santa Elena | K76: Huacas
A77: Curubandé | B77: Sámara | C77: Cartagena | F77: Porozal | H77: Líbano | I77: Porvenir
B78: Nosara | C78: Cuajiniquil | H78: Tierras Morenas | I78: Bejuco
B79: Belén de Nosarita | C79: Diriá | H79: Arenal
C80: Cabo Velas
C81: Tamarindo
A83: PUNTARENAS
A85: PUNTARENAS | B85: ESPARZA | C85: BUENOS AIRES | D85: MONTES DE ORO | E85: OSA | F85: AGUIRRE | G85: GOLFITO | H85: COTO BRUS | I85: PARRITA | J85: CORREDORES | K85: GARABITO
A86: Puntarenas | B86: Espíritu Santo | C86: Buenos Aires | D86: Miramar | E86: Puerto Cortés | F86: Quepos | G86: Golfito | H86: San Vito | I86: Parrita | J86: Corredor | K86: Jacó
A87: Pitahaya | B87: San Juan Grande | C87: Volcán | D87: Unión | E87: Palmar | F87: Savegre | G87: Puerto Jiménez | H87: Sabalito | J87: La Cuesta | K87: Tárcoles
A88: Chomes | B88: Macacona | C88: Potrero Grande | D88: San Isidro | E88: Sierpe | F88: Naranjito | G88: Guaycará | H88: Agua Buena | J88: Canoas
A89: Lepanto | B89: San Rafael | C89: Boruca | E89: Bahía Ballena | G89: Pavón | H89: Limoncito | J89: Laurel
A90: Paquera | B90: San Jerónimo | C90: Pilas | E90: Piedras Blancas | H90: Pittier
A91: Manzanillo | C91: Colinas
A92: Guacimal | C92: Chánguena
A93: Barranca | C93: Biolley
A94: Monteverde
A95: Cóbano
A96: Chacarita
A97: Chira
A98: Acapulco
A100: LIMON
A102: LIMON | B102: POCOCI | C102: SIQUIRRES | D102: TALAMANCA | E102: MATINA | F102: GUACIMO
A103: Limón | B103: Guápiles | C103: Siquirres | D103: Bratsi | E103: Matina | F103: Guácimo
A104: Valle La Estrella | B104: Jiménez | C104: Pacuarito | D104: Sixaola | E104: Batán | F104: Mercedes
A105: Río Blanco | B105: Rita | C105: Florida | D105: Cahuita | E105: Carrandí | F105: Pocora
A106: Matama | B106: Roxana | C106: Germania | F106: Río Jiménez
B107: Cariari | C107: Cairo | F107: Duacarí
B108: Colorado | C108: Alegría

Sheet UNICOMER
E2: 2022
E3: TRIMESTRAL | G3: ANUAL
B4: INGRESO BRUTO CURACAO | E4: 7.9047004e+08 | F4: =E4/E7 -> 0.39789476
B5: INGRESO BRUTO GOLLO | E5: 1.1961609e+09 | F5: =E5/E7 -> 0.60210524
E7: =E5+E4 -> 1.9866309e+09
E9: TRIMESTRAL | G9: ANUAL
B10: Impuesto 2022 | E10: =#REF! -> #REF! | G10: =E10*4 -> #REF!
B12: IMPUESTO TRIMESTRAL CURACAO | E12: =E10*F4 -> #REF!
B13: IMPUESTO TRIMESTRAL GOLLO | E13: =E10*F5 -> #REF!
N14: 2021
E15: =SUM(E12:E14) -> #REF! | N15: TRIMESTRAL
K16: CURACAO LINEA BLANCA | N16: 1146065.1 | O16: =N16/N18 -> 0.93925817 | P16: 93.93
E17: TRIMESTRAL | G17: ANUAL | K17: CURACAO ABARROTES | N17: 74116.04 | O17: =N17/N18 -> 0.060741833 | P17: 6.07
B18: CURACAO LINEA BLANCA | E18: =E12*F18 -> #REF! | F18: 0.9393 | G18: =E18*4 -> #REF! | N18: =SUM(N16:N17) -> 1220181.2 | O18: =SUM(O16:O17) -> 1 | P18: =SUM(P16:P17) -> 100
B19: CURACAO ABARROTES | E19: =E12*F19 -> #REF! | F19: 0.0607 | G19: =E19*4 -> #REF!
E20: =SUM(E18:E19) -> #REF! | G20: =SUM(G18:G19) -> #REF! | K20: EL GOLLO LINEA BLANCA | N20: 438987.59 | O20: =N20/N22 -> 0.91651299 | P20: 91.65
K21: EL GOLLO ABARROTES | N21: 39988.26 | O21: =N21/N22 -> 0.083487007 | P21: 8.35
B22: EL GOLLO LINEA BLANCA | E22: =E13*F22 -> #REF! | F22: 0.9165 | G22: =E22*4 -> #REF! | N22: =SUM(N20:N21) -> 478975.85 | O22: =SUM(O20:O21) -> 1 | P22: =SUM(P20:P21) -> 100
B23: EL GOLLO ABARROTES | E23: =E13*F23 -> #REF! | F23: 0.0835 | G23: =E23*4 -> #REF!
E24: =SUM(E22:E23) -> #REF! | G24: =SUM(G22:G23) -> #REF!
G26: =G20+G24 -> #REF!

Sheet PAYUTE
D13: NENEN | E13: 50947668 | F13: =+E13/E16 -> 0.36473999
D14: PAYUTE | E14: 88734488 | F14: =+E14/E16 -> 0.63526001
E16: =SUM(E13:E15) -> 139682156
D17: 2022 | E17: =+#REF! -> #REF!
D20: NENEN | E20: =+E17*F13 -> #REF! | F20: =+E20*4 -> #REF!
D21: PAYUTE | E21: =+E17*F14 -> #REF! | F21: =+E21*4 -> #REF!
E23: =SUM(E20:E22) -> #REF!

Sheet GESSA
A1: gess
B2: INGRESO BRUTO ARENAL | E2: 9.6334089e+08 | G2: =E2/E5 -> 0.61552251
B3: INGRESO BRUTO TILARÁN | E3: 6.0173735e+08 | G3: =E3/E5 -> 0.38447749
E5: =E3+E2 -> 1.5650782e+09
B8: Impuesto Anual 2022 | E8: =1271626*4 -> 5086504
B10: INGRESO BRUTO ARENAL | E10: =E8*G2 -> 3130857.7
B11: INGRESO BRUTO TILARÁN | E11: =E8*G3 -> 1955646.3
E13: =SUM(E10:E12) -> 5086504

Sheet BNCR
B2: INGRESO BRUTO ARENAL | E2: 3.0976022e+08 | G2: =E2/E5 -> 0.34006234
B3: INGRESO BRUTO TILARÁN | E3: 6.0113225e+08 | G3: =E3/E5 -> 0.65993766
E5: =E3+E2 -> 9.1089247e+08
B8: Impuesto trimestral 2022 | E8: =#REF! -> #REF!
B10: INGRESO BRUTO ARENAL | E10: =E8*G2 -> #REF!
B11: INGRESO BRUTO TILARÁN | E11: =E8*G3 -> #REF!
E13: =SUM(E10:E12) -> #REF!

Sheet colono
B15: 000021 FERRETERIA | H15: 2010417.2 | I15: =+H15/$H$20 -> 0.39500076
A16: 2021 | B16: 000020 MATERIALES CONSTRUCCION. | H16: 2010417.2 | I16: =+H16/$H$20 -> 0.39500076
B17: 000021 FERRETERIA | H17: 952700.96 | I17: =+H17/$H$20 -> 0.18718384
B18: 000021 FERRETERIA | H18: 116118.63 | I18: =+H18/$H$20 -> 0.022814642
H20: =SUM(H15:H19) -> 5089654 | I20: =SUM(I15:I19) -> 1
G22: 4807161
B23: 000021 FERRETERIA | H23: =+G22*I15 -> 1898832.3 | I23: =+H23/G22 -> 0.39500076
A24: 2022 | B24: 000020 MATERIALES CONSTRUCCION. | H24: =+G22*I16 -> 1898832.3 | I24: =+H24/G22 -> 0.39500076
B25: 000021 FERRETERIA | H25: =+G22*I17 -> 899822.84 | I25: =+H25/G22 -> 0.18718384
B26: 000021 FERRETERIA | H26: =+G22*I18 -> 109673.66 | I26: =+H26/G22 -> 0.022814642
H28: =SUM(H23:H27) -> 4807161 | I28: =SUM(I23:I26) -> 1
G30: 4807161
B31: 000021 FERRETERIA | H31: =+H23*4 -> 7595329 | I31: =+H31/G30 -> 1.580003
A32: 2022 | B32: 000020 MATERIALES CONSTRUCCION. | H32: =+H24*4 -> 7595329 | I32: =+H32/G30 -> 1.580003
B33: 000021 FERRETERIA | H33: =+H25*4 -> 3599291.3 | I33: =+H33/G30 -> 0.74873534
B34: 000021 FERRETERIA | H34: =+H26*4 -> 438694.63 | I34: =+H34/G30 -> 0.091258569
H36: =SUM(H31:H35) -> 19228644 | I36: =SUM(I31:I34) -> 4
