Workbook
Name ABANGARES: PROVINCIAS!$G$73:$G$76
Name ACOSTA: PROVINCIAS!$L$13:$L$17
Name AGUIRRE: PROVINCIAS!$F$86:$F$88
Name ALAJUELA: PROVINCIAS!$B$3:$P$3
Name ALAJUELA_: PROVINCIAS!$A$28:$A$41
Name ALAJUELITA: PROVINCIAS!$J$13:$J$17
Name ALFARO_RUIZ: PROVINCIAS!$K$28:$K$34
Name ALVARADO: PROVINCIAS!$F$46:$F$48
Name ASERRI: PROVINCIAS!$F$12:$F$18
Name ATENAS: PROVINCIAS!$E$28:$E$34
Name BAGACES: PROVINCIAS!$D$73:$D$76
Name BARVA: PROVINCIAS!$B$61:$B$66
Name BELÉN: PROVINCIAS!$G$61:$G$63
Name BUENOS_AIRES: PROVINCIAS!$C$86:$C$93
Name CAÑAS: PROVINCIAS!$F$73:$F$77
Name CARRILLO: PROVINCIAS!$E$73:$E$76
Name CARTAGO: PROVINCIAS!$B$4:$I$4
Name CARTAGO_: PROVINCIAS!$A$46:$A$56
Name CORREDORES: PROVINCIAS!$J$86:$J$89
Name COTO_BRUS: PROVINCIAS!$H$86:$H$90
Name CURRIDABAT: PROVINCIAS!$R$13:$R$16
Name DESAMPARADOS: PROVINCIAS!$C$12:$C$23
Name DOTA: PROVINCIAS!$Q$13:$Q$15
Name EL_GUARCO: PROVINCIAS!$H$46:$H$49
Name ESCAZÚ: PROVINCIAS!$B$12:$B$14
Name ESPARZA: PROVINCIAS!$B$86:$B$90
Name FLORES: PROVINCIAS!$H$61:$H$63
Name GARABITO: PROVINCIAS!$K$86:$K$87
Name GOICOCHEA: PROVINCIAS!$H$13:$H$19
Name GOLFITO: PROVINCIAS!$G$86:$G$89
Name GRECIA: PROVINCIAS!$C$28:$C$35
Name GUÁCIMO: PROVINCIAS!$F$103:$F$107
Name GUANACASTE: PROVINCIAS!$B$6:$L$6
Name GUATUSO: PROVINCIAS!$O$28:$O$30
Name HEREDIA: PROVINCIAS!$B$5:$K$5
Name HEREDIA_: PROVINCIAS!$A$61:$A$65
Name HOJANCHA: PROVINCIAS!$K$73:$K$76
Name JIMÉNEZ: PROVINCIAS!$D$46:$D$48
Name LA_CRUZ: PROVINCIAS!$J$73:$J$76
Name LA_UNIÓN: PROVINCIAS!$C$46:$C$53
Name LEÓN_CORTES: PROVINCIAS!$T$13:$T$18
Name LIBERIA: PROVINCIAS!$A$73:$A$77
Name LIMÓN: PROVINCIAS!$B$8:$G$8
Name LIMÓN_: PROVINCIAS!$A$103:$A$106
Name LOS_CHILES: PROVINCIAS!$N$28:$N$31
Name MATINA: PROVINCIAS!$E$103:$E$105
Name MONTES_DE_OCA: PROVINCIAS!$O$13:$O$16
Name MONTES_DE_ORO: PROVINCIAS!$D$86:$D$88
Name MORA: PROVINCIAS!$G$13:$G$17
Name MORAVIA: PROVINCIAS!$N$13:$N$15
Name NANDAYURE: PROVINCIAS!$I$73:$I$78
Name NARANJO: PROVINCIAS!$F$28:$F$34
Name NICOYA: PROVINCIAS!$B$73:$B$79
Name OREAMUNO: PROVINCIAS!$G$46:$G$50
Name OROTINA: PROVINCIAS!$I$28:$I$32
Name OSA: PROVINCIAS!$E$86:$E$90
Name PALMARES: PROVINCIAS!$G$28:$G$34
Name PARAÍSO: PROVINCIAS!$B$46:$B$49
Name PARRITA: PROVINCIAS!$I$86
Name PEREZ_ZELEDÓN: PROVINCIAS!$S$13:$S$23

Sheet PROVINCIAS
A1: PROVINCIA | B1: CANTON
A2: SAN_JOSE | B2: SAN_JOSE | C2: ESCAZÚ | D2: DESAMPARADOS | E2: PURISCAL | F2: TARRAZU | G2: ASERRI | H2: MORA | I2: GOICOCHEA | J2: SANTA_ANA | K2: ALAJUELITA | L2: VASQUEZ_DE_CORONADO | M2: ACOSTA | N2: TIBAS | O2: MORAVIA | P2: MONTES_DE_OCA | Q2: TURRUBARES | R2: DOTA | S2: CURRIDABAT | T2: PEREZ_ZELEDÓN | U2: LEÓN_CORTES
A3: ALAJUELA | B3: ALAJUELA_ | C3: SAN_RAMON | D3: GRECIA | E3: SAN_MATEO | F3: ATENAS | G3: NARANJO | H3: PALMARES | I3: POÁS | J3: OROTINA | K3: SAN_CARLOS | L3: ALFARO_RUIZ | M3: VALVERDE_VEGA | N3: UPALA | O3: LOS_CHILES | P3: GUATUSO
A4: CARTAGO | B4: CARTAGO_ | C4: PARAÍSO | D4: LA_UNIÓN | E4: JIMÉNEZ | F4: TURRIALBA | G4: ALVARADO | H4: OREAMUNO | I4: EL_GUARCO
A5: HEREDIA | B5: HEREDIA_ | C5: BARVA | D5: SANTO_DOMINGO | E5: SANTA_BÁRBARA | F5: SAN_RAFAEL | G5: SAN_ISIDRO | H5: BELÉN | I5: FLORES | J5: SAN_PABLO | K5: SARAPIQUÍ
A6: GUANACASTE | B6: LIBERIA | C6: NICOYA | D6: SANTA_CRUZ | E6: BAGACES | F6: CARRILLO | G6: CAÑAS | H6: ABANGARES | I6: TILARAN | J6: NANDAYURE | K6: LA_CRUZ | L6: HOJANCHA
A7: PUNTARENAS | B7: PUNTARENAS_ | C7: ESPARZA | D7: BUENOS_AIRES | E7: MONTES_DE_ORO | F7: OSA | G7: AGUIRRE | H7: GOLFITO | I7: COTO_BRUS | J7: PARRITA | K7: CORREDORES | L7: GARABITO
A8: LIMÓN | B8: LIMÓN_ | C8: POCOCI | D8: SIQUIRRES | E8: TALAMANCA | F8: MATINA | G8: GUÁCIMO
A10: SAN JOSE
A12: SAN_JOSE | B12: Escazú | C12: Desamparados | D12: Santiago | E12: San Marcos | F12: Aserri | G12: MORA | H12: GOICOECHEA | I12: SANTA ANA | J12: ALAJUELITA | K12: VASQUEZ DE CORONADO | L12: ACOSTA | M12: TIBAS | N12: MORAVIA | O12: MONTES DE OCA | P12: TURRUBARES | Q12: DOTA | R12: CURRIDABAT | S12: PEREZ ZELEDON | T12: LEON CORTES
A13: El Carmen | B13: San Antonio | C13: San Miguel | D13: Mercedes Sur | E13: San Lorenzo | F13: Tarbaca | G13: Colón | H13: Guadalupe | I13: Santa Ana | J13: Alajuelita | K13: San Isidro | L13: San Ignacio | M13: San Juan | N13: San Vicente | O13: San Pedro | P13: San Pablo | Q13: Santa María | R13: Curridabat | S13: San Isidro de El General | T13: San Pablo
A14: Merced | B14: San Rafael | C14: San Juan de Dios | D14: Barbacoas | E14: San Carlos | F14: Vuelta de Jorco | G14: Guayabo | H14: San Francisco | I14: Salitral | J14: San Josecito | K14: San Rafael | L14: Guaitíl | M14: Cinco Esquinas | N14: San Jerónimo | O14: Sabanilla | P14: San Pedro | Q14: Jardín | R14: Granadilla | S14: General | T14: San Andrés
A15: Hospital | C15: San Rafael Arriba | D15: Grifo Alto | F15: San Gabriel | G15: Tabarcia | H15: Calle Blancos | I15: Pozos | J15: San Antonio | K15: Dulce Nombre de Jesús | L15: Palmichal | M15: Anselmo Llorente | N15: Trinidad | O15: Mercedes | P15: San Juan de Mata | Q15: Copey | R15: Sánchez | S15: Daniel Flores | T15: Llano Bonito
A16: Catedral | C16: San Antonio | D16: San Rafael | F16: Legua | G16: Piedras Negras | H16: Mata de Plátano | I16: Uruca | J16: Concepción | K16: Patalillo | L16: Cangrejal | M16: León XIII | O16: San Rafael | P16: San Luis | R16: Tirrases | S16: Rivas | T16: San Isidro
A17: Zapote | C17: Frailes | D17: Candelarita | F17: Monterrey | G17: Picagres | H17: Ipís | I17: Piedades | J17: San Felipe | K17: Cascajal | L17: Sabanillas | M17: Colima | S17: San Pedro | T17: Santa Cruz
A18: San Fco.de Dos Ríos | C18: Patarrá | D18: Desamparaditos | F18: Salitrillos | H18: Rancho Redondo | I18: Brasil | S18: Platanares | T18: San Antonio
A19: Uruca | C19: San Cristóbal | D19: San Antonio | H19: Purral | S19: Pejibaye
A20: Mata Redonda | C20: Rosario | D20: Chires | S20: Cajón
A21: Pavas | C21: Damas | S21: Barú
A22: Hatillo | C22: San Rafael Abajo | S22: Río Nuevo
A23: San Sebastián | C23: Gravilias | S23: Páramo
A25: ALAJUELA
A27: ALAJUELA | B27: SAN RAMON | C27: GRECIA | D27: SAN MATEO | E27: ATENAS | F27: NARANJO | G27: PALMARES | H27: POAS | I27: OROTINA | J27: SAN CARLOS | K27: ALFARO RUIZ | L27: VALVERDE VEGA | M27: UPALA | N27: LOS CHILES | O27: GUATUSO
A28: Alajuela | B28: San Ramón | C28: Grecia | D28: San Mateo | E28: Atenas | F28: Naranjo | G28: Palmares | H28: San Pedro | I28: Orotina | J28: Quesada | K28: Zarcero | L28: Sarchí Norte | M28: Upala | N28: Los Chiles | O28: San Rafael
A29: San José | B29: Santiago | C29: San Isidro | D29: Desmonte | E29: Jesús | F29: San Miguel | G29: Zaragoza | H29: San Juan | I29: Mastate | J29: Florencia | K29: Laguna | L29: Sarchí Sur | M29: Aguas Claras | N29: Caño Negro | O29: Buenavista
A30: Carrizal | B30: San Juan | C30: San José | D30: Jesús María | E30: Mercedes | F30: San José | G30: Buenos Aires | H30: San Rafael | I30: Hacienda Vieja | J30: Buenavista | K30: Tapezco | L30: Toro Amarillo | M30: San José o Pizote | N30: El Amparo | O30: Cote
A31: San Antonio | B31: Piedades Norte | C31: San Roque | E31: San Isidro | F31: Cirrí Sur | G31: Santiago | H31: Carrillos | I31: Coyolar | J31: Aguas Zarcas | K31: Guadalupe | L31: San Pedro | M31: Bijagua | N31: San Jorge
A32: Guácima | B32: Piedades Sur | C32: Tacares | E32: Concepción | F32: San Jerónimo | G32: Candelaria | H32: Sabana Redonda | I32: Ceiba | J32: Venecia | K32: Palmira | L32: Rodríguez | M32: Delicias
A33: San Isidro | B33: San Rafael | C33: Río Cuarto | E33: San José | F33: San Juan | G33: Esquipulas | J33: Pital | K33: Zapote | M33: Dos Ríos
A34: Sabanilla | B34: San Isidro | C34: Puente de Piedra | E34: Santa Eulalia | F34: Rosario | G34: Granja | J34: Fortuna | K34: Brisas | M34: Yolillal
A35: San Rafael | B35: Angeles | C35: Bolívar | J35: Tigra
A36: Río Segundo | B36: Alfaro | J36: Palmera
A37: Desamparados | B37: Volio | J37: Venado
A38: Turrúcares | B38: Concepción | J38: Cutris
A39: Tambor | B39: Zapotal | J39: Monterrey
A40: La Garita | B40: Peñas Blancas | J40: Pocosol
A41: Sarapiquí
A43: CARTAGO
A45: CARTAGO | B45: PARAISO | C45: LA UNION | D45: JIMENEZ | E45: TURRIALBA | F45: ALVARADO | G45: OREAMUNO | H45: EL GUARCO
A46: Oriental | B46: Paraíso | C46: Tres Ríos | D46: Juan Viñas | E46: Turrialba | F46: Pacayas | G46: San Rafael | H46: El Tejar
A47: Occidental | B47: Santiago | C47: San Diego | D47: Tucurrique | E47: La Suiza | F47: Cervantes | G47: Cot | H47: San Isidro
A48: Carmen | B48: Orosi | C48: San Juan | D48: Pejibaye | E48: Peralta | F48: Capellades | G48: Potrero Cerrado | H48: Tobosi
A49: San Nicolás | B49: Cachí | C49: San Rafael | E49: Santa Cruz | G49: Cipreses | H49: Patio de Agua
A50: Aguacaliente o San Fco. | C50: Concepción | E50: Santa Teresita | G50: Santa Rosa
A51: Guadalupe o Arenilla | C51: Dulce Nombre | E51: Pavones
A52: Corralillo | C52: San Ramón | E52: Tuis
A53: Tierra Blanca | C53: Río Azul | E53: Tayutic
A54: Dulce Nombre | E54: Santa Rosa
A55: Llano Grande | E55: Tres Equis
A56: Quebradilla
A58: HEREDIA
A60: HEREDIA | B60: BARVA | C60: SANTO DOMINGO | D60: SANTA BARBARA | E60: SAN RAFAEL | F60: SAN ISIDRO | G60: BELEN | H60: FLORES | I60: SAN PABLO | J60: SARAPIQUI
A61: Heredia | B61: Barva | C61: Santo Domingo | D61: Santa Bárbara | E61: San Rafael | F61: San Isidro | G61: San Antonio | H61: San Joaquín | I61: San Pablo | J61: Puerto Viejo
A62: Mercedes | B62: San Pedro | C62: San Vicente | D62: San Pedro | E62: San Josecito | F62: San José | G62: Rivera | H62: Barrantes | J62: La Vírgen
A63: San Francisco | B63: San Pablo | C63: San Miguel | D63: San Juan | E63: Santiago | F63: Concepción | G63: Asunción | H63: Llorente | J63: Horquetas
A64: Ulloa | B64: San Roque | C64: Paracito | D64: Jesús | E64: Angeles | F64: San Francisco | J64: Llanuras del Gaspar
A65: Vara Blanca | B65: Santa Lucía | C65: Santo Tomás | D65: Santo Domingo | E65: Concepción | J65: Cureña
B66: San José de La Montaña | C66: Santa Rosa | D66: Purabá
C67: Tures
C68: Pará
A70: GUANACASTE
A72: LIBERIA | B72: NICOYA | C72: SANTA CRUZ | D72: BAGACES | E72: CARRILLO | F72: CAÑAS | G72: ABANGARES | H72: TILARAN | I72: NANDAYURE | J72: LA CRUZ | K72: HOJANCHA
A73: Liberia | B73: Nicoya | C73: Santa Cruz | D73: Bagaces | E73: Filadelfia | F73: Cañas | G73: Juntas | H73: Tilarán | I73: Carmona | J73: La Cruz | K73: Hojancha
A74: Cañas Dulces | B74: Mansión | C74: Bolsón | D74: Fortuna | E74: Palmira | F74: Palmira | G74: Sierra | H74: Quebrada Grande | I74: Santa Rita | J74: Santa Cecilia | K74: Monte Romo
A75: Mayorga | B75: San Antonio | C75: 27 de Abril | D75: Mogote | E75: Sardinal | F75: San Miguel | G75: San Juan | H75: Tronadora | I75: Zapotal | J75: Garita | K75: Puerto Carrillo
A76: Nacascolo | B76: Quebrada Honda | C76: Tempate | D76: Río Naranjo | E76: Belén | F76: Bebedero | G76: Colorado | H76: Santa Rosa | I76: San Pablo | J76: Santa Elena | K76: Huacas
A77: Curubandé | B77: Sámara | C77: Cartagena | F77: Porozal | H77: Líbano | I77: Porvenir
B78: Nosara | C78: Cuajiniquil | H78: Tierras Morenas | I78: Bejuco
B79: Belén de Nosarita | C79: Diriá | H79: Arenal
C80: Cabo Velas | H80: Cabeceras
C81: Tamarindo
A83: PUNTARENAS
A85: PUNTARENAS | B85: ESPARZA | C85: BUENOS AIRES | D85: MONTES DE ORO | E85: OSA | F85: AGUIRRE | G85: GOLFITO | H85: COTO BRUS | I85: PARRITA | J85: CORREDORES | K85: GARABITO
A86: Puntarenas | B86: Espíritu Santo | C86: Buenos Aires | D86: Miramar | E86: Puerto Cortés | F86: Quepos | G86: Golfito | H86: San Vito | I86: Parrita | J86: Corredor | K86: Jacó
A87: Pitahaya | B87: San Juan Grande | C87: Volcán | D87: Unión | E87: Palmar | F87: Savegre | G87: Puerto Jiménez | H87: Sabalito | J87: La Cuesta | K87: Tárcoles
A88: Chomes | B88: Macacona | C88: Potrero Grande | D88: San Isidro | E88: Sierpe | F88: Naranjito | G88: Guaycará | H88: Agua Buena | J88: Canoas
A89: Lepanto | B89: San Rafael | C89: Boruca | E89: Bahía Ballena | G89: Pavón | H89: Limoncito | J89: Laurel
A90: Paquera | B90: San Jerónimo | C90: Pilas | E90: Piedras Blancas | H90: Pittier
A91: Manzanillo | C91: Colinas
A92: Guacimal | C92: Chánguena
A93: Barranca | C93: Biolley
A94: Monteverde
A95: Cóbano
A96: Chacarita
A97: Chira
A98: Acapulco
A100: LIMON
A102: LIMON | B102: POCOCI | C102: SIQUIRRES | D102: TALAMANCA | E102: MATINA | F102: GUACIMO
A103: Limón | B103: Guápiles | C103: Siquirres | D103: Bratsi | E103: Matina | F103: Guácimo
A104: Valle La Estrella | B104: Jiménez | C104: Pacuarito | D104: Sixaola | E104: Batán | F104: Mercedes
A105: Río Blanco | B105: Rita | C105: Florida | D105: Cahuita | E105: Carrandí | F105: Pocora
A106: Matama | B106: Roxana | C106: Germania | F106: Río Jiménez
B107: Cariari | C107: Cairo | F107: Duacarí
B108: Colorado | C108: Alegría

Sheet PARÁMETROS
Y2: TIPO DE ZONA
B3: SI | C3: X | D3: CONDICIÓN | E3: MEDIOS DE NOTIFICACIÓN | I3: CUMPLE | J3: APLICA O NO | K3: USOS | Q3: GESTIÓN | U3: Permiso que señala la Ley General de Salud | Y3: Habitación.
B4: NO | D4: Apoderado | E4: Fax | I4: SI | J4: Aplica | K4: USO CONFORME | U4: Certificado Veterinario de Operación requerido en la Ley General del Servicio Nacional de Salud Animal. | Y4: Servicios de oficina.
B5: NA | D5: Representante Legal | E5: Correo electrónico | I5: NO | J5: No aplica | K5: USO NO CONFORME | Y5: Servicios para el comercio y abasto.
D6: Propietario | E6: Dirección representante o apoderado | Y6: Servicios educativos y administrativos oficinas
D7: Persona física | I7: No aplica | Y7: Servicios para la salud.
Y8: Servicios comunales
B10: PROVINCIA-CANTON-DISTRITO | C10: PROVINCIA | D10: PROVINCIA-CANTÓN | F10: HORARIO | I10: Sección | J10: División | K10: Grupo | L10: Clase | N10: El Permiso Sanitario de Funcionamiento se otorga a los establecimientos que albergan las siguientes actividades | O10: Equivalencia al CIIU 3 | P10: Riesgo Sanitario Ministerio de Salud | U10: Actividades de Comercialización y Servicios del SENASA | Y10: Servicios religiosos.
F11: 00:00 am | Q11: 1 | Y11: Servicios para la cultura y el deporte.
B12: SAN JOSE | C12: SAN JOSÉ | D12: San José | F12: 01:00 am | Q12: 2 | U12: Columna2 | V12: Columna12 | Y12: Servicios de alojamiento y turismo.
B13: SAN JOSE | C13: ALAJUELA | D13: SAN JOSE | F13: 02:00 am | Q13: 3 | U13: Venta al por mayor de carne y productos cárnicos | V13: 40201 | Y13: Instalaciones para la seguridad.
B14: El Carmen | C14: CARTAGO | D14: ESCAZU | F14: 03:00 am | Q14: 4 | U14: Expendio de carne y productos cárnicos | V14: 40601 | Y14: Servicios funerarios.
B15: Merced | C15: HEREDIA | D15: DESAMPARADOS | F15: 04:00 am | Q15: 5 | U15: Venta al por menor de medicamentos veterinarios | V15: 40801 | Y15: Transporte y comunicación.
B16: Hospital | C16: GUANACASTE | D16: PURISCAL | F16: 05:00 am | Q16: 6 | U16: Venta al por menor de productos destinados a la alimentación animal | V16: 40901 | Y16: Industria.
B17: Catedral | C17: PUNTARENAS | D17: TARRAZU | F17: 06:00 am | Q17: 7 | U17: Estética de mascotas | V17: 60301 | Y17: Instalaciones para la infraestructura.
B18: Zapote | C18: LIMÓN | D18: ASERRI | F18: 07:00 am | Q18: 8 | U18: Recibo, clasificación y primera venta de productos pesqueros. | V18: 40202 | Y18: Agrícola
B19: San Fco.de Dos Ríos | D19: MORA | F19: 08:00 am | Q19: 9 | U19: Venta al por mayor de productos lácteos | V19: 40203
B20: Uruca | D20: GOICOECHEA | F20: 09:00 am | Q20: 10 | U20: Venta al por mayor de huevo fresco | V20: 40204
B21: Mata Redonda | D21: SANTA ANA | F21: 10:00 am | Q21: 11 | U21: Envasado y Venta al por mayor de miel y productos apícolas (polen, propóleo, jalea real) | V21: 40205
B22: Pavas | D22: ALAJUELITA | F22: 11:00 am | Q22: 12 | U22: Venta al por mayor de productos pesqueros | V22: 40206
B23: Hatillo | D23: VASQUEZ DE CORONADO | F23: 12:00 m.d | Q23: 13 | U23: Envasado y venta al por mayor de jarabes | V23: 40207
B24: San Sebastián | D24: ACOSTA | F24: 01:00 pm | Q24: 14 | U24: Venta al por mayor de medicamentos veterinarios | V24: 40301
B25: ESCAZU | D25: TIBAS | F25: 02:00 pm | Q25: 15 | U25: Venta al por mayor de productos afines | V25: 40303
B26: Escazú | D26: MORAVIA | F26: 03:00 pm | Q26: 16 | U26: Venta al por mayor de medicamentos veterinarios de medicina alternativa | V26: 40304
B27: San Antonio | D27: MONTES DE OCA | F27: 04:00 pm | Q27: 17 | U27: Venta al por mayor de productos afines de medicina alternativa | V27: 40305
B28: San Rafael | D28: TURRUBARES | F28: 05:00 pm | Q28: 18 | U28: Venta al por mayor de alimentos, mezclas y premezclas para animales | V28: 40401
B29: DESAMPARADOS | D29: DOTA | F29: 06:00 pm | Q29: 19 | U29: Venta al por mayor de materias primas para alimentación animal | V29: 40402
B30: Desamparados | D30: CURRIDABAT | F30: 07:00 pm | Q30: 20 | U30: Reempaque de alimentos destinados a la alimentación animal | V30: 40403
B31: San Miguel | D31: PEREZ ZELEDON | F31: 08:00 pm | Q31: 21 | U31: Venta al por menor de mascotas o animales domésticos | V31: 40501 | Y31: 4. Servicios para la salud.
B32: San Juan de Dios | D32: LEON CORTES | F32: 09:00 pm | Q32: 22 | U32: Venta al por menor de animales acuáticos ornamentales | V32: 40503
B33: San Rafael Arriba | F33: 10:00 pm | Q33: 23 | U33: Venta al por menor de animales silvestres autorizados | V33: 40504 | Y33: 4.1 Consultorios médicos.
B34: San Antonio | D34: Alajuela | F34: 11:00 pm | Q34: 24 | U34: Expendio de productos pesqueros | V34: 40602 | Y34: 4.2 Clínicas y centros de salud.
B35: Frailes | D35: ALAJUELA | F35: 11:59 pm | Q35: 25 | U35: Expendio de lácteos | V35: 40603 | Y35: 4.3 Hospitales, sanatorios, maternidades, y centros de rehabilitación.
B36: Patarrá | D36: SAN RAMON | Q36: 26 | U36: Expendio de huevos | V36: 40604
B37: San Cristóbal | D37: GRECIA | F37: CONICIÓN DEL LOCAL | Q37: 27 | U37: Expendio de miel y productos apícolas | V37: 40605 | Y37: 5. Servicios para la educación.
B38: Rosario | D38: SAN MATEO | Q38: 28 | U38: Reempaque de productos de origen animal con fines de venta minorista | V38: 40606
B39: Damas | D39: ATENAS | F39: Excelente | Q39: 29 | U39: Expendio de carne de caballo | V39: 40607 | Y39: 5.1 Educación preparatoria y educación primaria.
B40: San Rafael Abajo | D40: NARANJO | F40: Buena | Q40: 30 | U40: Venta al por menor de productos afines | V40: 40802 | Y40: 5.2 Educación media: académica, de artes y oficios y tecnológicas o vocacionales.
B41: Gravilias | D41: PALMARES | F41: Regular | Q41: 31 | U41: Venta al por menor de medicamentos de medicina alternativa | V41: 40803 | Y41: 5.3 Educación superior, institutos técnicos, centros de capacitación, academias profesionales, colegios universitarios y universidades.
B42: PURISCAL | D42: POAS | F42: Deficiente | Q42: 32 | U42: Venta al por menor de productos afines de medicina alternativa | V42: 40804 | Y42: 5.4 Educación física y artística: escuelas de natación, música, baile, artes marciales, modelos, pintura, escultura, actuación y fotografía.
B43: Santiago | D43: OROTINA | Q43: 33 | U43: Reempaque de productos destinados a la alimentación animal en punto de venta | V43: 40902
B44: Mercedes Sur | D44: SAN CARLOS | F44: POSESIÓN INSTALACIONES | Q44: 34 | U44: Servicio de hospitalización veterinaria | V44: 60101 | Y44: 6. Servicios religiosos.
B45: Barbacoas | D45: ALFARO RUIZ | Q45: 35 | U45: Servicio de clínica y cirugía veterinaria | V45: 60102
B46: Grifo Alto | D46: VALVERDE VEGA | F46: Propio | Q46: 36 | U46: Servicio de laboratorio y diagnóstico | V46: 60103 | Y46: 6.1 Instalaciones religiosas: templos y lugares de cultos, conventos y edificaciones para la enseñanza religiosa.
B47: San Rafael | D47: UPALA | F47: Arrendado | Q47: 37 | U47: Servicio de consulta y cirugía menor | V47: 60104
B48: Candelarita | D48: LOS CHILES | F48: Concesionado | Q48: 38 | U48: Servicio de clínica veterinaria ambulante | V48: 60105 | Y48: 7. Servicios para la cultura y el deporte.
B49: Desamparaditos | D49: GUATUSO | F49: Otro (especifique): | Q49: 39 | U49: Estética de mascotas móvil | V49: 60302
B50: San Antonio | Q50: 40 | Y50: 7.1 Centros de espectáculos y recreativos: auditorios, teatros, cines, salas de música, salas de video juegos, “café Internet” y similares.
B51: Chires | D51: Cartago | F51: SENASA | Q51: 41 | Y51: 7.2 Centros culturales: bibliotecas, museos, galerías de arte, filmotecas, cinematecas, casas de cultura, centros comunitarios.
B52: TARRAZU | D52: CARTAGO | F52: Subsistencia | Q52: 42 | Y52: 7.3 Instalaciones para la recreación y el deporte: gimnasia, “squash”, billares, salas de juegos de mesa.
B53: San Marcos | D53: PARAISO | F53: Pequeña | Q53: 43 | Y53: 7.4 Instalaciones para deportes de exhibición al aire libre: estadios, hipódromos, autódromos, velódromos, plaza de toros, polígonos y similares.
B54: San Lorenzo | D54: LA UNION | F54: Mediana | Q54: 44 | Y54: 7.5 Clubes, instalaciones campestres, campamentos y paraderos turísticos.
B55: San Carlos | D55: JIMENEZ | F55: Grande | Q55: 45 | Y55: 7.6 Parques, jardines, juegos infantiles.
B56: ASERRI | D56: TURRIALBA | F56: No aplica | Q56: 46
B57: Aserrí | D57: ALVARADO | Q57: 47 | Y57: 8. Servicios de alojamiento y turismo.
B58: Tarbaca | D58: OREAMUNO | F58: MES | G58: DIA | Q58: 48
B59: Vuelta de Jorco | D59: EL GUARCO | F59: Enero | G59: 1 | Q59: 49 | Y59: 8.1 Hoteles, moteles, albergues, casas de huéspedes, orfanatos, asilos.
B60: San Gabriel | F60: Febrero | G60: 2 | Q60: 50 | Y60: 8.2 Atracciones turísticas.
B61: Legua | D61: Heredia | F61: Marzo | G61: 3 | Q61: 51
B62: Monterrey | D62: HEREDIA | F62: Abril | G62: 4 | Q62: 52 | Y62: 9. Instalaciones para la seguridad.
B63: Salitrillos | D63: BARVA | F63: Mayo | G63: 5 | Q63: 53
B64: MORA | D64: SANTO DOMINGO | F64: Junio | G64: 6 | Q64: 54 | Y64: 9.1 Instalaciones para la seguridad pública: estación de bomberos, cruz roja, protección civil, policía.
B65: Colón | D65: SANTA BARBARA | F65: Julio | G65: 7 | Q65: 55
B66: Guayabo | D66: SAN RAFAEL | F66: Agosto | G66: 8 | Q66: 56 | Y66: 10. Servicios funerarios.
B67: Tabarcia | D67: SAN ISIDRO | F67: Septiembre | G67: 9 | Q67: 57
B68: Piedras Negras | D68: BELEN | F68: Octubre | G68: 10 | Q68: 58 | Y68: 10.1 Funerarias y salas de velación.
B69: Picagres | D69: FLORES | F69: Noviembre | G69: 11 | Q69: 59 | Y69: 10.2 Cementerios, panteones y crematorios.
B70: GOICOECHEA | D70: SAN PABLO | F70: Diciembre | G70: 12 | Q70: 60
B71: Guadalupe | D71: SARAPIQUI | G71: 13 | Q71: 61 | Y71: 11. Transporte y comunicación.
B72: San Francisco | F72: AÑO | G72: 14 | Q72: 62
B73: Calle Blancos | D73: Guanacaste | F73: 2018 | G73: 15 | Q73: 63 | Y73: 11.1 Estacionamientos.
B74: Mata de Plátano | D74: LIBERIA | F74: 2019 | G74: 16 | Q74: 64 | Y74: 11.2 Garajes de buses y terminales de transporte de carga y pasajeros.
B75: Ipís | D75: NICOYA | F75: 2020 | G75: 17 | Q75: 65 | Y75: 11.3 Atracaderos turísticos.
B76: Rancho Redondo | D76: SANTA CRUZ | F76: 2021 | G76: 18 | Q76: 66 | Y76: 11.4 Centrales telefónicas, torres de transmisión, antenas y torres de radio, líneas de transmisión.
B77: Purral | D77: BAGACES | F77: 2022 | G77: 19 | Q77: 67
B78: SANTA ANA | D78: CARRILLO | F78: 2023 | G78: 20 | Q78: 68 | Y78: 12. Industria.
B79: Santa Ana | D79: CAÑAS | F79: 2024 | G79: 21 | Q79: 69
B80: Salitral | D80: ABANGARES | F80: 2025 | G80: 22 | Q80: 70 | Y80: 12.1 Industria inofensiva y producción artesanal: industria y talleres localizados dentro de las viviendas y que no son contaminantes.
B81: Pozos | D81: TILARAN | F81: 2026 | G81: 23 | Q81: 71 | Y81: 12.2 Canteras, tajos, caleras y similares.
B82: Uruca | D82: NANDAYURE | F82: 2027 | G82: 24 | Q82: 72
B83: Piedades | D83: LA CRUZ | F83: 2028 | G83: 25 | Q83: 73 | Y83: 13. Instalaciones para la infraestructura.
B84: Brasil | D84: HOJANCHA | F84: 2029 | G84: 26 | Q84: 74
B85: ALAJUELITA | F85: 2030 | G85: 27 | Q85: 75 | Y85: 13.1 Planta, estación, subestación de infraestructura básica: bombas, pozos, captaciones, tanques reguladores, lagunas de control y regulación, subestaciones eléctricas, líneas de transmisión y distribución, líneas de distribución telefónica, televisión e Internet.
B86: Alajuelita | D86: Puntarenas | F86: 2031 | G86: 28 | Q86: 76 | Y86: 13.2 Depósito de desechos sólidos, plantas de tratamiento, basureros, rellenos sanitarios, tuberías de distribución: agua
B87: San Josecito | D87: PUNTARENAS | F87: 2032 | G87: 29 | Q87: 77 | Y87: potable, pluvial y sanitario.
B88: San Antonio | D88: ESPARZA | F88: 2033 | G88: 30 | Q88: 78
B89: Concepción | D89: BUENOS AIRES | G89: 31 | Q89: 79
B90: San Felipe | D90: MONTES DE ORO | Q90: 80
B91: VASQUEZ DE CORONADO | D91: OSA | Q91: 81
B92: San Isidro | D92: AGUIRRE | Q92: 82
B93: San Rafael | D93: GOLFITO | Q93: 83
B94: Dulce Nombre de Jesús | D94: COTO BRUS | Q94: 84
B95: Patalillo | D95: PARRITA | Q95: 85
B96: Cascajal | D96: CORREDORES | Q96: 86
B97: ACOSTA | D97: GARABITO | Q97: 87
B98: San Ignacio | Q98: 88
B99: Guaitíl | D99: Limón | Q99: 89
B100: Palmichal | D100: LIMON | Q100: 90
B101: Cangrejal | D101: POCOCI | Q101: 91
B102: Sabanillas | D102: SIQUIRRES | Q102: 92
...

Sheet  FMT 104 TOMA DATOS
B1: Formulario único para Apertura, Actualización y Renovación de Empresas para actividades de bajo riesgo del Ministerio de Salud y de Comercialización y Servicios de SENASA - en los cantones de Abangares, Cañas, Tilarán, Bagaces, Liberia y La Cruz de Región Chorotega
K7: CONDICIÓN | S7: Sólo Licencia para la comercialización de bebidas con contenido alcohólico
B9: A. DATOS DEL SOLICITANTE O REPRESENTANTE LEGAL
B10: 1) Nombre del solicitante:
B11: 2) Cédula de identidad: | M11: 3) En calidad de | R11: Representante Legal
B12: de la sociedad denominada (Razón social):
R13: Cédula Jurídica:
B14: 4) Ubicación: | F14: Provincia: | R14: Cantón:
B15: Distrito: | R15: Barrio:
B16: 5) Dirección exacta:
B18: 6) Teléfono domicilio: | R18: 7) Fax:
B19: 8) Celular: | L19: 9) Correo electrónico:
B20: 10) Medio para notificaciones: | J20: Correo electrónico
B21: 11) Firmo como solicitante de la gestión que aquí se detalla:
B22: B. DATOS DEL PROPIETARIO DEL LOCAL O ESTABLECIMIENTO
B23: 12) Nombre del propietario:
B24: 13) N° Cédula: | M24: 14) Representante Legal:
B25: 15) Cédula de identidad: | N25: 16) Teléfono domicilio:
B26: 17) Fax: | K26: 18) Correo electrónico:
B27: C. DATOS DEL ESTABLECIMIENTO O PROPIEDAD DONDE SE DESARROLLA LA ACTIVIDAD
B28: 19) Nombre comercial:
B29: 20) Actividad para PFS :
B30: 21) Actividad principal para SENANSA:
B31: 22) Actividad principal:
B32: 23) Actividades secundarias:
B33: 24) Requiere licencia para la comercialización de bebidas con contenido alcohólico:
B34: 25) Actividad principal para la comercialización de bebidas con contenido alcohólico:
B36: 26) Ubicación: | F36: Provincia: | R36: Cantón:
B37: Distrito: | R37: Barrio:
B38: 27) Dirección exacta: | H38: 150 este CCSS
B39: 28) Número de Finca: | Q39: 28) Número de Plano:
B40: 29) Área en m2: | Q40: 30) Fecha inicio operaciones:
B41: 31) Horario: | F41: Apertura | M41: Cierre | T41: 32) Cantidad de Trabajadores:
B42: Hombres | G42: Mujeres | J42: =+AB41-E42 -> 0 | L42: ¿Este dato incluye al solicitante en la cantidad de trabajadores?
B43: 33) Página web: | Q43: 34) Condición del local
B44: 35) El inmueble en el que se pretende desarrollar la actividad es:
B46: D. CONDICIONES ESPERADAS AL INICIO DE OPERACIONES
B47: 36) Mercadería o producto elaborado | L47: ………………………………………………………. | W47: 1000000
B48: 37) Materias primas | L48: ………………………………………………………. | W48: 1000000
B49: 38) Mobiliario, maquinaria y equipo | L49: ………………………………………………………. | W49: 2000000
B50: 39) Edificio e instalaciones | L50: ………………………………………………………. | W50: 150000000
B51: 40) Total mensual de alquileres | L51: ………………………………………………………. | W51: 3000000
B52: 41) Total mensual de salarios | L52: ………………………………………………………. | W52: 6500000
B53: 42) Proyección de ingresos mensual | L53: ………………………………………………………. | W53: 25000000
B54: E. PARA USO DE LA OFICINA
B55: 43) Verificación de requisitos:
B56: 43.1 Listado de requisitos entregados para RESOLUCIÓN DE UBICACIÓN (para uso interno) | AB56: CUMPLE
B57: Formulario único y declaración jurada debidamente llenos. | AB57: SI
B58: Presentar la cédula de identidad o cédula de residencia libre de condición o DIMEX en caso de ser extranjero | AB58: SI
B59: Presentar certificación de personería jurídica | AB59: SI
B60: Plano catastrado (se revisa internamente en la municipalidad, pero si el mismo no se encuentra en la base de datos el solicitante deberá presentarlo físicamente). | AB60: SI
B61: Presentar original del contrato de arrendamiento o autorización del propietario (autenticada por abogado). | AB61: SI
B62: 43.2 Revisión interna (usuario no debe presentarlos pero si su cumplimiento)
B63: Que el solicitante se encuentre al día en los pagos correspondientes a la CCSS, FODESAF y HACIENDA | AB63: SI
B64: Consulta por número de finca emitida por Registro Nacional (se revisa internamente en la municipalidad). | AB64: SI
B65: Que el solicitante y el propietario del inmueble donde se va a desarrollar la actividad, estén al día en el pago de impuestos, tasas o multas municipales. | AB65: SI
B66: Las propiedades a nombre tanto del propietario del inmueble como de quien pretenda desarrollar la actividad comercial, tienen una declaración
B67: de valor vigente, de conformidad con lo establecido en la Ley del Impuesto Sobre Bienes Inmuebles. | AB67: SI
B68: 43.3 Listado de requisitos entregados para LICENCIA COMERCIAL (para uso interno)
B69: Póliza de riesgos del trabajo emitida por entidad aseguradora o exoneración. Art 202 del Código de Trabajo. | AC69: SI
B70: Estar inscrito como contribuyente ante el Ministerio de Hacienda | AC70: SI
B71: Cien colones en timbres fiscales o pago del entero. | AC71: SI
B72: Presentar comprobante de pago a favor del Servicio Nacional de Salud Animal del MAG. | AC72: SI
B73: Presentar comprobante de pago a favor del Ministerio de Salud, según corresponda, o bien el comprobante de exoneración del
B74: pago por el IMAS. | AC74: SI
B75: Regencia o asesoría veterinaria aprobada por el Colegio de Médicos Veterinarios (cuando aplique) | AC75: SI
B76: Presentar Autorización por concepto de derechos de autor ACAM (cuando aplique) | AC76: SI
B77: En el caso de los traspasos de licencias comerciales deberá evidenciarse la voluntad de las partes para ceder y aceptar los derechos asociados a una licencia
B78: comercial. Las firmas correspondientes deberán estar debidamente autenticadas por abogado; salvo que la manifestación de voluntad sea firmada por ambas partes
B79: en presencia de un funcionario municipal. | AC79: SI
B80: Certificado de Idoneidad Técnica para salones de belleza, barbería, peluquería y afines (cuando aplique) | AC80: SI
B81: En el caso de actividades que requieran la correspondiente autorización de la Dirección General de Minería, del Ministerio de
B82: Ambiente y Energía o la Secretaria Técnica Nacional Ambiental; deberá aportarse una certificación de la misma. | AC82: SI
B83: El Ministerio de Salud revisará en el sistema que el solicitante no se encuentra moroso en el Registro de Infractores, Ley 9028. | AC83: SI
B85: Funcionario que recibe solicitud: | K85: Carolay Solera Calvo | W85: Fecha: | Y85: =NOW() -> 45349.511
B87: OBSERVACIONES: | K87: AQUÍ SELLO Y FIRMA DE RECIBIDO

Sheet CONSTANCIA REQUISITOS
B2: MUNICIPALIDAD DE TILARÁN
B3: Proceso Servicios Ciudadanos y Técnicos
B4: Unidad Plataforma de Servicios
B6: CONSTANCIA DE VERIFICACIÓN DE REQUISITOS
B8: El(la) abajo firmante, funcionaro(a) municipal, hace constar que ante ésta administración se trámita licencia comercial
B9: desde el | E9: =+' FMT 104 TOMA DATOS'!Y85 -> 45349.511 | I9: bajo las siguientes condiciones:
B11: Nombre del solicitante: | I11: =+' FMT 104 TOMA DATOS'!I10:AD10 -> 0
B12: Cédula de identidad: | H12: =+' FMT 104 TOMA DATOS'!H11 -> 0 | M12: En calidad de | R12: =+' FMT 104 TOMA DATOS'!R11:AD11 -> Representante Legal
B13: de la sociedad denominada (Razón social): | M13: =+' FMT 104 TOMA DATOS'!M12:AD12 -> 0
B14: =+' FMT 104 TOMA DATOS'!B13:Q13 -> 0 | R14: Cédula Jurídica: | W14: =+' FMT 104 TOMA DATOS'!X13 -> 0
B15: Teléfono domicilio: | H15: =+' FMT 104 TOMA DATOS'!H18 -> 0 | R15: Fax: | T15: =+' FMT 104 TOMA DATOS'!T18:AD18 -> 0
B16: Celular: | E16: =+' FMT 104 TOMA DATOS'!E19:K19 -> 0 | L16: Correo electrónico: | R16: =+' FMT 104 TOMA DATOS'!R19:AD19 -> 0
B17: Nombre comercial: | G17: =+' FMT 104 TOMA DATOS'!H28 -> 0
B18: Detalle de actividades: | H18: =+' FMT 104 TOMA DATOS'!I29 -> 0
B19: Número de Finca: | G19: =+' FMT 104 TOMA DATOS'!H39 -> 0
B21: Verificado el expediente de la solicitud, se constata la presentación de los siguientes requisitos:
B23: Listado de requisitos entregados para RESOLUCIÓN DE UBICACIÓN (para uso interno) | Z23: CUMPLE
B24: =+' FMT 104 TOMA DATOS'!B57 -> Formulario único y declaración jurada debidamente llenos. | Z24: =+' FMT 104 TOMA DATOS'!AB57 -> SI
B25: =+' FMT 104 TOMA DATOS'!B58 -> Presentar la cédula de identidad o cédula de residencia libre de condición o DIMEX en caso de ser extranjero | Z25: =+' FMT 104 TOMA DATOS'!AB58 -> SI
B26: =+' FMT 104 TOMA DATOS'!B59 -> Presentar certificación de personería jurídica | Z26: =+' FMT 104 TOMA DATOS'!AB59 -> SI
B27: =+' FMT 104 TOMA DATOS'!B60 -> Plano catastrado (se revisa internamente en la municipalidad, pero si el mismo no se encuentra en la base de datos el solicitante deberá presentarlo físicamente). | Z27: =+' FMT 104 TOMA DATOS'!AB60 -> SI
B28: =+' FMT 104 TOMA DATOS'!B61 -> Presentar original del contrato de arrendamiento o autorización del propietario (autenticada por abogado). | Z28: =+' FMT 104 TOMA DATOS'!AB61 -> SI
B29: Revisión interna (usuario no debe presentarlos pero si su cumplimiento)
B30: =+' FMT 104 TOMA DATOS'!B63 -> Que el solicitante se encuentre al día en los pagos correspondientes a la CCSS, FODESAF y HACIENDA | Z30: =+' FMT 104 TOMA DATOS'!AB63 -> SI
B31: =+' FMT 104 TOMA DATOS'!B64 -> Consulta por número de finca emitida por Registro Nacional (se revisa internamente en la municipalidad). | Z31: =+' FMT 104 TOMA DATOS'!AB64 -> SI
B32: =+' FMT 104 TOMA DATOS'!B65 -> Que el solicitante y el propietario del inmueble donde se va a desarrollar la actividad, estén al día en el pago de impuestos, tasas o multas municipales. | Z32: =+' FMT 104 TOMA DATOS'!AB65 -> SI
B33: =+' FMT 104 TOMA DATOS'!B66 -> Las propiedades a nombre tanto del propietario del inmueble como de quien pretenda desarrollar la actividad comercial, tienen una declaración
B34: =+' FMT 104 TOMA DATOS'!B67 -> de valor vigente, de conformidad con lo establecido en la Ley del Impuesto Sobre Bienes Inmuebles. | Z34: =+' FMT 104 TOMA DATOS'!AB67 -> SI
B35: Listado de requisitos entregados para LICENCIA COMERCIAL
B36: =+' FMT 104 TOMA DATOS'!B69 -> Póliza de riesgos del trabajo emitida por entidad aseguradora o exoneración. Art 202 del Código de Trabajo. | Z36: =+' FMT 104 TOMA DATOS'!AC69 -> SI
B37: =+' FMT 104 TOMA DATOS'!B70 -> Estar inscrito como contribuyente ante el Ministerio de Hacienda | Z37: =+' FMT 104 TOMA DATOS'!AC70 -> SI
B38: =+' FMT 104 TOMA DATOS'!B71 -> Cien colones en timbres fiscales o pago del entero. | Z38: =+' FMT 104 TOMA DATOS'!AC71 -> SI
B39: =+' FMT 104 TOMA DATOS'!B72 -> Presentar comprobante de pago a favor del Servicio Nacional de Salud Animal del MAG. | Z39: =+' FMT 104 TOMA DATOS'!AC72 -> SI
B40: =+' FMT 104 TOMA DATOS'!B73 -> Presentar comprobante de pago a favor del Ministerio de Salud, según corresponda, o bien el comprobante de exoneración del
B41: =+' FMT 104 TOMA DATOS'!B74 -> pago por el IMAS. | Z41: =+' FMT 104 TOMA DATOS'!AC74 -> SI
B42: =+' FMT 104 TOMA DATOS'!B75 -> Regencia o asesoría veterinaria aprobada por el Colegio de Médicos Veterinarios (cuando aplique) | Z42: =+' FMT 104 TOMA DATOS'!AC75 -> SI
B43: =+' FMT 104 TOMA DATOS'!B76 -> Presentar Autorización por concepto de derechos de autor ACAM (cuando aplique) | Z43: =+' FMT 104 TOMA DATOS'!AC76 -> SI
B44: En el caso de los traspasos de licencias comerciales deberá evidenciarse la voluntad de las partes para ceder y aceptar los derechos asociados a una licencia
B45: comercial. Las firmas correspondientes deberán estar debidamente autenticadas por abogado; salvo que la manifestación de voluntad sea firmada por ambas partes
B46: en presencia de un funcionario municipal. | Z46: =+' FMT 104 TOMA DATOS'!AC79 -> SI
B47: =+' FMT 104 TOMA DATOS'!B80 -> Certificado de Idoneidad Técnica para salones de belleza, barbería, peluquería y afines (cuando aplique) | Z47: =+' FMT 104 TOMA DATOS'!AC80 -> SI
B48: =+' FMT 104 TOMA DATOS'!B81 -> En el caso de actividades que requieran la correspondiente autorización de la Dirección General de Minería, del Ministerio de
B49: =+' FMT 104 TOMA DATOS'!B82 -> Ambiente y Energía o la Secretaria Técnica Nacional Ambiental; deberá aportarse una certificación de la misma. | Z49: =+' FMT 104 TOMA DATOS'!AC82 -> SI
B50: =+' FMT 104 TOMA DATOS'!B83 -> El Ministerio de Salud revisará en el sistema que el solicitante no se encuentra moroso en el Registro de Infractores, Ley 9028. | Z50: =+' FMT 104 TOMA DATOS'!AC83 -> SI
B51: Se apercibe al solicitante que conforme lo prescribe el artículo 5° del Reglamento General de Patentes Comerciales y Similares de la Municipalidad de Tilarán, deberá en el término de DIEZ días cumplir con el(los) requisito(s) pediente(s), caso contrario se ordenará el archivo de la solicitud sin mayor trámite.
B56: =+' FMT 104 TOMA DATOS'!K85 -> Carolay Solera Calvo
B57: =VLOOKUP(B56,PARÁMETROS!E109:H126,4,0) -> PLATAFORMISTA

Sheet MANIFIESTO TRASPASO
B2: MUNICIPALIDAD DE TILARAN
B3: PROCESO DE SERVICIOS CIUDADANOS Y TÉCNICOS
B10: MANIFIESTO DE LA VOLUNTAD DE TRASPASO DE PATENTES COMERCIALES
C12: NOMBRE DEL NEGOCIO: | I12: =+' FMT 104 TOMA DATOS'!H28 -> 0
C13: ACTIVIDAD PSF: | H13: =+' FMT 104 TOMA DATOS'!I29 -> 0
C14: ACTIVIDAD CVO: | H14: =+' FMT 104 TOMA DATOS'!I30 -> 0
C15: N° FINCA: | F15: =+' FMT 104 TOMA DATOS'!H39 -> 0
C17: NOMBRE DEL PATENTADO: | V17: N° CÉDULA:
C18: REPRESENTANTE LEGAL: | V18: N° CÉDULA:
C19: TELÉFONO: | N19: FAX: | V19: FIRMA transmitente
C20: CORREO ELECTRÓNICO:
C22: NOMBRE DEL ADQUIRENTE: | J22: Frayman S.A. | V22: N° CÉDULA: | Y22: =VLOOKUP(J22,PARÁMETROS!B611:C613,2,FALSE) -> #N/A
C23: REPRESENTANTE LEGAL: | I23: Picado Fernandez Ricardo | V23: N° CÉDULA: | Y23: =VLOOKUP(I23,PARÁMETROS!B611:C613,2,FALSE) -> #N/A
C24: DIRECCIÓN EXACTA: | I24: =+' FMT 104 TOMA DATOS'!H16 -> 0
H25: ( Referencia, distrito, cantón y provincia )
C26: TELÉFONO: | F26: =+' FMT 104 TOMA DATOS'!H18 -> 0 | N26: FAX: | P26: =+' FMT 104 TOMA DATOS'!T18 -> 0 | V26: FIRMA adquirente
C27: CORREO ELECTRÓNICO: | I27: =+' FMT 104 TOMA DATOS'!R19 -> 0
C29: Las firmas correspondientes deberán estar debidamente autenticadas por abogado; salvo que la manifestación de voluntad sea firmada por ambas partes en presencia de un funcionario municipal. | V29: FIRMA autenticante
B32: Los arriba firmantes manifestamos libremente la voluntad de las partes para ceder y aceptar los derechos asociados a la licencia comercial detallada.

Sheet REQUISITOS FMT 104
B2: Formulario único para Apertura, Actualización y Renovación de Empresas para actividades de bajo riesgo del Ministerio de Salud y de Comercialización y Servicios de SENASA - en los cantones de Abangares, Cañas, Tilarán, Bagaces, Liberia y La Cruz de Región Chorotega
B7: APERTURA DE ESTABLECIMIENTOS COMERCIALES
B8: 1. Formulario único y declaración jurada debidamente llenos
B9: 2. Presentar la cédula de identidad o cédula de residencia libre de condición o DIMEX en caso de ser extranjero.
B10: 3. Certificación de personería jurídica . (Verificación interna).
B11: 4. Plano catastrado (se revisa internamente en la municipalidad, pero si el mismo no se encuentra en la base de datos el solicitante deberá presentarlo físicamente).
B12: 5. Presentar original del contrato de arrendamiento o autorización del propietario (autenticada por abogado).
B13: 6. Que el solicitante se encuentre al día en los pagos correspondientes a la CCSS, FODESAF y HACIENDA (Verificación interna).
B14: 7. Que el solicitante y el propietario del inmueble donde se va a desarrollar la actividad, estén al día en el pago de impuestos, tasas o multas municipales. (Verificación interna).
B15: 8. Las propiedades a nombre tanto del propietario del inmueble como de quien pretenda desarrollar la actividad comercial, tienen una declaración de valor vigente, de conformidad con lo establecido en la Ley del Impuesto Sobre Bienes Inmuebles . (Verificación interna).
B16: 9. Póliza de riesgos del trabajo emitida por entidad aseguradora o exoneración. Art 202 del Código de Trabajo.
B17: 10. Estar inscrito como contribuyente ante el Ministerio de Hacienda. (Verificación interna).
... B66: 5. Estar al día con el pago de la patente municipal.

Sheet DECLARACIÓN JURADA
B2: DECLARACIÓN JURADA PARA TRÁMITES DE SOLICITUD DE LICENCIA COMERCIAL DECRETO EJECUTIVO Nº 41437-MEIC-S-MAG
B5: Yo | C5: Perez Elizondo Rafael Antonio | N5: en mi condición de | S5: Persona física
B6: de | N6: solicito | P6: Certificado Veterinario de Operación requerido en la Ley General del Servicio Nacional de Salud Animal.
B7: a mi representada, para lo cual declaro bajo fe de juramento y que de no decir la verdad incurro en perjurio
B8: sancionado con pena de prisión según el Código Penal y consciente de la importancia de lo aquí anotado,
B9: lo siguiente:
B11: Primero: Que conozco la legislación aplicable a la actividad señalada en el presente formulario único que se realizará en el establecimiento indicado y que éste cumple con toda la normativa establecida para el caso en concreto.
B14: Segundo: Que la información que contiene el formulario unificado es verdadera.
B16: Tercero: Que en cumplimiento de lo establecido en los artículos 44, 74 y 74 bis de la Ley Constitutiva de la Caja Costarricense de Seguro Social y el artículo 66 del Reglamento del Seguro Social, me comprometo a la inscripción como patrono, trabajador dependiente o en ambas modalidades dentro de los ocho días siguientes al inicio de la actividad. Asimismo, declaro estar al día en el pago de mis obligaciones con esa institución.
B21: Cuarto: Que cumplo con lo establecido en la Ley N° 9028 del 22 de marzo de 2012 ”Ley General de Control de Tabaco y sus Efectos Nocivos a la Salud” y sus reglamentos (así adicionado el punto “tercer bis” anterior por el inciso a) del artículo 61 del Reglamento a la Ley General de Control de Tabaco y sus Efectos Nocivos en la Salud, aprobado mediante el decreto ejecutivo N° 37185-S de 26 de junio de 2012), y sus reformas.
B26: Quinto: Asimismo, me comprometo a mantener las condiciones debidas por el tiempo de vigencia del permiso y cumplir con los términos de la normativa antes indicada y el Decreto Ejecutivo N. 34859-MAG, “Reglamento General para el Otorgamiento del Certificado Veterinario de Operación”, por ser requisito indispensable para la operación de mi establecimiento, de igual forma me comprometo que todos los servicios brindados y los productos, equipos y materiales que se comercialicen o utilicen dentro del establecimiento que represento, cuando proceda, estarán debidamente autorizados por el Ministerio de Salud y a no ampliar o cambiar de actividad sin la autorización previa de este Ministerio o SENASA.
B33: Sexto. Que el establecimiento reúne los requisitos y condiciones físicas y sanitarias exigidas para su funcionamiento.
B36: Sétimo. Por lo anterior, quedo apercibido de las consecuencias legales y judiciales, con que la legislación castiga los delitos de perjurio y falso testimonio. Asimismo, exonero de toda responsabilidad a las autoridades del Ministerio de Salud o del Servicio Nacional de Salud Animal por el otorgamiento del PSF o CVO con base en lo declarado bajo fe de juramento en la presente declaración, y soy conocedor de que si la autoridad de Salud o SENASA llegase a corroborar alguna falsedad en la presente declaración, errores u omisiones en los documentos aportados, o que los servicios prestados y/o los productos comercializados dentro de mi establecimiento no cuentan con la debida autorización sanitaria, suspenderá o cancelará el PSF o CVO. Es todo.
B44: Firmo en el cantón de | H44: Tilarán | R44: a las | T44: 0.625
B45: del | C45: 12 | E45: de | F45: Enero | I45: del | J45: 2022
M46: Firma
B48: Autorización a terceros: Si el trámite es realizado por un tercero, debe adjuntar copia de la cédula de identidad certificada del titular, acompañada de la respectiva autorización.
B51: =IF(' FMT 104 TOMA DATOS'!M12<>"",' FMT 104 TOMA DATOS'!M12&' FMT 104 TOMA DATOS'!B13,' FMT 104 TOMA DATOS'!I10) -> 0 | O51: =' FMT 104 TOMA DATOS'!H28 -> 0

Sheet CONSTANCIA INS
B2: MUNICIPALIDAD DE TILARÁN
B3: Proceso Servicios Ciudadanos y Técnicos
B4: Unidad Plataforma de Servicios
B6: CONSTANCIA DE TRÁMITE DE PATENTE COMERCIAL
B7: Para trámite de exoneración póliza de riesgos del trabajo ante el Instituto Nacional de Seguros
B10: El abajo firmante en mi condición de funcionario municipal, hago constar que ante ésta administración se gestiona
B11: licencia comercial en el cantón de Tilarán, bajo las siguientes condiciones:
B13: NOMBRE DEL NEGOCIO: | I13: =+' FMT 104 TOMA DATOS'!H28 -> 0
B14: UBICACIÓN: | F14: =+' FMT 104 TOMA DATOS'!H38 -> 150 este CCSS
B15: ACTIVIDADES COMERCIALES AUTORIZADAS POR LA MUNICIPALIDAD DE TILARÁN:
B16: 1 | C16: =+' FMT 104 TOMA DATOS'!I29 -> 0
B17: =1+B16 -> 2 | C17: NINGUNA
B18: =1+B17 -> 3 | C18: NINGUNA
B19: =1+B18 -> 4 | C19: NINGUNA
B20: NOMBRE DEL SOLICITANTE: | I20: =+' FMT 104 TOMA DATOS'!I10 -> 0 | Y20: N° CEDULA: | AB20: =+' FMT 104 TOMA DATOS'!H11 -> 0
B22: Frayman Pérez Ramírez
B23: =VLOOKUP(B22,PARÁMETROS!E109:H126,4,0) -> #N/A

Sheet EX INS-F-D0139
G2: INSTITUTO NACIONAL DE SEGUROS
G3: Seguro Obligatorio de Riesgos del Trabajo
G4: Solicitud de validación del artículo 194 del Código de Trabajo
B6: REQUISITOS | C6: I. Original del documento de identificación del interesado, vigente y en buen estado. II. Si el interesado (a) autoriza a otra persona para presentar esta solicitud a su nombre, debe aportar: • Carta de autorización. • Fotocopia del documento de identificación del interesado (a). • Original del documento de identificación de la persona autorizada, vigente y en buen estado. III. A efecto de verificar la actividad económica a exonerar, deberá presentar en original o fotocopia, alguno de los documentos que se citan: • Permiso sanitario de funcionamiento vigente. • Último recibo de la patente pagado o comprobante digital. • Permiso o concesión vigente para transporte de personas. • Si se encuentra tramitando por primera vez el permiso respectivo, podrá presentar el formulario de solicitud debidamente cumplimentado y sellado por la institución correspondiente o en su defecto, comprobante digital cuando el trámite se pueda realizar en línea. No obstante, en el caso del servicio de transporte de personas, solo debe presentar el formulario de “Solicitud de validación del artículo 194 del Código de Trabajo” debidamente cumplimentado. • Cualquier documento de respaldo de la actividad económica, expedido por la entidad reguladora en ese sector.
B27: DECLARACIÓN | C27: 1. Yo | D27: Picado Fernandez Ricardo | K27: , N° identificación | N27: =VLOOKUP(D27,PARÁMETROS!B611:C613,2,FALSE) -> #N/A
C28: declaro que la información suministrada en este documento es fiel reflejo de las condiciones en que realizaré la actividad, para la cual solicito la validación de conformidad con lo establecido en el artículo 194 del Título IV del Código de Trabajo, que a la letra señala: “Sin perjuicio de que, a solicitud del interesado, se pueda expedir el seguro contra riesgos del trabajo, estarán excluidos de las disposiciones de este Título: a) La actividad laboral familiar de personas físicas, entendida ésta como la que se ejecuta entre los cónyuges, o los que viven como tales, entre éstos y sus ascendientes y descendientes, en beneficio común, cuando en forma indudable no exista relación de trabajo. b) Los trabajadores que realicen actividades por cuenta propia, entendidos como los que trabajan solos o asociados, en forma independiente, y que no devengan salario.” Asimismo, que los datos consignados son veraces y se pueden comprobar en cualquier momento y que, con la firma de este documento doy fe que conozco y acepto la responsabilidad existente por cualquier información suministrada que se compruebe ser falsa, todo de acuerdo con el marco legal costarricense.
B50: INFORMACIÓN ACTIVIDAD ECONÓMICA | C50: 2. Nombre del negocio: | I50: =+' FMT 104 TOMA DATOS'!H28 -> 0
C51: 3. Dirección del negocio: | I51: =+' FMT 104 TOMA DATOS'!H38 -> 150 este CCSS
C52: 4. Provincia: | E52: =+' FMT 104 TOMA DATOS'!I36 -> 0 | J52: 5. Cantón: | L52: =+' FMT 104 TOMA DATOS'!U36 -> 0
C53: 6. Distrito: | E53: =+' FMT 104 TOMA DATOS'!E37 -> 0
C54: 7. Correo electrónico: | H54: =+' FMT 104 TOMA DATOS'!R19 -> 0
C55: 8. Teléfono del negocio: | G55: =+' FMT 104 TOMA DATOS'!H18 -> 0 | J55: 9. Número celular: | M55: =+' FMT 104 TOMA DATOS'!E19 -> 0
C56: 10. Actividad económica del negocio: | J56: =+' FMT 104 TOMA DATOS'!I29 -> 0
C57: 11. La actividad económica señalada anteriormente, la realiza:
D58: NO | E58: Con trabajadores a su cargo
D60: NO | E60: Asociado:
D61: Nombre | M61: N° identificación
B69: INFORMACIÓN ACTIVIDAD ECONÓMICA | D69: NO | E69: Con familiares:
D70: a. Seleccione la o las personas con quien ejecuta la actividad laboral.
D71: b. Selecciones si existe o no relación laboral; es decir, si hay o no remuneración, subordinación y prestación de un servicio.
D73: ¿Existe relación laboral? | I73: Nombre | M73: N° identificación
G74: SI | H74: NO
C75: Cónyuge / conviviente
C76: Papá / mamá | H76: X
C77: Suegro (a) | H77: X
C78: Hijo (a) | H78: X
C79: Hijastro (a) | H79: X
C80: Abuelo (a) | H80: X
C81: Bisabuelo (a) | H81: X
C82: Nieto (a) | H82: X
C83: Bisnieto (a) | H83: X
C84: Otros: | H84: X
D86: SI | E86: Sólo
C87: 12. Fecha de solicitud | I87: 13. Firma del interesado (a)
C88: =TODAY() -> 45349
C94: USO EXCLUSIVO DEL INSTITUTO NACIONAL DE SEGUROS
B95: VALIDACIÓN ART. 194 | C95: 14. De conformidad con lo dispuesto en el artículo 194 del Código de Trabajo y una vez analizada la información declarada anteriormente por la persona interesada, se tiene como resultado que:
D99: No está en la obligación de tomar la póliza del Seguro Obligatorio de Riesgos del Trabajo.
D101: Por tanto, esta condición rige a partir de la fecha de esta validación y se extenderá hasta un año calendario.
D103: Sin embargo, esta condición cesará automáticamente si los aspectos declarados en esta solicitud que consta en poder del Instituto Nacional de Seguros varían, o se inicia una relación laboral en los términos del Código de Trabajo, por lo que la persona interesada quedará obligada a adquirir la póliza del Seguro Obligatorio de Riesgos del Trabajo.
D106: Debe adquirir la póliza del Seguro Obligatorio de Riesgos del Trabajo.
C108: 15. Fecha validación | F108: 16. Sede | I108: 17. Revisado | L108: 18. Sello de Autorizado
B112: Instituto Nacional de Seguros / Apdo. Postal 10061-1000 Central telefónica 2287-6000 / Fax: 2243-7062 Consultas: contactenos@ins-cr.com / Defensoría del Cliente: defensoriadelcliente@ins-cr.com / página web: www.ins-cr.com

Sheet ANTIGUA DECLARA
B2: DECLARACIÓN JURADA PARA TRÁMITES DE SOLICITUD DE PERMISOS SANITARIOS DE FUNCIONAMIENTO POR PRIMERA VEZ O RENOVACIONES
B4: Yo | C4: Victor Manuel Chan Quintero | M4: con domicilio en | Q4: distrito: | S4: =+' FMT 104 TOMA DATOS'!E15 -> 0
B5: cantón | D5: =+' FMT 104 TOMA DATOS'!U14 -> 0 | M5: provincia | P5: =+' FMT 104 TOMA DATOS'!I14 -> 0
B6: Otras señas | E6: =+' FMT 104 TOMA DATOS'!H16 -> 0
B7: en mi condición de | H7: Representante Legal
B8: de la sociedad denominada (Razón social):
B10: propietario del establecimiento comercial
B11: =+' FMT 104 TOMA DATOS'!H28 -> 0
B12: cuyas actividades son: | H12: =+' FMT 104 TOMA DATOS'!I29 -> 0
B13: solicito sea otorgado | G13: Certificado Veterinario de Operación requerido en la Ley General del Servicio Nacional de Salud Animal.
B14: a mi representada, para lo cual declaro bajo fe de juramento y que de no decir la verdad incurro en perjurio sancionado con pena de prisión según el Código Penal y consciente de la importancia de lo aquí anotado, lo siguiente: Primero. Que la actividad señalada en el formulario de solicitud del PSF, cumple con toda la normativa establecida para el caso en concreto. Segundo. Que la información que contiene el formulario unificado que adjunto a esta declaración es verdadera. Tercero. Que en cumplimiento de lo establecido en los artículos 44, 74 y 74 bis de la Ley Constitutiva de la Caja Costarricense de Seguro Social y el artículo 66 del Reglamento del Seguro Social, me comprometo a la inscripción como patrono, trabajador independiente o en ambas modalidades dentro de los ocho días al inicio de la actividad. Asimismo, declaro estar al día en el pago de mis obligaciones con esa institución. Cuarto. Que cumplo con lo establecido en la Ley N.º 9028 del 22 de marzo de 2012 "Ley General de Control de Tabaco y sus Efectos Nocivos a la Salud" y sus reglamentos (así adicionado el punto "tercer bis" anterior por el inciso a) del artículo 61 del Reglamento a la Ley General de Control de Tabaco y sus Efectos Nocivos en la Salud, aprobado mediante el decreto ejecutivo N.º 37185-S de 26 de junio de 2012) Quinto. Que conforme a lo establecido en el Decreto N.º 36979-MEIC, RTCR 458:2011 Reglamento de Oficialización del Código Eléctrico de Costa Rica para la Seguridad de la Vida y de la Propiedad, artículo 5°, inciso 5.2.4.3, cuando corresponda según el artículo 21 inciso 7 del Reglamento General para Autorizaciones y de Permisos Sanitarios de Funcionamiento Otorgados por el Ministerio de Salud y sus reformas, cumplo con lo ahí exigido. Sexto. Que de conformidad con lo establecido en el Reglamento General para Autorizaciones y Permisos Sanitarios de Funcionamiento Otorgados por el Ministerio de Salud en su Artículo 9, Condiciones Previas, mi representada cumple con lo ahí solicitado y para ello suministro la siguiente información según corresponda: (Aplica solo para trámites de permisos sanitarios de funcionamiento por primera vez).
B30: 1. Resolución municipal de ubicación - uso de suelo - otorgada por la Municipalidad de Tilarán.
B31: 2. Viabilidad ambiental emitida por SETENA.
B32: 3. Oficio emitido por ente administrador de alcantarillado sanitario indicando que acepta el volúmen y la ca-
B33: lidad físicoquímica de las aguas residuales del establecimiento que serán vertidas en el alcantarillado sani-
B34: tario.
A37: NA | B37: 4. Permiso de vertido emitido por el MINAE que permita descargar aguas residuales al cuerpo de agua.
A38: NA | B38: 5. Certificado de regencia profesional otorgada por el Colegio Profesional ccorrespondiente.
A39: NA | B39: 6. Certificado de operación del establecimiento otorgado por el Colegio Profesional ccorrespondiente.
A40: NA | B40: 7. Permiso de funcionamiento para calderas vigente, extendido por el ministerio.
A41: NA | B41: 8. Resolución de la DPAH autorizando la utilización de la fuente de emisiones de radiaciones ionizantes.
A42: NA | B42: 9. Contrato asignado por el Colegio de Ingenieros y Aruitectos a los planos constructivos.
B44: Además, declaro que la actividad para la cual solicito el PSF, cumple con los requisitos señalados para la solicitud del trámite por primera vez según el Reglamento General para Autorizaciones y Permisos Sanitarios de Funcionamiento Otorgados por el Ministerio de Salud. Sétimo. Asimismo, me comprometo a mantener las condiciones debidas por el tiempo de vigencia del permiso y cumplir con los términos de la normativa antes indicada, por ser requisito indispensable para la operación de mi establecimiento, de igual forma me comprometo que todos los servicios brindados y los productos, equipos y materiales que se comercialicen o utilicen dentro del establecimiento que represento, cuando proceda, estarán debidamente autorizados por el Ministerio de Salud y a no ampliar o cambiar de actividad sin la autorización previa de este Ministerio. Octavo. Por lo anterior, quedo apercibido de las consecuencias legales y judiciales, con que la legislación castiga el delito de perjurio. Asimismo, exonero de toda responsabilidad a las autoridades del Ministerio de Salud por el otorgamiento del PSF con base en la presente declaración. ADEMAS: conocedor de las consecuencias legales y administrativas de la presente declaración jurada, manifiesto y autorizo en forma expresa para que la autoridad de salud correspondiente, proceda a suspender o a cancelar el Permiso Sanitario de Funcionamiento, según corresponda, y prosiga con la clausura del establecimiento para el cual tramito el presente Permiso Sanitario de Funcionamiento, si se llegase a corroborar alguna falsedad en la presente declaración, errores u omisiones en los documentos aportados, o que los servicios prestados y/o los productos comercializados dentro de mi establecimiento no cuentan con la debida autorización sanitaria. ES TODO.
B58: Firmo en el cantón de | H58: Tilarán | R58: a las | T58: 04:00 pm
B59: NOVIEMBRE | F59: de | G59: 2019 | L59: Firma
L61: Es auténtica:
B63: INSTRUCCIONES: a) En caso de persona jurídica debe aportar la certificación registral o notarial de la personería la cual tendrá una vigencia de un mes. La certificación digital expedida por el Registro Público tendrá una validez de 15 días naturales. b) En caso de que un tercero realice el trámite se debe adjuntar fotocopia de documento de identificación de quien solicita el PSF (eventual titular), además de la respectiva autorización. c) Solamente podrá rendir la declaración jurada quien esté facultado legalmente para dicho acto. d) Si la firma es digital no se requiere de autenticación. Igualmente, no requerirá autenticación si el gestionante realiza el trámite personalmente.

Sheet USO DE SUELO
J2: USO DE SUELO
J3: Coordinación Desarrollo y Control Urbano
B5: N° FINCA: | E5: =+' FMT 104 TOMA DATOS'!H39 -> 0 | O5: N° PLANO CATASTRADO: | U5: =+' FMT 104 TOMA DATOS'!W39 -> 0
B6: ÁREA DE LA FINCA: | G6: EN METROS CUADRADOS | M6: =+' FMT 104 TOMA DATOS'!G40 -> 0 | S6: EN HECTÁREAS CUADRADAS: | Z6: =+M6/10000 -> 0
B7: ANCHO DE LA VÍA (en metros): | J7: 12.5
B8: EXISTE PLAN REGULADOR: | I8: NO | L8: TIPO DE ZONA: | P8: Industria.
B9: SE DA AFECTACIÓN POR RÍOS, CUERPOS DE AGUA O PATRIMONIO NATURAL DEL ESTADO (Si tiene afectación a-
B10: plican retiros conforme al artículo 33 de la Ley Forestal y demás relacionados, conexos y vinculantes, mismos que serán
B11: establecidos por el INVU mediante sello en el plano catastrado y serán requisito para el Permiso de Construcción o Paten-
B12: te). | C12: NO
B14: ALTURA DE CONSTRUCCIÓN PARA LA ZONA: | H14: Todo lo relacionado con Alturas de Edificaciones, será regulado en su efecto por lo establecido en el ARTÍCULO 99 del Reglamento de construcciones del Instituto Nacional de Vivienda y Urbanismo .
B17: LOTE MÍNIMO (Depende del Uso Solicitado): | H17: USO RESIDENCIAL Y COMERCIAL: 150m2 // USOS DE HOSPEDAJE: 280m2 // PARCELAS AGRÍCOLAS, PECUARIAS Y FORESTALES: 5000m2//.
B20: DENSIDAD: | H20: USO RESIDENCIAL Y COMERCIAL: 1 Unidad Habitacional por cada 150m2 // USOS DE HOSPEDAJE: 6 Habitaciones por cada 280m2 // PARCELAS AGRÍCOLAS, PECUARIAS Y FORESTALES: 1 Vivienda Unifamiliar por lote.
B23: COBERTURA MÁXIMA: | H23: Aplica Artículo 188 del Reglamento de construcciones del Instituto Nacional de Vivienda y Urbanismo. La Cobertura abarca toda construcción asociada (vivienda, edificios, accesos, parqueos, ranchos, piscina, pozos, entre otros). El porcentaje indicado se calcula en relación con el área lote.
H26: USO RESIDENCIAL Y COMERCIAL: 75% u 80% en Lote Esquinero // USOS DE HOSPEDAJE: 70% // PARCELAS AGRÍCOLAS, PECUARIAS Y FORESTALES: 15% y Hasta UNA Vivienda Unifamiliar Máximo// INDUSTRIA: 60%.
H29: RETIROS, COBERTURAS Y ALTURAS PODRÍAN VARIAR EN CASO DE ESCUELAS, TORRES DE TELECOMUNICACIÓN, BARES, ENTRE OTROS, POR LO QUE SE SOLICITA OBSERVAR EL APARTADO “OBSERVACIONES” PARA CONOCER DETALLES ADICIONALES AL USO SOLICITADO. Art. 387 del Reglamento de construcciones del Instituto Nacional de Vivienda y Urbanismo.
B33: ÁREA DE COBERTURA PARA EL LOTE EN M2 (para Residencia o Comercio) | R33: =+$M$6*75% -> 0 | U33: Si es esquinero | Y33: =+$M$6*80% -> 0
B34: ÁREA DE COBERTURA PARA EL LOTE EN M2 (para usos de hospedaje) | R34: =+$M$6*70% -> 0 | U34: ÁREA DE COBERTURA PA-
B35: RA EL LOTE EN M2 (Aplica solo si el tipo de zona es Parcela Agrícola, Forestal o Pecuaria) | U35: =+M6*15% -> 0 | X35: DENSIDAD
B36: PARA RESIDENCIA O COMERCIO (N° de Unidades Habitacionales o Comerciales para el lote) | W36: 1
B37: DENSIDAD PARA USOS DE HOSPEDAJE (N° de habitaciones para el lote)
B38: Para Parcelas Agrícolas, Forestales o Pecuarias aplica ÚNICAMENTE 1 Unidad Habitacional y/o todas aquellas estructuras
B39: asociadas a la actividad Agrícola, Forestal o Pecuaria dentro del área dada por el 15% de cobertura máxima anotado.
B40: ALTURA DE CONSTRUCCION (una vez y media el ancho de la vía) | Q40: =+J7*1.5 -> 18.75 | W40: metros lineales.
B41: REGULACIÓN DE ESPACIOS DE PARQUEO: Todo lo relacionado con los espacios de Parqueo, será regulado en su defec-
B42: to por lo establecido en el CAPITULO XVIII del Reglamento de Construcciones del INVU. Serán solicitdos conforme a la acti-
B43: vidad al momento de otorgar el Permiso de Construcción o la Patente Comercial.
B44: USO SOLICITADO: | G44: =+' FMT 104 TOMA DATOS'!I29 -> 0
B45: CONDICIÓN DEL USO SOLICITADO: | K45: USO CONFORME
B47: CONTRA ÉSTA RESOLUCIÓN CABEN LOS RECURSOS DE REVOCATORIA Y APELACIÓN DENTRO DE UN PLAZO DE CINCO DÍAS A PARTIR DE LA NOTIFICACIÓN DE LA MISMA, DE CONFORMIDAD CON EL ARTÍCULO 171 DEL CÓDIGO MUNICIPAL.
B50: Según el artículo 12 del Reglamento para la obtención de permisos de construción de la Municipalidad de Tilarán, el certificado de uso de suelo tendrá vigencia por un año.
B55: DADO EN TILARÁN EL | H55: =TODAY() -> 45349
Q56: Rose Mary Ruiz Soto
Q57: =VLOOKUP(Q56,PARÁMETROS!E109:H126,4,0) -> COORDINADOR DE DESARROLLO Y CONTROL URBANO

Sheet RESOLUCIÓN PSF
B5: DARST-ERS-009-M-2019 | H5: DIRECCION ÁREA RECTORA DE SALUD DE TILARÁN, MINISTERIO
B6: DE SALUD, REGIÓN CHOROTEGA, EL DIA | M6: 18 | N6: MARZO | S6: 2019
B8: Solicitud de Permiso Sanitario de Funcionamiento por | P8: =+' FMT 104 TOMA DATOS'!S7 -> Sólo Licencia para la comercialización de bebidas con contenido alcohólico
B9: para el establecimiento | H9: =' FMT 104 TOMA DATOS'!H28:AD28 -> 0
B11: RESULTANDO
B13: PRIMERO: | E13: Que el | G13: 43474 | K13: =+' FMT 104 TOMA DATOS'!I10 -> 0
B14: con cédula de identidad | H14: =+' FMT 104 TOMA DATOS'!H11:L11 -> 0 | M14: en calidad de | Q14: =+' FMT 104 TOMA DATOS'!R11 -> Representante Legal
B15: de la organización | G15: =+' FMT 104 TOMA DATOS'!M12 -> 0
B16: interpuso solicitud de Permiso Sanitario de Funcionamiento para el establecimiento
B17: =+H9 -> 0
B18: con dirección | F18: =+' FMT 104 TOMA DATOS'!H38 -> 150 este CCSS
B20: distrito | D20: =+' FMT 104 TOMA DATOS'!E37 -> 0
B22: SEGUNDO: | E22: Consta en autos se aportó la siguiente documentación
B24: Formulario único para la apertura de establecimientos en el cantón de Tilarán
B25: Recibo de pago para PSF. N° | I25: 1548888 | M25: del | N25: 43473 | R25: por | S25: 50000
B26: El solicitante se encuentre al día en los pagos correspondientes a la CCSS
B27: El solicitante se encuentre al día en los pagos correspondientes a FODESAF
B28: No registra infracción a la Ley 9028
B30: CONSIDERANDO
B32: PRIMERO: | E32: Que en materia de PSF, los mismos están definidos por el Decreto N° 39472-S
B33: “Reglamento General para Autorizaciones y Permisos Sanitarios de Funcionamiento Otorgados
B34: por el Ministerio de Salud”.
B36: SEGUNDO: | E36: Que la solicitud CUMPLE con todas las disposiciones establecidas en el artículo 13
B37: del Decreto 39472-S, el establecimiento se clasifica dentro del | Q37: 5610 | T37: del grupo de ries-
B38: go | C38: B | D38: por lo que se procede a otorgar el PSF por | N38: 1 | O38: años.
B40: TERCERO: | E40: Que corresponde al gobierno local, previo al funcionamiento de cualquiera de las ac-
B41: tividades reguladas en el presente decreto, establecer las condiciones de ubicación, por lo que el
B42: establecimiento de la infraestructura para este comercio, estará sometida a la previa aprobación
B43: de la Resolución Municipal de Ubicación, de acuerdo con el reglamento de zonificación del Plan Re-
B44: gulador del cantón.
B46: CUARTO: | E46: Que el Decreto 39472-S permite extender el PSF por declaración jurada, sin embar-
B47: go el mismo queda sujeto a la visita de verificación por parte de funcionarios del Área Rectora de
B48: Salud de Tilarán.
B50: QUINTO: | E50: Que con la Declaración Jurada el representante legal indica que el establecimiento
B51: cumple con la normativa nacional vigente y queda apercibido de las consecuencias legales y ju-
B52: diciales por perjurio.
B60: POR TANTO El AREA RECTORA DE SALUD DE TILARAN RESUELVE
B62: Con fundamento a los artículos 01 y 11 de la Constitución Política de la República; a los artículos
B63: 6, 7 y 11 de la Ley General de la Administración Pública; a los artículos 1, 2, 4, 7, 9, 222, 340,
B64: 355, 356, 357 y 363 de la Ley General de Salud y al Decreto N° 39472-S “Reglamento General para
B65: Autorizaciones y Permisos Sanitarios de Funcionamiento Otorgados por el Ministerio de Salud”, se
B66: procede a
B68: Otorgar en el permiso sanitario de funcionamiento por declaración jurada para con la actividad
B69: =' FMT 104 TOMA DATOS'!L29 -> 0 | T69: por | U69: =+N38 -> 1 | V69: años
B70: El mismo queda sujeto a la visita de verificación sanitaria por parte de funcionarios del Área Rec-
B71: tora de Salud de Tilarán.
B74: María de Jesús González Zumbado | M74: Hilda María Barrantes Guerrero
B75: Regulación de la Salud | M75: Directora Área Rectora de Salud Tilarán

Sheet CERTIFICADO PSF
B2: PERMISO SANITARIO DE FUNCIONAMIENTO DEL
B3: MINISTERIO DE SALUD
B4: N° RCH-DARS-T- | M4: 262 | O4: 2019
B6: REGION RECTORA DE SALUD CHOROTEGA
B7: ÁREA RECTORA DE SALUD TILARÁN
B9: En cumplimiento a lo que establece la Ley General de Salud (N°5395) y el Reglamento general
B10: para autorizaciones y permisos sanitarios de funcionamiento otorgados por el Ministerio de Salud
B11: (DE.39472-S), así como demás normativa vigente, se extiende el presente permiso sanitario de
B12: funcionamiento a:
B14: =+' FMT 104 TOMA DATOS'!H28 -> 0
B15: NOMBRE DEL ESTABLECIMIENTO
B17: RAZÓN SOCIAL: | G17: Muñóz Agüero Esteban Josué
B18: CÉDULA JURÍDICA: | G18: 0
B19: REPRESENTANTE LEGAL: | I19: 0
B20: CÉDULA DE IDENTIDAD: | I20: 2-0711-0195
B21: TIPO DE ACTIVIDAD: | H21: =+'RESOLUCIÓN PSF'!B69 -> 0
B22: DIRECCIÓN:
B23: Provincia: | E23: GUANACASTE | J23: Cantón: | M23: TILARAN
B24: Otras señas
B25: =+' FMT 104 TOMA DATOS'!H38 -> 150 este CCSS
B28: CÓDIGOS CIIU | F28: =+'RESOLUCIÓN PSF'!Q37 -> 5610 | O28: TIPO DE RIESGO | T28: =+'RESOLUCIÓN PSF'!C38 -> B
B30: DADO EN LA CIUDAD DE TILARÁN A LOS | L30: 7 | N30: DEL MES DE | R30: Enero
B31: DE | C31: 2019
B33: El presente permiso es válido exclusivamente para la actividad y lugar arriba indicado por el período correspondiente, salvo que las condiciones de este o de su funcionamiento, o las infracciones que cometan a la legislación ameriten la suspensión o cancelación anticipada del mismo o la clausura del establecimiento para garantizar la salud de los trabajadores, de la población y del ambiente en general.
B40: TIENE VALIDEZ DE | G40: ='RESOLUCIÓN PSF'!U69 -> 1 | H40: AÑOS | J40: DEBE SER RENOVADO EL | Q40: ='RESOLUCIÓN PSF'!M6 -> 18 | R40: DE | S40: ='RESOLUCIÓN PSF'!N6 -> MARZO
B41: DE | C41: =C31+G40 -> 2020
B43: Los alcances y condiciones bajo las cuales se otorga este permiso se establecen en la
B44: Resolución | E44: =+'RESOLUCIÓN PSF'!B5 -> DARST-ERS-009-M-2019
B48: =+'RESOLUCIÓN PSF'!M74 -> Hilda María Barrantes Guerrero
B49: Director(a) Área Rectora de Salud Tilarán
B51: COLÓQUESE EN LUGAR VISIBLE
B52: ORIGINAL: Interesado | R52: Cc: Expediente del ARS

Sheet CALCULO LICENCIA
B1: MUNICIPALIDAD DE TILARAN
B2: Proceso de Servicios Ciudadanos y Técnicos
B4: Cálculo del impuesto de patentes
B6: INFORMACIÓN GENERAL
B7: NOMBRE DEL NEGOCIO: | I7: =+' FMT 104 TOMA DATOS'!H28 -> 0
B8: UBICACIÓN: | F8: =+' FMT 104 TOMA DATOS'!H38 -> 150 este CCSS | T8: Nº FINCA: | W8: =+' FMT 104 TOMA DATOS'!H39 -> 0
B10: NOMBRE DEL SOLICITANTE: | I10: Picado Fernandez Ricardo | T10: Nº CÉDULA: | W10: 501450912
B11: REPRESENTANTE LEGAL: | T11: Nº CÉDULA: | W11: 0
B12: PATENTE COMERCIAL SOLICITADA:
B13: CODIGO:
B14: =VLOOKUP(H14,Tabla8[#All],2,0) -> 1133010200000-L2 | H14: ELABORACIÓN DE PRODUCTOS EMULSIFICADOS
B15: =VLOOKUP(H15,Tabla8[#All],2,0) -> NA | H15: NINGÚN OTRA
B16: =VLOOKUP(H16,Tabla8[#All],2,0) -> NA | H16: NINGÚN OTRA
B17: =VLOOKUP(H17,Tabla8[#All],2,0) -> NA | H17: NINGÚN OTRA
B18: =VLOOKUP(H18,Tabla8[#All],2,0) -> NA | H18: NINGÚN OTRA
B19: =VLOOKUP(H19,Tabla8[#All],2,0) -> NA | H19: NINGÚN OTRA
B21: ACTIVIDADES AUTORIZADAS | Y21: 1
B23: TIPO DE RIESGO PSF | Y23: C
B25: CANTIDAD | E25: PUESTO | M25: SALARIO | P25: SALARIO GRUPAL | S25: CARGAS SOCIALES 31.36% | V25: COSTO MENSUAL
B26: 1 | E26: Licenciado Universitario | M26: =VLOOKUP(E26,PARÁMETROS!N362:O370,2,0) -> 705514.95 | P26: =+M26*B26 -> 705514.95 | S26: =+P26*31.36% -> 221249.49 | V26: =+ROUND(S26+P26,0) -> 926764
B27: =+' FMT 104 TOMA DATOS'!AB41-B26 -> -1 | E27: Trabajador no Calificado Genéricos | M27: =VLOOKUP(E27,PARÁMETROS!N362:O370,2,0) -> 330299.11 | P27: =+M27*B27 -> -330299.11 | S27: =+P27*31.36% -> -103581.8 | V27: =+ROUND(S27+P27,0) -> -433881
B28: COSTO ANUAL ESTIMADO POR REMUNERACIONES: | V28: =SUM(V26:Z27)*12 -> 5914596 | AA28: 0.4
B29: OTROS COSTOS ANUALES ESTIMADOS: | V29: =+V28*60%/AA28 -> 8871894 | AA29: =+V29/V30 -> 0.6
B30: TOTAL COSTOS ANUALES ESTIMADOS: | V30: =+V29+V28 -> 14786490
B32: INVERSIÓN INICIAL:
B33: Monto | D33: =+' FMT 104 TOMA DATOS'!W47+' FMT 104 TOMA DATOS'!W48+' FMT 104 TOMA DATOS'!W49+' FMT 104 TOMA DATOS'!W50+' FMT 104 TOMA DATOS'!W51+' FMT 104 TOMA DATOS'!W52 -> 163500000
B34: Puntaje | D34: =+IF(D33>=10000000,1.15,IF(D33<=5000000,1,1.1)) -> 1.15
B36: ZONA: | D36: Comercial Tilarán
B37: Puntaje | D37: =VLOOKUP(D36,PARÁMETROS!N373:O376,2,0) -> 1.15
B39: HORARIO:
B40: Apertura | D40: =+' FMT 104 TOMA DATOS'!I41 -> 0
B41: Cierre | D41: =+' FMT 104 TOMA DATOS'!P41 -> 0
B42: Horas | D42: - 12 horas
B43: Puntaje | D43: =VLOOKUP(D42,PARÁMETROS!N378:O380,2,0) -> 1
B52: PUNTAJE TOTAL: | G52: =+D34+D37+D43 -> 3.3 | K52: =+PARÁMETROS!O381 -> 3.25 | L52: 1 | M52: =+G52 -> 3.3 | N52: X
B53: TOTAL GASTOS ESTIMADOS: | M53: =+M52*L52/K52 -> 1.0153846
B54: COSTO ANUAL ESTIMADO * ( 1+PUNTAJE TOTAL/9 ) | V54: =+M53*V30 -> 15013974
B55: ACTIVIDAD COMERCIAL SEGÚN AGRUPACIÓN: | L55: =+' FMT 104 TOMA DATOS'!J31 -> 0
B56: FACTOR DE UTILIDAD: | H56: =VLOOKUP(L55,PARÁMETROS!B595:C609,2,0) -> #N/A | J56: =+H56-1 -> #N/A | L56: =100%/J56 -> #N/A | O56: =100%+L56 -> #N/A | R56: =+O56/100*100 -> #N/A
B57: INGRESO BRUTO ANUAL ESPERADO: | V57: =+V54*R56 -> #N/A
B58: INGRESO BRUTO MENSUAL ESPERADO: | V58: =+V57/12 -> #N/A
B59: IMPUESTO ANUAL:
B61: De ¢ 0,00 hasta ¢ 750,000,000,00 | N61: 1.75
B62: De ¢750,000,001,00 hasta ¢ 1,500,000,000,00 | N62: =+N61+0.75 -> 2.5
B63: De ¢ 1,500,000,001,00 hasta ¢ 3,000,000,000,00 | N63: =+N62+0.75 -> 3.25
B64: De ¢ 3,000,000,001,00 hasta ¢ más | N64: =+N63+0.75+0.25 -> 4.25
B65: IMPUESTO ANUAL | G65: =+IF(V57<750000000,V57*N61/1000,IF(V57<1500000000,V57*N62/1000,IF(V57<3000000000,V57*N63/1000,V57*N64/1000))) -> #N/A | O65: IMPUESTO TRIMESTRAL | U65: =+ROUND(G65/4,0) -> #N/A
B67: n) A PARTIR DEL TRIMESTRE: | X67: I
B69: CODIGO: | H69: ACTIVIDAD:
B70: =+B14 -> 1133010200000-L2 | H70: =+H14 -> ELABORACIÓN DE PRODUCTOS EMULSIFICADOS | U70: =+$U$65/$Y$21 -> #N/A
B71: =+B15 -> NA | H71: =+H15 -> NINGÚN OTRA | U71: =+$U$65/$Y$21 -> #N/A
B72: =+B16 -> NA | H72: =+H16 -> NINGÚN OTRA | U72: =+$U$65/$Y$21 -> #N/A
B73: =+B17 -> NA | H73: =+H17 -> NINGÚN OTRA | U73: =+$U$65/$Y$21 -> #N/A
B74: =+B18 -> NA | H74: =+H18 -> NINGÚN OTRA | U74: =+$U$65/$Y$21 -> #N/A
B75: =+B19 -> NA | H75: =+H19 -> NINGÚN OTRA | U75: =+$U$65/$Y$21 -> #N/A
B77: 1191020000000-02 | H77: Timbre 2% impuesto de patentes, ley 7788 | U77: =+U65*2% -> #N/A
B79: =VLOOKUP(H79,PARÁMETROS!U157:W161,2,0) -> 1312050410000-08 | H79: =VLOOKUP(Y23,PARÁMETROS!S157:W159,3,0) -> RECOLECCION BASURA COMERCIAL C | U79: =VLOOKUP(H79,PARÁMETROS!U157:W160,3,0) -> 21977.18
B81: ¿En el sector se brinda servicio de recolección de basura? | U81: SI
B83: EJECUTADO POR ( firma ): | H83: =+' FMT 104 TOMA DATOS'!K85 -> Carolay Solera Calvo
B84: FECHA: | D84: =' FMT 104 TOMA DATOS'!Y85 -> 45349.511
B86: REVISADO POR ( firma ): | G86: Frayman Perez Ramirez
B87: FECHA: | D87: 44518
B89: AUTORIZADO POR (firma): | G89: José Antonio Rodríguez Herrera
B90: FECHA: | D90: =D87 -> 44518
C98: =I10 -> Picado Fernandez Ricardo | N98: =+' FMT 104 TOMA DATOS'!H28 -> 0

Sheet RES TRASLADO
C3: Municipalidad de Tilarán
C4: PROCESO DE SERVICIOS CIUDADANOS Y TÉCNICOS
C5: Administración Tributaria
U7: =NOW() -> 45349.511
C8: Vista la solicitud de traslado de licencia comercial presentada por:
C9: Picado Fernandez Ricardo | Q9: cédula nº: | T9: 5-0294-0584
C10: representada(o) en este acto por
C11: cédula nº: | K11: y constatándose el cumplimiento de los requisitos establecidos por
C12: ley; por tanto se resuelve APROBAR el traslado de la(s) licencia(s):
C14: =VLOOKUP(I14,PARÁMETROS!$N$158:$O$316,2,FALSE) -> 1133010200000-L3 | I14: GLAMPING Y CAMPING
C15: =VLOOKUP(I15,PARÁMETROS!$N$158:$O$316,2,FALSE) -> 1133010200000-K4 | I15: CAFETERIA Y REFRESQUERIA
C16: =VLOOKUP(I16,PARÁMETROS!$N$158:$O$316,2,FALSE) -> 1133010200000-K4 | I16: CAFETERIA Y REFRESQUERIA
C17: =VLOOKUP(I17,PARÁMETROS!$N$158:$O$316,2,FALSE) -> 1133010200000-K0 | I17: VENTA DE ACCESORIOS PARA CELULARES
C18: =VLOOKUP(I18,PARÁMETROS!$N$158:$O$316,2,FALSE) -> 1133010200000-I3 | I18: PELUQUERIA Y TRAT. BELLEZA (SPA)
C20: La actividad comercial autorizada, se desarrollará en la finca con número según el Registro Público
C21: =+' FMT 104 TOMA DATOS'!H39 -> 0 | G21: ,ubicada | J21: =+' FMT 104 TOMA DATOS'!H38 -> 150 este CCSS
C22: debiendo el autorizado ajustarse a la legislación que a continuación se indica: | W22: √
C24: √ | D24: ARTÍCULO Nº 90 bis DEL CÓDIGO MUNICIPAL: La licencia referida en el artículo 88, podrá suspenderse por falta de pago de dos o más trimestres, o bien por incumplimiento de los requisitos ordenados en las leyes para el desarrollo de la actividad. ...
C26: √ | D26: REGLAMENTO GENERAL PARA EL OTORGAMIENTO DE PERMISOS SANITARIOS DE FUNCIONAMIENTO DEL MINISTERIO DE SALUD: Ningún establecimiento o actividad a los que se refiere el presente Reglamento, podrá funcionar sin el P.S.F. que otorga el Ministerio, teniendo potestad la autoridad de salud de ejecutar la clausura inmediata del establecimiento o actividad de conformidad con la Ley General de Salud.
D29: ARTICULO 45 DEL REGLAMENTO GENERAL DE PATENTES COMERCIALES Y SIMILARES DE LA MUNICIPALIDAD DE TILARAN, publicado en la gaceta nº 84 del viernes 02 de mayo del año 2008: Todo espectáculo público, ocasional o permanente, que se programe en el cantón de Tilarán, deberá contar con la correspondiente autorización del Coordinador de Hacienda. En ningún caso, se autorizará el desarrollo de actividades de karaoke, música en vivo, discomóvil, conciertos o similares; sean estas permanentes u ocasionales, más allá de las 01:00 horas.; con ésta hora como límite deberán cesar completamente todas las actividades de este tipo, en virtud de que la Corporación Municipal debe resguardar primordialmente el interés público.
D35: ARTÍCULO Nº 3 LEY DE LICORES: Los puestos para expendios de licores al menudeo sólo se pueden obtener por medio de remate público, salvo lo que adelante se dispone sobre patente especial para el expendio de toda clase de licores y cerveza. La venta de cerveza al menudeo, solamente podrá efectuarse en los puestos de licores y una vez satisfechas las patentes respectivas establecidas o que se establezcan para el expendio de cerveza.
D39: ARTÍCULO 20 LEY N° 9505. Todos los patentados tienen la obligación de presentar, cada año, la declaración jurada del impuesto ante la Municipalidad de Tilarán y anexar la fotocopia de la declaración del impuesto sobre la renta del período sujeto a gravar, debidamente recibida por la Dirección General de Tributación, cualquiera que sea la cuantía de sus ingresos o ventas brutas obtenidas. En el mes de enero de cada año, podrá solicitarse en Plataforma de Servicios, el respectivo formulario.
D43: ARTÍCULO Nº 13 LEY DE JUEGOS: En las capitales de provincia y demás ciudades, los billares públicos sólo podrán abrirse de las cuatro de la tarde a las once de la noche, en los días de trabajo, y de las doce del día a las once de la noche en los días de fiesta legal. En las otras poblaciones, estos establecimientos se abrirán de las doce del día a las diez de la noche en días feriados y de las seis de la tarde a las diez de la noche en los días de trabajo.
N47: Zeidy Campos Artavia
N48: ASISTENTE TECNICO
N51: José Antonio Rodríguez Herrera
C52: Original | E52: =+C9 -> Picado Fernandez Ricardo | N52: COORDINADOR PROCESO
C53: Copia 1: | E53: Oficina de gestión de cobros
C54: Copia 2: | E54: Oficina de catastro y bienes inmuebles | N54: UL
N56: Colóquese en lugar visible

Sheet RES TRASPASO
C3: MUNICIPALIDAD DE TILARÁN
C4: PROCESO SERVICIOS CIUDADANOS Y TÉCNICOS
R6: =NOW() -> 45349.511
C7: Vista la solicitud de traspaso de licencia comercial presentada por:
C8: =+'[5]TOMA DATOS'!I12 -> BARRANTES CHAVES GERARDO | Q8: cédula nº: | T8: =+'[5]TOMA DATOS'!W12 -> 900260738
C9: representada(o) en este acto por | L9: =+'[5]TOMA DATOS'!I13 -> 0
C10: cédula nº: | F10: =+'[5]TOMA DATOS'!W13 -> 0 | K10: para traspasar las licencias comerciales, a su nombre y constatándose
C11: el cumplimiento de los requisitos establecidos por ley, por tanto se resuelve, APROBAR el traspaso de
C12: la(s) licencia(s):
C14: 1133010200000 | H14: =+'[5]TOMA DATOS'!G19 -> 0 | I14: TALLER MECANICO
C15: 1133010200000 | H15: =+'[5]TOMA DATOS'!G20 -> 0 | I15: =+'[5]TOMA DATOS'!H20 -> OFICINA DE SERVICIOS
C16: 1133010200000 | H16: =+'[5]TOMA DATOS'!G21 -> 0 | I16: =+'[5]TOMA DATOS'!H21 -> ELABORACION DE JUGOS
C17: 1133010200000 | H17: =+'[5]TOMA DATOS'!G22 -> 0 | I17: =+'[5]TOMA DATOS'!H22 -> VENTA DE VIDRIOS
C18: 1133010200000 | H18: =+'[5]TOMA DATOS'!G23 -> 0 | I18: =+'[5]TOMA DATOS'!H23 -> BAR
C20: La actividad comercial autorizada, se desarrollará en la finca con número según el Registro Público
C21: =+'[5]TOMA DATOS'!W10 -> 49349-000 | G21: , ubicada | J21: =+'[5]TOMA DATOS'!F10 -> 475 SUR DEL BANCO NACIONAL DE C.R TILARAN
C22: debiendo el autorizado ajustarse a la legislación que a continuación se indica: | W22: √
C24: √ | D24: ARTÍCULO Nº 81 bis DEL CÓDIGO MUNICIPAL: La licencia referida en el artículo 79, podrá suspenderse por falta de pago de dos o más trimestres, o bien por incumplimiento de los requisitos ordenados en las leyes para el desarrollo de la actividad. ...
C26: √ | D26: ARTÍCULO 20 LEY N° 9505. Todos los patentados tienen la obligación de presentar, cada año, la declaración jurada del impuesto ante la Municipalidad de Tilarán y anexar la fotocopia de la declaración del impuesto sobre la renta del período sujeto a gravar, debidamente recibida por la Dirección General de Tributación, cualquiera que sea la cuantía de sus ingresos o ventas brutas obtenidas. En el mes de enero de cada año, podrá solicitarse en Plataforma de Servicios, el respectivo formulario.
D29: ARTICULO 45 DEL REGLAMENTO GENERAL DE PATENTES COMERCIALES Y SIMILARES DE LA MUNICIPALIDAD DE TILARAN, publicado en la gaceta nº 84 del viernes 02 de mayo del año 2008: Todo espectáculo público, ocasional o permanente, que se programe en el cantón de Tilarán, deberá contar con la correspondiente autorización del Coordinador de Hacienda. En ningún caso, se autorizará el desarrollo de actividades de karaoke, música en vivo, discomóvil, conciertos o similares; sean estas permanentes u ocasionales, más allá de las 01:00 horas.; con ésta hora como límite deberán cesar completamente todas las actividades de este tipo, en virtud de que la Corporación Municipal debe resguardar primordialmente el interés público.
D35: ARTÍCULO Nº 3 LEY DE LICORES: Los puestos para expendios de licores al menudeo sólo se pueden obtener por medio de remate público, salvo lo que adelante se dispone sobre patente especial para el expendio de toda clase de licores y cerveza. La venta de cerveza al menudeo, solamente podrá efectuarse en los puestos de licores y una vez satisfechas las patentes respectivas establecidas o que se establezcan para el expendio de cerveza.
D39: ARTÍCULO Nº 1 LEY DE HORARIO DE FUNCIONAMIENTO EN EXPENDIOS DE BEBIDAS ALCOHÓLICAS: Prohíbese la venta de bebidas alcohólicas a menores de edad, así como su permanencia en establecimientos cuya actividad principal consista en venderlas para ser consumidas ahí mismo. La venta de cerveza al menudeo, solamente podrá efectuarse en los puestos de licores y una vez satisfechas las patentes respectivas establecidas o que se establezcan para el expendio de cerveza.
D43: ARTÍCULO Nº 13 LEY DE JUEGOS: En las capitales de provincia y demás ciudades, los billares públicos sólo podrán abrirse de las cuatro de la tarde a las once de la noche, en los días de trabajo, y de las doce del día a las once de la noche en los días de fiesta legal. En las otras poblaciones, estos establecimientos se abrirán de las doce del día a las diez de la noche en días feriados y de las seis de la tarde a las diez de la noche en los días de trabajo.
C47: Original | E47: =+C8 -> BARRANTES CHAVES GERARDO | N47: =+'[5]TOMA DATOS'!G30 -> María Cecilia Prendas Martínez
C48: Copia 1: | E48: Oficina de gestión de cobros | N48: Asistencia Tecnica
N49: UL
N51: Colóquese en lugar visible

Sheet RESOLUCION COMERCIAL
C3: MUNICIPALIDAD DE TILARAN
C4: Proceso de Servicios Ciudadanos y Técnicos
V6: =+'CALCULO LICENCIA'!D87 -> 44518
C7: Vista la solicitud de licencia comercial presentada por:
C8: ='CALCULO LICENCIA'!I10 -> Picado Fernandez Ricardo | Q8: cédula nº: | T8: ='CALCULO LICENCIA'!W10 -> 501450912
C9: representada(o) en este acto por | L9: ='CALCULO LICENCIA'!H11 -> 0
C10: cédula nº: | F10: ='CALCULO LICENCIA'!W11 -> 0 | K10: ésta Coordinación resuelve de conformidad con el artículo ochenta
C11: y ocho, siguientes y concordantes del Código Municipal APROBAR el desarrollo de las siguientes
C12: actividades:
C14: =VLOOKUP(I14,PARÁMETROS!$N$158:$O$316,2,FALSE) -> 1133010200000-L2 | I14: =+'CALCULO LICENCIA'!H70 -> ELABORACIÓN DE PRODUCTOS EMULSIFICADOS
C15: =VLOOKUP(I15,PARÁMETROS!$N$158:$O$316,2,FALSE) -> NA | I15: =+'CALCULO LICENCIA'!H71 -> NINGÚN OTRA
C16: =VLOOKUP(I16,PARÁMETROS!$N$158:$O$316,2,FALSE) -> NA | I16: =+'CALCULO LICENCIA'!H72 -> NINGÚN OTRA
C17: =VLOOKUP(I17,PARÁMETROS!$N$158:$O$316,2,FALSE) -> NA | I17: =+'CALCULO LICENCIA'!H73 -> NINGÚN OTRA
C18: =VLOOKUP(I18,PARÁMETROS!$N$158:$O$316,2,FALSE) -> NA | I18: =+'CALCULO LICENCIA'!H74 -> NINGÚN OTRA
C19: =VLOOKUP(I19,PARÁMETROS!$N$158:$O$316,2,FALSE) -> NA | I19: =+'CALCULO LICENCIA'!H75 -> NINGÚN OTRA
C21: La actividad comercial autorizada, se desarrollará en la finca con número según el Registro Público
C22: =+' FMT 104 TOMA DATOS'!H39 -> 0 | G22: ,ubicada | J22: =+' FMT 104 TOMA DATOS'!H38 -> 150 este CCSS
C23: debiendo el autorizado ajustarse a la legislación que a continuación se indica: | W23: √
C25: √ | D25: ARTÍCULO Nº 90 bis DEL CÓDIGO MUNICIPAL: La licencia referida en el artículo 88, podrá suspenderse por falta de pago de dos o más trimestres, o bien por incumplimiento de los requisitos ordenados en las leyes para el desarrollo de la actividad. ...
C27: √ | D27: REGLAMENTO GENERAL PARA EL OTORGAMIENTO DE PERMISOS SANITARIOS DE FUNCIONAMIENTO DEL MINISTERIO DE SALUD: Ningún establecimiento o actividad a los que se refiere el presente Reglamento, podrá funcionar sin el P.S.F. que otorga el Ministerio, teniendo potestad la autoridad de salud de ejecutar la clausura inmediata del establecimiento o actividad de conformidad con la Ley General de Salud.
D30: ARTICULO 42 DEL REGLAMENTO GENERAL DE PATENTES COMERCIALES Y SIMILARES DE LA MUNICIPALIDAD DE TILARAN, publicado en Gaceta n° 43 del 03 de marzo de 2014: Todo espectáculo público, ocasional o permanente, que se programe en el cantón de Tilarán, deberá contar con la correspondiente autorización del Coordinador de Hacienda. En ningún caso, se autorizará el desarrollo de actividades de música en vivo, para grupos mayores a tres integrantes, discomóviles, conciertos o similares, sean estos permanentes u ocasionales, más allá de las 01:00 horas. Con ésta hora como límite deberán cesar completamente todas las actividades de este tipo, en virtud de que la Corporación Municipal debe resguardar primordialmente el interés público. Las actividades de karaokes, marimbas y música en vivo con grupos de hasta tres integrantes, no requerirán de la autorización municipal.
D36: ARTÍCULO 3 LEY N° 9047-2012 La comercialización al detalle de bebidas con contenido alcohólico requiere licencia de la municipalidad del cantón donde se ubique el negocio. La licencia que otorguen las municipalidades para la comercialización de bebidas con contenido alcohólico se denominará “licencia de expendio de bebidas con contenido alcohólico” y no constituye un activo, por lo que no se puede vender, canjear, arrendar, transferir, traspasar ni enajenar en forma alguna.
D40: ARTÍCULO 20 LEY N° 9505. Todos los patentados tienen la obligación de presentar, cada año, la declaración jurada del impuesto ante la Municipalidad de Tilarán y anexar la fotocopia de la declaración del impuesto sobre la renta del período sujeto a gravar, debidamente recibida por la Dirección General de Tributación, cualquiera que sea la cuantía de sus ingresos o ventas brutas obtenidas. En el mes de enero de cada año, podrá solicitarse en Plataforma de Servicios, el respectivo formulario.
D44: ARTÍCULO Nº 13 LEY DE JUEGOS: En las capitales de provincia y demás ciudades, los billares públicos sólo podrán abrirse de las cuatro de la tarde a las once de la noche, en los días de trabajo, y de las doce del día a las once de la noche en los días de fiesta legal. En las otras poblaciones, estos establecimientos se abrirán de las doce del día a las diez de la noche en días feriados y de las seis de la tarde a las diez de la noche en los días de trabajo.
N49: =+'CALCULO LICENCIA'!G86 -> Frayman Perez Ramirez
N50: =VLOOKUP(N49,PARÁMETROS!E109:H124,4,0) -> ASISTENTE TÉCNICO
N53: José Antonio Rodríguez Herrera
C54: Original | E54: =+C8 -> Picado Fernandez Ricardo | N54: =VLOOKUP(N53,PARÁMETROS!$E$111:$H$126,4,0) -> COORDINADOR
C55: Copia 1: | E55: Oficina de gestión de cobros | N55: **********UL**********
C56: Copia 2: | E56: Oficina de Catastro
N57: Colóquese en lugar visible

Sheet CERTIFICADO
B2: GOBIERNO MUNICIPAL DE TILARÁN
B3: Proceso de Servicios Ciudadanos y Técnicos
B6: CERTIFICADO DE PATENTE COMERCIAL
B8: NOMBRE DEL NEGOCIO: | I8: =+' FMT 104 TOMA DATOS'!H28 -> 0
B9: UBICACIÓN: | F9: =+' FMT 104 TOMA DATOS'!H38 -> 150 este CCSS
B10: ACTIVIDADES COMERCIALES AUTORIZADAS POR LA MUNICIPALIDAD DE TILARÁN:
B11: 1 | C11: =+'RESOLUCION COMERCIAL'!I14 -> ELABORACIÓN DE PRODUCTOS EMULSIFICADOS
B12: =1+B11 -> 2 | C12: =+'RESOLUCION COMERCIAL'!I15 -> NINGÚN OTRA
B13: =1+B12 -> 3 | C13: =+'RESOLUCION COMERCIAL'!I16 -> NINGÚN OTRA
B14: =1+B13 -> 4 | C14: =+'RESOLUCION COMERCIAL'!I17 -> NINGÚN OTRA
B15: NOMBRE DEL PATENTADO: | I15: ='CALCULO LICENCIA'!I10 -> Picado Fernandez Ricardo | AB15: N° CEDULA: | AE15: ='CALCULO LICENCIA'!W10 -> 501450912
B16: REPRESENTANTE LEGAL: | H16: ='CALCULO LICENCIA'!H11 -> 0 | AB16: =+AB15 -> N° CEDULA: | AE16: ='CALCULO LICENCIA'!W11 -> 0
B17: EL PORTADOR DE LA CÉDULA NÚMERO: | L17: =AE15 -> 501450912 | R17: HA CUMPLIDO CON LOS REQUISITOS NECESARIOS PARA OTORGARLE LA(S)
B18: LICENCIA(S) MUNICIPALES HASTA EL 31 DE DICIEMBRE DEL AÑO: | R18: 2023 | U18: ////Colóquese en lugar visible////
B20: Permiso Sanitario de Funcionamiento # | K20: 665 | M20: DEL | N20: 21 | O20: DE | P20: DICIEMBRE | U20: DE | V20: 2022 | Y20: El establecimiento se clasifica dentro del CIIU | AJ20: 4520
B21: del grupo de riesgo | G21: B | H21: por lo que el Área Rectora de Salud, procedión a otorgar el PSF por | W21: 5 | X21: años, debiendo renovarse el | AE21: =+N20 -> 21 | AF21: de | AG21: =+P20 -> DICIEMBRE
B22: de | C22: =+V20+W21 -> 2027
B27: =+'RESOLUCION COMERCIAL'!N49 -> Frayman Perez Ramirez
B28: =+'RESOLUCION COMERCIAL'!N50 -> ASISTENTE TÉCNICO
B29: OBSERVACIONES:

Sheet INFORME LICORES
C2: GOBIERNO LOCAL DE TILARAN
C3: Proceso de Servicios Ciudadanos y Técnicos
C6: INFORME ADMINISTRATIVO PARA EL OTORGAMIENTO Y CALIFICACIÓN
C7: DE LICENCIAS PARA EL EXPENDIO DE LICOR
C8: Ley de Regulación y Comercialización de bebidas con contenido alcohólico N° 9047
B10: EL SUSCRITO, | F10: José Antonio Rodríguez Herrera | L10: , PORTADOR DE LA CÉDULA DE IDENTIDAD N° | T10: 108770167
B11: EN MI CONDICIÓN DE | G11: Coordinador PSCT | L11: HAGO CONSTAR QUE PROCEDÍ A VALORAR LA PRESENTE SOLICI-
B12: TUD PARA EL OTORGAMIENTO DE UNA LICENCIA PARA EL EXPENDIO DE LICOR, DETERMINÁNDOSE QUE EL PROYECTO:
C13: X | E13: CUMPLE | K13: NO CUMPLE | N13: con las condiciones para otorgar la licencia N°:
C15: LCBCA | E15: 333333 | O15: y la categoría | R15: =VLOOKUP(+' FMT 104 TOMA DATOS'!C35,PARÁMETROS!B617:C628,2,FALSE) -> #N/A
B17: EL HORARIO SERÁ EL SIGUIENTE: | I17: =VLOOKUP(R15,PARÁMETROS!C617:D628,2,0) -> #N/A
B19: 1. INFORMACIÓN GENERAL
C21: NOMBRE DEL NEGOCIO: | H21: =+' FMT 104 TOMA DATOS'!H28:AD28 -> 0 | R21: UBICACIÓN:
C22: =+' FMT 104 TOMA DATOS'!H38 -> 150 este CCSS
C23: N° DE FINCA: | F23: =+' FMT 104 TOMA DATOS'!H39 -> 0
C24: DISTRITO: | E24: =+' FMT 104 TOMA DATOS'!E37:Q37 -> 0
C25: PATENTADO (comercial): | H25: =+CERTIFICADO!I15 -> Picado Fernandez Ricardo | R25: Nº CÉDULA: | T25: =+CERTIFICADO!AE15 -> 501450912
C26: REPRESENTANTE LEGAL: | H26: =+CERTIFICADO!H16 -> 0 | R26: Nº CÉDULA: | T26: =+CERTIFICADO!AE16 -> 0
B39: 2. CALIFICACIÓN DE LICENCIAS PARA EL EXPENDIO DE LICOR
C41: P= ((0,6 * pe/NTcs) + (0,3 * van/VNcs) + (0,1 * ate/Atcs)) *100
C43: P: | E43: Puntaje obtenido por el negocio.
C44: pe: | E44: Personal promedio empleado por el negocio durante el último período fiscal.
C45: NTcs: | E45: Parámetro de referencia para el número de trabajadores de los sectores de comercio y servicios.
C46: van: | E46: Valor de las ventas anuales netas del negocio en el último período fiscal.
C47: VNcs: | E47: Parámetro monetario de referencia para las ventas netas de los sectores de comercio y servicios.
C48: ate: | E48: Valor de los activos totales netos de la empresa en el último período fiscal.
C49: ATcs: | E49: Parámetro monetario de referencia para los activos netos de los sectores de comercio y servicios.
C51: pe | E51: =+' FMT 104 TOMA DATOS'!AB41 -> 0
C52: NTcs | E52: 30 | K52: Conozca el Tamaño de su Empresa
C53: van | E53: =+' FMT 104 TOMA DATOS'!W53*12 -> 300000000 | K53: http://pyme.go.cr/cuadro5.php?id=1
C54: VNcs | E54: 3092899107
C55: ate | E55: =+' FMT 104 TOMA DATOS'!W47+' FMT 104 TOMA DATOS'!W48+' FMT 104 TOMA DATOS'!W49+' FMT 104 TOMA DATOS'!W50 -> 154000000 | N55: =0.6*(+E51/+E52) -> 0
C56: ATcs | E56: 966781718 | N56: =0.3*(E53/E54) -> 0.029098912
N57: =0.1*(E55/E56) -> 0.015929139
N58: =SUM(N55:N57) -> 0.045028051
L59: P: | N59: =+N58*100 -> 4.5028051
C62: Con sustento en la anterior fórmula, las licencias se clasificarán en las siguientes subcategorías de acuerdo con el
C63: puntaje obtenido:
C64: Subcategoría 1. | G64: puntaje obtenido menor o igual a 10
C65: Subcategoría 2. | G65: puntaje obtenido mayor de 10 y menor o igual a 35
C66: Subcategoría 3. | G66: puntaje obtenido mayor de 35, pero menor o igual a 100
C67: Subcategoría 4. | G67: puntaje obtenido mayor de 100
C69: RESULTADO | U69: =IF(N59<=10,"Sub categoría 1","Subcategoría 2") -> Sub categoría 1
C71: Resolución No. 015-2017.' Ministerio de Economía, Industria y Comercio: Dirección General de Apoyo a la Pequeña y Mediana Empresa.-San José a las catorce horas del 17 de marzo del dos mil diecisiete.
C73: c) Para determinar el tamaño de las empresas de los sectores de comercio y servicios, se utilizará la siguiente fórmula: P= [(0,6 x pe/30) + (0,3 x inpf/C3.092.899.107) + (0,1 x an/C966.781.718)] x 100
C78: 3 ¿EL ESTABLECIMIENTO CUENTA CON CONDICIONES MÍNIMAS PARA SERVICIO DE RESTAURANTE?
C80: SI
C82: 4 EL ESTABLECIMIENTO CUENTA CON DECLARATORIA DE INTERÉS TURÍSTICO (ICT), PARA:
C84: No aplica | G84: Empresas de hospedaje con menos de quince habitaciones.
C85: No aplica | G85: Empresas de hospedaje con quince o más habitaciones.
C86: No aplica | G86: Marinas y atracaderos.
C87: No aplica | G87: Empresas gastronómicas.
C88: No aplica | G88: Centros de diversión nocturna.
C89: No aplica | G89: Actividades temáticas.
C91: 5 TARIFA TRIMESTRAL POR APLICAR SEGÚN EL TIPO DE LICENCIA:
K93: Categoría 1 | S93: Categoría 2
K95: TARIFA CABECERA CANTÓN | O95: TARIFA DEMÁS POBLACIÓN
C96: 1) Licoreras y similares (categoría A): | K96: =+PARÁMETROS!F617 -> 115550 | O96: =+PARÁMETROS!G617 -> 115550 | T96: =+PARÁMETROS!I617 -> 173325
C97: 2) Cantinas, bares y tabernas sin actividad de baile (categoría B1):
K98: =+PARÁMETROS!F618 -> 115550 | O98: =+PARÁMETROS!G618 -> 57775 | T98: =+PARÁMETROS!I618 -> 173325
C99: 3) Salones de baile, discotecas, clubes nocturnos y cabarés con actividad de baile (categoría B2):
K100: =+PARÁMETROS!F619 -> 115550 | O100: =+PARÁMETROS!G619 -> 57775 | T100: =+PARÁMETROS!I619 -> 173325
C101: 4) Restaurantes y similares (categoría C): | K101: =+PARÁMETROS!F620 -> 115550 | O101: =+PARÁMETROS!G620 -> 115550 | T101: =+PARÁMETROS!I620 -> 173325
C102: 5) Mini - súper (categoría D1): | K102: =+PARÁMETROS!F621 -> 57775 | O102: =+PARÁMETROS!G621 -> 57775 | T102: =+PARÁMETROS!I621 -> 173325
C103: 6) Supermercado (categoría D2): | K103: =+PARÁMETROS!F622 -> 231100 | O103: =+PARÁMETROS!G622 -> 231100 | T103: =+PARÁMETROS!I622 -> 346650
C104: 7) Empresas de hospedaje con menos de quince habitaciones (Categorías E.1.a):
K105: =+PARÁMETROS!F623 -> 115550 | O105: =+PARÁMETROS!G623 -> 86662.5 | T105: =+PARÁMETROS!I623 -> 173325
C106: 8) Empresas de hospedaje con quince o más habitaciones (Categorías E.1.b): Un impuesto igual a dos salarios base.
K107: =+PARÁMETROS!F624 -> 231100 | O107: =+PARÁMETROS!G624 -> 173325 | T107: =+PARÁMETROS!I624 -> 288875
C108: 9) Marinas y atracaderos declarados de interés turístico por el ICT (categoría E3):
K109: =+PARÁMETROS!F625 -> 231100 | O109: =+PARÁMETROS!G625 -> 231100 | T109: =+PARÁMETROS!I625 -> 346650
C110: 10) Empresas gastronómicas declaradas de interés turístico por el I.C.T (categoría E3):
K111: =+PARÁMETROS!F626 -> 231100 | O111: =+PARÁMETROS!G626 -> 231100 | T111: =+PARÁMETROS!I626 -> 346650
C115: 11) Centros de diversión nocturna declarados de interés turístico por el I.C.T (categoría E4):
K116: =+PARÁMETROS!F627 -> 231100 | O116: =+PARÁMETROS!G627 -> 231100 | T116: =+PARÁMETROS!I627 -> 346650
C117: 12) Actividades temáticas declaradas de interés turístico por el I.C.T (categoría E5):
K118: =+PARÁMETROS!F628 -> 115550 | O118: =+PARÁMETROS!G628 -> 115550 | T118: =+PARÁMETROS!I628 -> 173325
C120: TARIFA TRIMESTRAL APLICABLE | I120: 21 21 01 00 00 00 0 0C | S120: =+K101 -> 115550
C121: Licencia de expendio de bebidas con contenido alcohólico
C123: TIMBRE ANUAL | I123: 11 91 02 00 00 00 0 03 | S123: 5000
C124: Timbre pro parque, Ley 7788
C126: A PARTIR DEL TRIMESTRE: | S126: =+'CALCULO LICENCIA'!X67 -> I
C129: HECHO POR: | F129: José Antonio Rodríguez Herrera
C130: FECHA: | E130: =NOW() -> 45349.511

Sheet RESOLUCION LICORES
C4: Municipalidad de Tilarán
C5: PROCESO DE SERVICIOS CIUDADANOS Y TÉCNICOS
C7: RESOLUCIÓN: LCBCA | K7: =+'INFORME LICORES'!E15 -> 333333 | T7: =NOW() -> 45349.511
C8: Vista la solicitud de licencia para la comercialización de bebidas con contenido alcohólico presentada
C9: por: | E9: =+CERTIFICADO!I15 -> Picado Fernandez Ricardo
C10: cédula nº: | F10: =+CERTIFICADO!AE15 -> 501450912 | K10: representada(o) en este acto por | T10: =+CERTIFICADO!H16 -> 0
C11: cédula nº: | F11: =+CERTIFICADO!AE16 -> 0 | K11: ésta Coordinación resuelve de conformidad con el acuerdo municipal
C12: n° 001, tomado en la Sesión Extraordinaria n° 068 del 22 de octubre del año 2012, | X12: APROBAR
C13: licencia para la comercialización de bebidas con contenido alcohólico, para el funcionmiento del esta-
C14: blecimiento | F14: =+' FMT 104 TOMA DATOS'!H28 -> 0 | P14: ubicado en la finca matrícula | X14: =+'RESOLUCION COMERCIAL'!C22 -> 0
C15: =+' FMT 104 TOMA DATOS'!E37 -> 0
C16: asignándosele la categoría | J16: =+'INFORME LICORES'!R15 -> #N/A | L16: con horario: | O16: =+'INFORME LICORES'!I17 -> #N/A
C17: el autorizado ajustarse a la legislación que a continuación se indica: | W17: √
C18: √ | D18: La comercialización al detalle de bebidas con contenido alcohólico requiere licencia de la municipalidad del cantón donde se ubique el negocio. La licencia que otorguen las municipalidades para la comercialización de bebidas con contenido alcohólico se denominará “licencia de expendio de bebidas con contenido alcohólico” y no constituye un activo, por lo que no se puede vender, canjear, arrendar, transferir, traspasar ni enajenar en forma alguna. ARTÍCULO 3 LEY N° 9047-2012
C21: √ | D21: Ésta licencia podrá suspenderse por falta de pago, o bien, por incumplimiento de los requisitos y las prohibiciones establecidos por esta ley y su reglamento, que regulan el desarrollo de la actividad. El pago extemporáneo de los derechos trimestrales está sujeto a una multa del uno por ciento (1%) por mes sobre el monto no pagado o fracción de mes hasta un máximo de un veinte por ciento (20%), y al pago de intereses. ARTÍCULO 10 LEY N° 9047-2012
C24: √ | D24: La edad mínima para el consumo de bebidas con contenido alcohólico será de dieciocho años cumplidos. Los expendedores de bebidas con contenido alcohólico deberán solicitar la cédula de identificación u otro documento público oficial cuando tengan dudas con respecto a la edad de la persona, a fin de cumplir con la prohibición del expendio, a título oneroso o el otorgamiento gratuito, de bebidas con contenido alcohólico a personas menores de edad. ARTÍCULO 13 LEY N° 9047-2012
C27: √ | D27: Será sancionado con una multa de entre uno y diez salarios base quien: a) Exceda las limitaciones de comercialización de la licencia permanente o licencia temporal con que opere. b) Comercialice bebidas con contenido alcohólico fuera de los horarios establecidos para su licencia. c) Venda, canjee, arriende, transfiera, enajene, traspase o subarriende de forma alguna la licencia o por cualquier medio permita su utilización indebida por terceros en contravención de lo dispuesto en el artículo 3 de esta ley. ARTÍCULO 14 LEY N° 9047-2012
C31: √ | D31: Quien venda o facilite bebidas con contenido alcohólico a menores de edad y a personas con limitaciones cognoscitivas y volitivas será sancionado con una multa de entre uno y quince salarios base. La permanencia de personas menores de edad en los establecimientos con licencia clase B y E4 será sancionada con una multa de entre uno y quince salarios base. ARTÍCULO 16 LEY N° 9047-2012
C34: √ | D34: Quien venda bebidas con contenido alcohólico en las vías públicas y sitios públicos, casas de habitación y en aquellos otros lugares donde se desarrollan actividades deportivas, mientras se efectúa el espectáculo, recibirán sanción de entre diez y treinta días multa. ARTÍCULO 19 LEY N° 9047-2012
C37: √ | D37: Quien expenda o facilite, a título oneroso o gratuito, bebidas con contenido alcohólico a menores de edad o a personas con evidentes limitaciones cognoscitivas y volitivas, recibirá sanción de seis meses a tres años de prisión y se ordenará el cierre del establecimiento.. ARTÍCULO 22 LEY N° 9047-2012
C40: √ | D40: Una vez aprobada la licencia en la municipalidad, deberá ser cancelada en un plazo máximo de quince días hábiles en las cajas recaudadoras de la Municipalidad, a partir del día siguiente a su notificación. En caso de no cumplirse con ese plazo, se procederá a archivar la solicitud sin más trámite.
N43: José Antonio Rodríguez Herrera
B44: Cc: | N44: COORDINADOR
C45: Original | E45: =+E9 -> Picado Fernandez Ricardo | N45: UL
C46: Copia 1: | E46: =+K7 -> 333333
N47: Colóquese en lugar visible

Sheet CERTIFICADO LICORES 
B5: MUNICIPALIDAD DE TILARAN
B6: PROCESO DE SERVICIOS CIUDADANOS Y TÉCNICOS
B10: CERTIFICADO DE PATENTE DE LICORES
B11: Ley de Regulación y Comercialización de bebidas con contenido alcohólico N° 9047
B13: N° PATENTE: | F13: LCBCA | J13: CATEGORÍA:
B14: =+'RESOLUCION LICORES'!K7 -> 333333 | J14: =+'RESOLUCION LICORES'!J16 -> #N/A
B15: DISTRITO: | E15: =+' FMT 104 TOMA DATOS'!E37:Q37 -> 0 | P15: HORARIO:
B16: N° FINCA: | E16: =+' FMT 104 TOMA DATOS'!H39 -> 0 | P16: =+'RESOLUCION LICORES'!O16 -> #N/A
B18: NOMBRE DEL NEGOCIO: | G18: =+'RESOLUCION LICORES'!F14:O14 -> 0
B19: PATENTADO (comercial): | G19: =+CERTIFICADO!I15 -> Picado Fernandez Ricardo | R19: Nº CÉDULA: | T19: =+CERTIFICADO!AE15 -> 501450912
B20: REPRESENTANTE LEGAL: | G20: =+'RESOLUCION COMERCIAL'!L9 -> 0 | R20: Nº CÉDULA: | T20: =+CERTIFICADO!AE16 -> 0
B21: Nº TELEFÓNO: | F21: =+' FMT 104 TOMA DATOS'!E19 -> 0 | L21: CORREO ELECTRÓNICO: | Q21: =+' FMT 104 TOMA DATOS'!R19 -> 0
B27: =+'RESOLUCION LICORES'!N43 -> José Antonio Rodríguez Herrera
B28: =+'RESOLUCION LICORES'!N44 -> COORDINADOR
E31: Tilarán, | G31: =+'CALCULO LICENCIA'!D84 -> 45349.511
B33: ORIGINAL: | E33: Patentado
B34: COPIA: | E34: LCBCA | F34: =+'RESOLUCION COMERCIAL'!M6 -> 0
B36: Colóquese en lugar visible

Sheet DECLARACIÓN JURADA  (3)
B2: DECLARACIÓN JURADA PARA TRÁMITES DE SOLICITUD DE PERMISOS SANITARIOS DE FUNCIONAMIENTO POR PRIMERA VEZ O RENOVACIONES
B4: Yo | C4: =+' FMT 104 TOMA DATOS'!I10 -> 0 | M4: con domicilio en | Q4: distrito: | S4: =+' FMT 104 TOMA DATOS'!E15 -> 0
B5: cantón | D5: =+' FMT 104 TOMA DATOS'!U14 -> 0 | M5: provincia | P5: =+' FMT 104 TOMA DATOS'!I14 -> 0
B6: Otras señas | E6: =+' FMT 104 TOMA DATOS'!H16 -> 0
B7: en mi condición de | H7: =+' FMT 104 TOMA DATOS'!R11 -> Representante Legal
B8: de la sociedad denominada (Razón social):
B9: =+' FMT 104 TOMA DATOS'!M12 -> 0
B10: propietario del establecimiento comercial
B11: =+' FMT 104 TOMA DATOS'!H28 -> 0
B12: cuyas actividades son: | H12: =+' FMT 104 TOMA DATOS'!M30 -> 0
H13: =+' FMT 104 TOMA DATOS'!M30 -> 0
B14: solicito sea otorgado | G14: Certificado Veterinario de Operación requerido en la Ley General del Servicio Nacional de Salud Animal.
B15: a mi representada, para lo cual declaro bajo fe de juramento y que de no decir la verdad incurro en perjurio sancionado con pena de prisión según el Código Penal y consciente de la importancia de lo aquí anotado, lo siguiente: Primero. Que la actividad señalada en el formulario de solicitud del PSF, cumple con toda la normativa establecida para el caso en concreto. Segundo. Que la información que contiene el formulario unificado que adjunto a esta declaración es verdadera. Tercero. Que en cumplimiento de lo establecido en los artículos 44, 74 y 74 bis de la Ley Constitutiva de la Caja Costarricense de Seguro Social y el artículo 66 del Reglamento del Seguro Social, me comprometo a la inscripción como patrono, trabajador independiente o en ambas modalidades dentro de los ocho días al inicio de la actividad. Asimismo, declaro estar al día en el pago de mis obligaciones con esa institución. Cuarto. Que cumplo con lo establecido en la Ley N.º 9028 del 22 de marzo de 2012 "Ley General de Control de Tabaco y sus Efectos Nocivos a la Salud" y sus reglamentos (así adicionado el punto "tercer bis" anterior por el inciso a) del artículo 61 del Reglamento a la Ley General de Control de Tabaco y sus Efectos Nocivos en la Salud, aprobado mediante el decreto ejecutivo N.º 37185-S de 26 de junio de 2012) Quinto. Que conforme a lo establecido en el Decreto N.º 36979-MEIC, RTCR 458:2011 Reglamento de Oficialización del Código Eléctrico de Costa Rica para la Seguridad de la Vida y de la Propiedad, artículo 5°, inciso 5.2.4.3, cuando corresponda según el artículo 21 inciso 7 del Reglamento General para Autorizaciones y de Permisos Sanitarios de Funcionamiento Otorgados por el Ministerio de Salud y sus reformas, cumplo con lo ahí exigido. Sexto. Que de conformidad con lo establecido en el Reglamento General para Autorizaciones y Permisos Sanitarios de Funcionamiento Otorgados por el Ministerio de Salud en su Artículo 9, Condiciones Previas, mi representada cumple con lo ahí solicitado y para ello suministro la siguiente información según corresponda: (Aplica solo para trámites de permisos sanitarios de funcionamiento por primera vez).
C31: 1. Resolución municipal de ubicación - uso de suelo - otorgada por la Municipalidad de Tilarán.
C32: 2. Viabilidad ambiental emitida por SETENA.
C33: 3. Oficio emitido por ente administrador de alcantarillado sanitario indicando que acepta el volúmen y la calidad físicoquímica de las aguas residuales del establecimiento que serán vertidas en el alcantarillado sanitario.
B36: NA | C36: 4. Permiso de vertido emitido por el MINAE que permita descargar aguas residuales al cuerpo de agua.
B37: NA | C37: 5. Certificado de regencia profesional otorgada por el Colegio Profesional ccorrespondiente.
B38: NA | C38: 6. Certificado de operación del establecimiento otorgado por el Colegio Profesional correspondiente.
B39: NA | C39: 7. Permiso de funcionamiento para calderas vigente, extendido por el ministerio.
B40: NA | C40: 8. Resolución de la DPAH autorizando la utilización de la fuente de emisiones de radiaciones ionizantes.
B41: NA | C41: 9. Contrato asignado por el Colegio de Ingenieros y Aruitectos a los planos constructivos.
B43: Además, declaro que la actividad para la cual solicito el PSF, cumple con los requisitos señalados para la solicitud del trámite por primera vez según el Reglamento General para Autorizaciones y Permisos Sanitarios de Funcionamiento Otorgados por el Ministerio de Salud. Sétimo. Asimismo, me comprometo a mantener las condiciones debidas por el tiempo de vigencia del permiso y cumplir con los términos de la normativa antes indicada, por ser requisito indispensable para la operación de mi establecimiento, de igual forma me comprometo que todos los servicios brindados y los productos, equipos y materiales que se comercialicen o utilicen dentro del establecimiento que represento, cuando proceda, estarán debidamente autorizados por el Ministerio de Salud y a no ampliar o cambiar de actividad sin la autorización previa de este Ministerio. Octavo. Por lo anterior, quedo apercibido de las consecuencias legales y judiciales, con que la legislación castiga el delito de perjurio. Asimismo, exonero de toda responsabilidad a las autoridades del Ministerio de Salud por el otorgamiento del PSF con base en la presente declaración. ADEMAS: conocedor de las consecuencias legales y administrativas de la presente declaración jurada, manifiesto y autorizo en forma expresa para que la autoridad de salud correspondiente, proceda a suspender o a cancelar el Permiso Sanitario de Funcionamiento, según corresponda, y prosiga con la clausura del establecimiento para el cual tramito el presente Permiso Sanitario de Funcionamiento, si se llegase a corroborar alguna falsedad en la presente declaración, errores u omisiones en los documentos aportados, o que los servicios prestados y/o los productos comercializados dentro de mi establecimiento no cuentan con la debida autorización sanitaria. ES TODO.
B57: Firmo en el cantón de | H57: Tilarán | R57: a las | T57: 03:00 pm
B58: del | C58: 12 | E58: de | F58: Agosto | I58: del | J58: 2019
M59: Firma
L61: Es auténtica:
B62: INSTRUCCIONES: a) En caso de persona jurídica debe aportar la certificación registral o notarial de la personería la cual tendrá una vigencia de un mes. La certificación digital expedida por el Registro Público tendrá una validez de 15 días naturales. b) En caso de que un tercero realice el trámite se debe adjuntar fotocopia de documento de identificación de quien solicita el PSF (eventual titular), además de la respectiva autorización. c) Solamente podrá rendir la declaración jurada quien esté facultado legalmente para dicho acto. d) Si la firma es digital no se requiere de autenticación. Igualmente, no requerirá autenticación si el gestionante realiza el trámite personalmente.

Sheet CIUU
B2: El Permiso Sanitario de Funcionamiento se otorga a los establecimientos que albergan las siguientes actividades | C2: Equivalencia al CIIU 3 | D2: Riesgo Sanitario Ministerio de Salud
B3: Actividades de la administración pública en general | C3: 7511 | D3: C
B4: Alquiler de cintas de video y discos. | C4: 7130 | D4: C
B5: Actividades combinadas de apoyo a instalaciones (mantenimiento, edificios y eliminación de sus residuos) | C5: 7020 | D5: C
B6: Actividades combinadas de servicios administrativos de oficina | C6: 7499 | D6: C
B7: Actividades de agencias de cobro y agencias de calificación crediticia | C7: 7495 | D7: C
B8: Actividades de agencias de empleos. | C8: 7491 | D8: C
B9: Actividades de agencias de noticias | C9: 9220 | D9: C
B10: Actividades de agencias de viajes | C10: 6304 | D10: C
B11: Actividades de arquitectura e ingeniería y actividades conexas de consultoría técnica (incluye servicios de ingeniería, arquitectura, dibujo de planos, diseño de edificios, servicios geodésicos, elaboración de proyectos de ingeniería civil, hidráulica, eléctrica, química, mecánica, industrial, planificación urbana, arquitectura paisajista. | C11: 7421 | D11: C
B12: Actividades de asociaciones empresariales y de empleadores. | C12: 9111 | D12: C
B13: Actividades de asociaciones profesionales | C13: 9112 | D13: C
B14: Actividades de bibliotecas y archivos | C14: 9231 | D14: C
B15: Actividades de centros de llamadas (call center) | C15: 7499 | D15: C
B16: Actividades de consultoría de gestión | C16: 7414 | D16: C
B17: Actividades de consultoría informática y gestión de instalaciones de informática | C17: 7220 | D17: C
B18: Actividades de contabilidad, teneduría de libros y auditoría; consultoría fiscal; asesoramiento en materia de impuestos | C18: 7412 | D18: C
B19: Actividades de distribución de películas, videocintas y programas de televisión | C19: 9212 | D19: C
B20: Actividades de fotografía (estudios fotográficos) | C20: 7494 | D20: C
B21: Actividades de investigación | C21: 7492 | D21: C
B22: Actividades de mantenimiento del orden público y de seguridad (salas de juicio, centros penitenciarios y correcciones de menores) | C22: 7523 | D22: C
B23: Actividades de mensajería (oficinas administrativas de mensajeros) | C23: Nuevo | D23: C
B24: Actividades de museos y conservación de lugares y edificios históricos | C24: 9231 | D24: C
B25: Actividades de oficinas principales | C25: Nuevo | D25: C
B26: Actividades de organizaciones políticas | C26: 9191 | D26: C
B27: Actividades de otras asociaciones n.c.p. | C27: 9191 | D27: C
B28: Actividades de planes de seguridad social de afiliación obligatoria | C28: Nuevo | D28: C
B29: Actividades de programación informática | C29: 7210 | D29: C
B30: Actividades de seguridad privada | C30: 7492 | D30: C
B31: Actividades de servicio de manutención y cuidado de paisajes (jardines, áreas verdes). | C31: 7493 | D31: C
B32: Actividades de servicios de sistemas de seguridad | C32: 5260 | D32: C
B33: Actividades de sindicatos | C33: 9120 | D33: C
B34: Actividades de telecomunicaciones alámbricas | C34: 7499 | D34: C
B35: Actividades de telecomunicaciones inalámbricas | C35: 7499 | D35: C
B36: Actividades de telecomunicaciones por satélite | C36: 7499 | D36: C
B37: Actividades especializadas de diseño (diseñadores de calzado, ropa) | C37: 7499 | D37: C
B38: Actividades inmobiliarias realizadas a cambio de una retribución o por contrata | C38: 7010 | D38: C
B39: Actividades inmobiliarias realizadas con bienes propios o arrendados (oficinas de bienes raíces) | C39: 7010 | D39: C
B40: Actividades jurídicas (oficinas de abogados) | C40: 7411 | D40: C
B41: Actividades postales (oficinas administrativas correos) | C41: Nuevo | D41: C
B42: Administración de mercados financieros (bolsa de valores) | C42: 6711 | D42: C
B43: Alquiler y arrendamiento de equipo recreativo y deportivo | C43: 7130 | D43: C
B44: Alquiler y arrendamiento de otros efectos personales y enseres domésticos | C44: 7130 | D44: C
B45: Alquiler y arrendamiento de otros tipos de maquinaria, equipo y bienes tangibles | C45: 9212 | D45: C
B46: Alquiler y arrendamiento de vehículos automotores | C46: 7111 | D46: C
B47: Ambulancias de Tipo B: Soporte Intermedio. | C47: 8519 | D47: C
B48: Ambulancias de Tipo C: Soporte Básico. | C48: 8519 | D48: C
B49: Construcción de carreteras y lineas de ferrocarril (oficinas) | C49: 4520 | D49: C
B50: Construcción de edificios (oficinas) | C50: 4520 | D50: C
B51: Construcción de otras obras de ingeniería civil (oficinas) | C51: 4520 | D51: C
B52: Construcción de proyectos de servicios públicos (oficinas) | C52: 4520 | D52: C
B53: Corretaje de valores y de contratos de productos básicos (oficinas de cambio) | C53: 6712 | D53: C
... B63: Establecimientos de atención Ambulatoria por profesionales en Enfermería Obstétrica. | C63: 8519 | D63: C
B64: Establecimientos de atención con servicios de albergues para la Atención de las personas que con V.I.H. / SIDA mayor de 18 años hasta 65 años | C64: 8531 | D64: C
B65: Establecimientos de atención con servicios de bronceado corporal | C65: 8519 | D65: C
B66: Establecimientos de atención con servicios de electrodiagnóstico. | C66: 8519 | D66: C
B67: Establecimientos que brindan atención a personas con discapacidad en la modalidad de alternativas residenciales | C67: Nuevo | D67: C
B68: Estacionamientos o parqueos públicos, parqueos para maquinaria de empresas constructoras sin mantenimiento. | C68: Nuevo | D68: C
B69: Estudios de mercado y encuestas de opinión pública | C69: 7413 | D69: C
B70: Fabricación artesanal de papel de tipo biodegradable | D70: C
B71: Fondo de pensiones (oficinas) | C71: 6602 | D71: C
B72: Fotocopiado, preparación de documentos y otras actividades especializadas de apoyo de oficina | C72: 7499 | D72: C
B73: Instalación de maquinaria y equipo industrial (oficinas) | C73: 2813 | D73: C
B74: Instalaciones de fontanería, de calefacción y de aire acondicionado | C74: 4530 | D74: C
B75: Instalaciones eléctricas (oficinas) | C75: 4530 | D75: C
B76: Investigaciones y desarrollo experimental en el campo de las ciencias naturales y la ingeniería | C76: 7310 | D76: C
B77: Investigaciones y desarrollo experimental en el campo de las ciencias sociales y las humanidades | C77: 7320 | D77: C
B78: Limpieza general de edificios | C78: 7493 | D78: C
B79: Organización de convenciones y exposiciones comerciales | C79: 7499 | D79: C
B80: Otras actividades de apoyo al transporte | C80: 6303 | D80: C
B81: Otras actividades de apoyo al transporte (incluye agencias de aduanas, tramitación de documentos de transporte, etc) | C81: 6303 | D81: C
B82: Otras actividades de dotación de recursos humanos | C82: Nuevo | D82: C
B83: Otras actividades de edición | C83: 2219 | D83: C
B84: Otras actividades de servicios de apoyo a las empresas n.c.p. | C84: 7499 | D84: C
B85: Otras actividades de servicios de información n.c.p | C85: 7499 | D85: C
B86: Otras actividades de tecnología de información y servicios informáticos. | C86: 7210 | D86: C
B87: Otras actividades de telecomunicaciones (incluye los café internet) | C87: 7499 | D87: C
B88: Otras actividades de venta al por menor en comercios no especializados entre los que no predominan los productos alimenticios, bebidas o tabaco (almacenes que venden variedad de productos como prendas de vestir, muebles, cosméticos, artículos de joyería y bisutería, juguetes, artículos de deporte, etc.) | C88: 5219 | D88: C
B89: Otras actividades de venta al por menor no realizadas en comercios, o mercados | C89: 5251 | D89: C
B90: Otras actividades especializadas de la construcción (Oficinas) | C90: 4520 | D90: C
B91: Otras actividades profesionales, científicas y técnicas n.c.p. (consultorías) | C91: 7499 | D91: C
B92: Otras instalaciones para obras de construcción | C92: 4530 | D92: C
B93: Otros servicios de reserva y actividades relacionadas | C93: 7513 | D93: C
B94: Peluquería y otros tratamientos de belleza (salones de belleza, barberías, corte, teñido de cabello , manicura y pedicura) | C94: 9302 | D94: C
B95: Portales Web | C95: 7230 | D95: C
B96: Preparación del terreno (oficinas) | C96: 4520 | D96: C
B97: Procesamiento de datos, hospedaje y actividades conexas | C97: 7230 | D97: C
B98: Procesamiento de datos, hospedaje y actividades conexas; portales Web. | C98: 7230 | D98: C
B99: Publicidad | C99: 7430 | D99: C
B100: Puestos de venta de lotería | C100: Nuevo | D100: C
B101: Regulación de las actividades de organismos que prestan servicios sanitarios, educativos, culturales y otros servicios sociales, excepto servicios de seguridad social | C101: 7512 | D101: C
B102: Regulación y facilitación de la actividad económica | C102: Nuevo | D102: C
B103: Reparación de aparatos de uso doméstico y equipo doméstico y de jardinería (taller de electrodomésticos como refrigeradoras, lavadoras, capeadoras de césped) | C103: 5260 | D103: C
B104: Reparación de aparatos electrónicos de consumo (talleres de cámara de videos, televisores, grabadoras, reproductores) | C104: 7250 | D104: C
B105: Reparación de calzado y artículos de cuero | C105: 5260 | D105: C
B106: Reparación de computadoras y equipo periférico (incluye pantallas, teclados, impresoras, servidores) | C106: 3220 | D106: C
B107: Reparación de equipo de comunicaciones (talleres de teléfonos, fax, celulares) | C107: 7250 | D107: C
B108: Reparación de muebles y accesorios domésticos | C108: 5260 | D108: C
B109: Reparación de otros efectos personales y enseres domésticos (incluye reparación de relojes, joyas, libros, juguetes, bicicletas, cerrajería) | C109: 5260 | D109: C
B110: Reproducción de grabaciones | C110: 2230 | D110: C
...

Sheet SIGRAMU
A1: RIESGO | D1: PATENTES | H1: Columna3 | I1: Columna2 | J1: Columna1
A2: A | B2: 1 | C2: Columna1 | D2: Columna2 | E2: Riesgo Sanitario Ministerio de Salud | F2: Tarifa recolección basura comercial | G2: Columna3 | H2: C | I2: 21956.912 | J2: Servicio recolección de basura comercial 1
A3: B | B3: =1+B2 -> 2 | C3: ACTIVIDADES TURISTICAS | D3: 0000133 | E3: B | F3: =VLOOKUP(Tabla822[[#This Row],[Riesgo Sanitario Ministerio de Salud]],$H$2:$J$4,3,0) -> Servicio recolección de basura comercial 2 | G3: =VLOOKUP(Tabla822[[#This Row],[Riesgo Sanitario Ministerio de Salud]],$H$2:$J$4,2,0) -> 30739.677 | H3: B | I3: 30739.677 | J3: Servicio recolección de basura comercial 2
A4: C | B4: =1+B3 -> 3 | C4: ACUARIO | D4: 0000208 | E4: C | F4: =VLOOKUP(Tabla822[[#This Row],[Riesgo Sanitario Ministerio de Salud]],$H$2:$J$4,3,0) -> Servicio recolección de basura comercial 1 | G4: =VLOOKUP(Tabla822[[#This Row],[Riesgo Sanitario Ministerio de Salud]],$H$2:$J$4,2,0) -> 21956.912 | H4: A | I4: 39522.442 | J4: Servicio recolección de basura comercial 3
B5: =1+B4 -> 4 | C5: AGEN Y REPARAC.BICICLETA | D5: 000077 | E5: C | F5: =VLOOKUP(Tabla822[[#This Row],[Riesgo Sanitario Ministerio de Salud]],$H$2:$J$4,3,0) -> Servicio recolección de basura comercial 1 | G5: =VLOOKUP(Tabla822[[#This Row],[Riesgo Sanitario Ministerio de Salud]],$H$2:$J$4,2,0) -> 21956.912
B6: =1+B5 -> 5 | C6: AGENCIA DE EQUIPO AGRICOLA | D6: 000011 | E6: C | F6: =VLOOKUP(Tabla822[[#This Row],[Riesgo Sanitario Ministerio de Salud]],$H$2:$J$4,3,0) -> Servicio recolección de basura comercial 1 | G6: =VLOOKUP(Tabla822[[#This Row],[Riesgo Sanitario Ministerio de Salud]],$H$2:$J$4,2,0) -> 21956.912
B7: =1+B6 -> 6 | C7: AGENCIA DE GAS PROPANO | D7: 00006 | E7: B | F7: =VLOOKUP(Tabla822[[#This Row],[Riesgo Sanitario Ministerio de Salud]],$H$2:$J$4,3,0) -> Servicio recolección de basura comercial 2 | G7: =VLOOKUP(Tabla822[[#This Row],[Riesgo Sanitario Ministerio de Salud]],$H$2:$J$4,2,0) -> 30739.677
B8: =1+B7 -> 7 | C8: AGENCIA DE MOTOCICLETAS | D8: 0000181 | E8: C | F8: =VLOOKUP(Tabla822[[#This Row],[Riesgo Sanitario Ministerio de Salud]],$H$2:$J$4,3,0) -> Servicio recolección de basura comercial 1 | G8: =VLOOKUP(Tabla822[[#This Row],[Riesgo Sanitario Ministerio de Salud]],$H$2:$J$4,2,0) -> 21956.912
B9: =1+B8 -> 8 | C9: AGENCIA DE PINTURAS | D9: 000013 | E9: C | F9: =VLOOKUP(Tabla822[[#This Row],[Riesgo Sanitario Ministerio de Salud]],$H$2:$J$4,3,0) -> Servicio recolección de basura comercial 1 | G9: =VLOOKUP(Tabla822[[#This Row],[Riesgo Sanitario Ministerio de Salud]],$H$2:$J$4,2,0) -> 21956.912
B10: =1+B9 -> 9 | C10: AGENCIA DE REPUESTOS | D10: 000060 | E10: C | F10: =VLOOKUP(Tabla822[[#This Row],[Riesgo Sanitario Ministerio de Salud]],$H$2:$J$4,3,0) -> Servicio recolección de basura comercial 1 | G10: =VLOOKUP(Tabla822[[#This Row],[Riesgo Sanitario Ministerio de Salud]],$H$2:$J$4,2,0) -> 21956.912
B11: =1+B10 -> 10 | C11: AGENCIA Y TALLER DE MOTOCICLETAS | D11: 000010 | E11: C | F11: =VLOOKUP(Tabla822[[#This Row],[Riesgo Sanitario Ministerio de Salud]],$H$2:$J$4,3,0) -> Servicio recolección de basura comercial 1 | G11: =VLOOKUP(Tabla822[[#This Row],[Riesgo Sanitario Ministerio de Salud]],$H$2:$J$4,2,0) -> 21956.912
B12: =1+B11 -> 11 | C12: ALBERGUE | D12: 0000108 | E12: C | F12: =VLOOKUP(Tabla822[[#This Row],[Riesgo Sanitario Ministerio de Salud]],$H$2:$J$4,3,0) -> Servicio recolección de basura comercial 1 | G12: =VLOOKUP(Tabla822[[#This Row],[Riesgo Sanitario Ministerio de Salud]],$H$2:$J$4,2,0) -> 21956.912
B13: =1+B12 -> 12 | C13: ALMACEN.. | D13: 000014 | E13: A | F13: =VLOOKUP(Tabla822[[#This Row],[Riesgo Sanitario Ministerio de Salud]],$H$2:$J$4,3,0) -> Servicio recolección de basura comercial 3 | G13: =VLOOKUP(Tabla822[[#This Row],[Riesgo Sanitario Ministerio de Salud]],$H$2:$J$4,2,0) -> 39522.442
B14: =1+B13 -> 13 | C14: ALQUILER DE CABALLOS | D14: 0000156 | E14: C | F14: =VLOOKUP(Tabla822[[#This Row],[Riesgo Sanitario Ministerio de Salud]],$H$2:$J$4,3,0) -> Servicio recolección de basura comercial 1 | G14: =VLOOKUP(Tabla822[[#This Row],[Riesgo Sanitario Ministerio de Salud]],$H$2:$J$4,2,0) -> 21956.912
B15: =1+B14 -> 14 | C15: ALQUILER DE CUADRACICLOS | D15: 0000157 | E15: C | F15: =VLOOKUP(Tabla822[[#This Row],[Riesgo Sanitario Ministerio de Salud]],$H$2:$J$4,3,0) -> Servicio recolección de basura comercial 1 | G15: =VLOOKUP(Tabla822[[#This Row],[Riesgo Sanitario Ministerio de Salud]],$H$2:$J$4,2,0) -> 21956.912
B16: =1+B15 -> 15 | C16: ALQUILER DE VIDEOS | D16: 000032 | E16: C | F16: =VLOOKUP(Tabla822[[#This Row],[Riesgo Sanitario Ministerio de Salud]],$H$2:$J$4,3,0) -> Servicio recolección de basura comercial 1 | G16: =VLOOKUP(Tabla822[[#This Row],[Riesgo Sanitario Ministerio de Salud]],$H$2:$J$4,2,0) -> 21956.912
... B26: =1+B25 -> 25 | C26: BOTANICA | D26: 0000146 | E26: C | F26: =VLOOKUP(Tabla822[[#This Row],[Riesgo Sanitario Ministerio de Salud]],$H$2:$J$4,3,0) -> Servicio recolección de basura comercial 1 | G26: =VLOOKUP(Tabla822[[#This Row],[Riesgo Sanitario Ministerio de Salud]],$H$2:$J$4,2,0) -> 21956.912
B27: =1+B26 -> 26 | C27: BUHONERO | D27: 000068
B28: =1+B27 -> 27 | C28: CABINAS | D28: 000071 | E28: C | F28: =VLOOKUP(Tabla822[[#This Row],[Riesgo Sanitario Ministerio de Salud]],$H$2:$J$4,3,0) -> Servicio recolección de basura comercial 1 | G28: =VLOOKUP(Tabla822[[#This Row],[Riesgo Sanitario Ministerio de Salud]],$H$2:$J$4,2,0) -> 21956.912
B29: =1+B28 -> 28 | C29: CAJA RECAUDADORA SERV. PUBLICOS | D29: 0000191 | E29: C | F29: =VLOOKUP(Tabla822[[#This Row],[Riesgo Sanitario Ministerio de Salud]],$H$2:$J$4,3,0) -> Servicio recolección de basura comercial 1 | G29: =VLOOKUP(Tabla822[[#This Row],[Riesgo Sanitario Ministerio de Salud]],$H$2:$J$4,2,0) -> 21956.912
B30: =1+B29 -> 29 | C30: CANCHA SINTETICA BUTBOL 5 | D30: 0000171 | E30: C | F30: =VLOOKUP(Tabla822[[#This Row],[Riesgo Sanitario Ministerio de Salud]],$H$2:$J$4,3,0) -> Servicio recolección de basura comercial 1 | G30: =VLOOKUP(Tabla822[[#This Row],[Riesgo Sanitario Ministerio de Salud]],$H$2:$J$4,2,0) -> 21956.912
B31: =1+B30 -> 30 | C31: CARNICERIA | D31: 000018 | E31: B | F31: =VLOOKUP(Tabla822[[#This Row],[Riesgo Sanitario Ministerio de Salud]],$H$2:$J$4,3,0) -> Servicio recolección de basura comercial 2 | G31: =VLOOKUP(Tabla822[[#This Row],[Riesgo Sanitario Ministerio de Salud]],$H$2:$J$4,2,0) -> 30739.677
B32: =1+B31 -> 31 | C32: CENTRO ACOPIO RESIDUOS VALORIZABLES | D32: 00000501 | E32: A | F32: =VLOOKUP(Tabla822[[#This Row],[Riesgo Sanitario Ministerio de Salud]],$H$2:$J$4,3,0) -> Servicio recolección de basura comercial 3 | G32: =VLOOKUP(Tabla822[[#This Row],[Riesgo Sanitario Ministerio de Salud]],$H$2:$J$4,2,0) -> 39522.442
B33: =1+B32 -> 32 | C33: CENTRO EDUCATIVO PRIVADO | D33: 0000113 | E33: B | F33: =VLOOKUP(Tabla822[[#This Row],[Riesgo Sanitario Ministerio de Salud]],$H$2:$J$4,3,0) -> Servicio recolección de basura comercial 2 | G33: =VLOOKUP(Tabla822[[#This Row],[Riesgo Sanitario Ministerio de Salud]],$H$2:$J$4,2,0) -> 30739.677
B34: =1+B33 -> 33 | C34: CERRAJERIA | D34: 0000159 | E34: C | F34: =VLOOKUP(Tabla822[[#This Row],[Riesgo Sanitario Ministerio de Salud]],$H$2:$J$4,3,0) -> Servicio recolección de basura comercial 1 | G34: =VLOOKUP(Tabla822[[#This Row],[Riesgo Sanitario Ministerio de Salud]],$H$2:$J$4,2,0) -> 21956.912
B35: =1+B34 -> 34 | C35: CLUB DE NUTRICION Y BATIDOS | D35: 0000179 | E35: C | F35: =VLOOKUP(Tabla822[[#This Row],[Riesgo Sanitario Ministerio de Salud]],$H$2:$J$4,3,0) -> Servicio recolección de basura comercial 1 | G35: =VLOOKUP(Tabla822[[#This Row],[Riesgo Sanitario Ministerio de Salud]],$H$2:$J$4,2,0) -> 21956.912
B36: =1+B35 -> 35 | C36: COMERCIALIZACION BIENES SERV.TELEC | D36: 0000217 | E36: C | F36: =VLOOKUP(Tabla822[[#This Row],[Riesgo Sanitario Ministerio de Salud]],$H$2:$J$4,3,0) -> Servicio recolección de basura comercial 1 | G36: =VLOOKUP(Tabla822[[#This Row],[Riesgo Sanitario Ministerio de Salud]],$H$2:$J$4,2,0) -> 21956.912
B37: =1+B36 -> 36 | C37: COMPRA Y VENTA | D37: 0000178 | E37: C | F37: =VLOOKUP(Tabla822[[#This Row],[Riesgo Sanitario Ministerio de Salud]],$H$2:$J$4,3,0) -> Servicio recolección de basura comercial 1 | G37: =VLOOKUP(Tabla822[[#This Row],[Riesgo Sanitario Ministerio de Salud]],$H$2:$J$4,2,0) -> 21956.912
B38: =1+B37 -> 37 | C38: CONFECCION DE CORTINAS | D38: 0000155 | E38: C | F38: =VLOOKUP(Tabla822[[#This Row],[Riesgo Sanitario Ministerio de Salud]],$H$2:$J$4,3,0) -> Servicio recolección de basura comercial 1 | G38: =VLOOKUP(Tabla822[[#This Row],[Riesgo Sanitario Ministerio de Salud]],$H$2:$J$4,2,0) -> 21956.912
B39: =1+B38 -> 38 | C39: CONFECCION ROTULOS Y ARTESANIAS | D39: 0000180 | E39: C | F39: =VLOOKUP(Tabla822[[#This Row],[Riesgo Sanitario Ministerio de Salud]],$H$2:$J$4,3,0) -> Servicio recolección de basura comercial 1 | G39: =VLOOKUP(Tabla822[[#This Row],[Riesgo Sanitario Ministerio de Salud]],$H$2:$J$4,2,0) -> 21956.912
... B83: =1+B82 -> 82 | C83: MULTISERVICIOS | D83: 00000499 | E83: B | F83: =VLOOKUP(Tabla822[[#This Row],[Riesgo Sanitario Ministerio de Salud]],$H$2:$J$4,3,0) -> Servicio recolección de basura comercial 2 | G83: =VLOOKUP(Tabla822[[#This Row],[Riesgo Sanitario Ministerio de Salud]],$H$2:$J$4,2,0) -> 30739.677
B84: =1+B83 -> 83 | C84: NO CLASIFICADAS | D84: 000016 | G84: =VLOOKUP(Tabla822[[#This Row],[Riesgo Sanitario Ministerio de Salud]],$H$2:$J$4,2,0) -> #N/A
B85: =1+B84 -> 84 | C85: OFICINA DE SERVICIOS | D85: 00005 | E85: C | F85: =VLOOKUP(Tabla822[[#This Row],[Riesgo Sanitario Ministerio de Salud]],$H$2:$J$4,3,0) -> Servicio recolección de basura comercial 1 | G85: =VLOOKUP(Tabla822[[#This Row],[Riesgo Sanitario Ministerio de Salud]],$H$2:$J$4,2,0) -> 21956.912
B86: =1+B85 -> 85 | C86: OFICINA SERVICIOS PROVEEDURIA | D86: 0000238 | E86: C | F86: =VLOOKUP(Tabla822[[#This Row],[Riesgo Sanitario Ministerio de Salud]],$H$2:$J$4,3,0) -> Servicio recolección de basura comercial 1 | G86: =VLOOKUP(Tabla822[[#This Row],[Riesgo Sanitario Ministerio de Salud]],$H$2:$J$4,2,0) -> 21956.912
B87: =1+B86 -> 86 | C87: OPERADOR DE TURISMO | D87: 000083 | E87: C | F87: =VLOOKUP(Tabla822[[#This Row],[Riesgo Sanitario Ministerio de Salud]],$H$2:$J$4,3,0) -> Servicio recolección de basura comercial 1 | G87: =VLOOKUP(Tabla822[[#This Row],[Riesgo Sanitario Ministerio de Salud]],$H$2:$J$4,2,0) -> 21956.912
B88: =1+B87 -> 87 | C88: OPTICA | D88: 0000162 | E88: C | F88: =VLOOKUP(Tabla822[[#This Row],[Riesgo Sanitario Ministerio de Salud]],$H$2:$J$4,3,0) -> Servicio recolección de basura comercial 1 | G88: =VLOOKUP(Tabla822[[#This Row],[Riesgo Sanitario Ministerio de Salud]],$H$2:$J$4,2,0) -> 21956.912
B89: =1+B88 -> 88 | C89: PANADERIA Y REPOSTERIA | D89: 000062 | E89: B | F89: =VLOOKUP(Tabla822[[#This Row],[Riesgo Sanitario Ministerio de Salud]],$H$2:$J$4,3,0) -> Servicio recolección de basura comercial 2 | G89: =VLOOKUP(Tabla822[[#This Row],[Riesgo Sanitario Ministerio de Salud]],$H$2:$J$4,2,0) -> 30739.677
B90: =1+B89 -> 89 | C90: PATINES TEMPORALES | D90: 000099 | E90: C | F90: =VLOOKUP(Tabla822[[#This Row],[Riesgo Sanitario Ministerio de Salud]],$H$2:$J$4,3,0) -> Servicio recolección de basura comercial 1 | G90: =VLOOKUP(Tabla822[[#This Row],[Riesgo Sanitario Ministerio de Salud]],$H$2:$J$4,2,0) -> 21956.912
B91: =1+B90 -> 90 | C91: PELUQUERIA Y TRATAMIENTO BELLEZA | D91: 00000506 | E91: C | F91: =VLOOKUP(Tabla822[[#This Row],[Riesgo Sanitario Ministerio de Salud]],$H$2:$J$4,3,0) -> Servicio recolección de basura comercial 1 | G91: =VLOOKUP(Tabla822[[#This Row],[Riesgo Sanitario Ministerio de Salud]],$H$2:$J$4,2,0) -> 21956.912
B92: =1+B91 -> 91 | C92: PERIFONEO SIMILARES | D92: 0000150 | E92: C | F92: =VLOOKUP(Tabla822[[#This Row],[Riesgo Sanitario Ministerio de Salud]],$H$2:$J$4,3,0) -> Servicio recolección de basura comercial 1 | G92: =VLOOKUP(Tabla822[[#This Row],[Riesgo Sanitario Ministerio de Salud]],$H$2:$J$4,2,0) -> 21956.912
B93: =1+B92 -> 92 | C93: PESCADERIA | D93: 0000117 | E93: B | F93: =VLOOKUP(Tabla822[[#This Row],[Riesgo Sanitario Ministerio de Salud]],$H$2:$J$4,3,0) -> Servicio recolección de basura comercial 2 | G93: =VLOOKUP(Tabla822[[#This Row],[Riesgo Sanitario Ministerio de Salud]],$H$2:$J$4,2,0) -> 30739.677
B94: =1+B93 -> 93 | C94: PIZZERIA | D94: 0000130 | E94: B | F94: =VLOOKUP(Tabla822[[#This Row],[Riesgo Sanitario Ministerio de Salud]],$H$2:$J$4,3,0) -> Servicio recolección de basura comercial 2 | G94: =VLOOKUP(Tabla822[[#This Row],[Riesgo Sanitario Ministerio de Salud]],$H$2:$J$4,2,0) -> 30739.677
B95: =1+B94 -> 94 | C95: POLLO FRITO | D95: 000036 | E95: B | F95: =VLOOKUP(Tabla822[[#This Row],[Riesgo Sanitario Ministerio de Salud]],$H$2:$J$4,3,0) -> Servicio recolección de basura comercial 2 | G95: =VLOOKUP(Tabla822[[#This Row],[Riesgo Sanitario Ministerio de Salud]],$H$2:$J$4,2,0) -> 30739.677
B96: =1+B95 -> 95 | C96: POOLES | D96: 000069 | E96: C | F96: =VLOOKUP(Tabla822[[#This Row],[Riesgo Sanitario Ministerio de Salud]],$H$2:$J$4,3,0) -> Servicio recolección de basura comercial 1 | G96: =VLOOKUP(Tabla822[[#This Row],[Riesgo Sanitario Ministerio de Salud]],$H$2:$J$4,2,0) -> 21956.912
... B184: =1+B183 -> 183 | C184: VIVERO | D184: 0000139 | E184: C | F184: =VLOOKUP(Tabla822[[#This Row],[Riesgo Sanitario Ministerio de Salud]],$H$2:$J$4,3,0) -> Servicio recolección de basura comercial 1 | G184: =VLOOKUP(Tabla822[[#This Row],[Riesgo Sanitario Ministerio de Salud]],$H$2:$J$4,2,0) -> 21956.912
B185: =1+B184 -> 184 | F185: =VLOOKUP(Tabla822[[#This Row],[Riesgo Sanitario Ministerio de Salud]],$H$2:$J$4,3,0) -> #N/A | G185: =VLOOKUP(Tabla822[[#This Row],[Riesgo Sanitario Ministerio de Salud]],$H$2:$J$4,2,0) -> #N/A
B186: =1+B185 -> 185 | F186: =VLOOKUP(Tabla822[[#This Row],[Riesgo Sanitario Ministerio de Salud]],$H$2:$J$4,3,0) -> #N/A | G186: =VLOOKUP(Tabla822[[#This Row],[Riesgo Sanitario Ministerio de Salud]],$H$2:$J$4,2,0) -> #N/A
B187: =1+B186 -> 186 | F187: =VLOOKUP(Tabla822[[#This Row],[Riesgo Sanitario Ministerio de Salud]],$H$2:$J$4,3,0) -> #N/A | G187: =VLOOKUP(Tabla822[[#This Row],[Riesgo Sanitario Ministerio de Salud]],$H$2:$J$4,2,0) -> #N/A
B188: =1+B187 -> 187 | F188: =VLOOKUP(Tabla822[[#This Row],[Riesgo Sanitario Ministerio de Salud]],$H$2:$J$4,3,0) -> #N/A | G188: =VLOOKUP(Tabla822[[#This Row],[Riesgo Sanitario Ministerio de Salud]],$H$2:$J$4,2,0) -> #N/A
B189: =1+B188 -> 188 | F189: =VLOOKUP(Tabla822[[#This Row],[Riesgo Sanitario Ministerio de Salud]],$H$2:$J$4,3,0) -> #N/A | G189: =VLOOKUP(Tabla822[[#This Row],[Riesgo Sanitario Ministerio de Salud]],$H$2:$J$4,2,0) -> #N/A
B190: =1+B189 -> 189 | F190: =VLOOKUP(Tabla822[[#This Row],[Riesgo Sanitario Ministerio de Salud]],$H$2:$J$4,3,0) -> #N/A | G190: =VLOOKUP(Tabla822[[#This Row],[Riesgo Sanitario Ministerio de Salud]],$H$2:$J$4,2,0) -> #N/A
B191: =1+B190 -> 190 | F191: =VLOOKUP(Tabla822[[#This Row],[Riesgo Sanitario Ministerio de Salud]],$H$2:$J$4,3,0) -> #N/A | G191: =VLOOKUP(Tabla822[[#This Row],[Riesgo Sanitario Ministerio de Salud]],$H$2:$J$4,2,0) -> #N/A
B192: =1+B191 -> 191 | F192: =VLOOKUP(Tabla822[[#This Row],[Riesgo Sanitario Ministerio de Salud]],$H$2:$J$4,3,0) -> #N/A | G192: =VLOOKUP(Tabla822[[#This Row],[Riesgo Sanitario Ministerio de Salud]],$H$2:$J$4,2,0) -> #N/A
B193: =1+B192 -> 192 | F193: =VLOOKUP(Tabla822[[#This Row],[Riesgo Sanitario Ministerio de Salud]],$H$2:$J$4,3,0) -> #N/A | G193: =VLOOKUP(Tabla822[[#This Row],[Riesgo Sanitario Ministerio de Salud]],$H$2:$J$4,2,0) -> #N/A
B194: =1+B193 -> 193 | F194: =VLOOKUP(Tabla822[[#This Row],[Riesgo Sanitario Ministerio de Salud]],$H$2:$J$4,3,0) -> #N/A | G194: =VLOOKUP(Tabla822[[#This Row],[Riesgo Sanitario Ministerio de Salud]],$H$2:$J$4,2,0) -> #N/A
B195: =1+B194 -> 194 | F195: =VLOOKUP(Tabla822[[#This Row],[Riesgo Sanitario Ministerio de Salud]],$H$2:$J$4,3,0) -> #N/A | G195: =VLOOKUP(Tabla822[[#This Row],[Riesgo Sanitario Ministerio de Salud]],$H$2:$J$4,2,0) -> #N/A
B196: =1+B195 -> 195 | F196: =VLOOKUP(Tabla822[[#This Row],[Riesgo Sanitario Ministerio de Salud]],$H$2:$J$4,3,0) -> #N/A | G196: =VLOOKUP(Tabla822[[#This Row],[Riesgo Sanitario Ministerio de Salud]],$H$2:$J$4,2,0) -> #N/A
... B200: =1+B199 -> 199 | F200: =VLOOKUP(Tabla822[[#This Row],[Riesgo Sanitario Ministerio de Salud]],$H$2:$J$4,3,0) -> #N/A | G200: =VLOOKUP(Tabla822[[#This Row],[Riesgo Sanitario Ministerio de Salud]],$H$2:$J$4,2,0) -> #N/A
B201: =1+B200 -> 200 | C201: NINGÚN OTRA | D201: NA | F201: =VLOOKUP(Tabla822[[#This Row],[Riesgo Sanitario Ministerio de Salud]],$H$2:$J$4,3,0) -> #N/A | G201: =VLOOKUP(Tabla822[[#This Row],[Riesgo Sanitario Ministerio de Salud]],$H$2:$J$4,2,0) -> #N/A
F202: =VLOOKUP(Tabla822[[#This Row],[Riesgo Sanitario Ministerio de Salud]],$H$2:$J$4,3,0) -> #N/A | G202: =VLOOKUP(Tabla822[[#This Row],[Riesgo Sanitario Ministerio de Salud]],$H$2:$J$4,2,0) -> #N/A

Sheet CERTIFICADO CVO
B2: GOBIERNO MUNICIPAL DE TILARÁN
B3: Proceso de Servicios Ciudadanos y Técnicos
B6: CERTIFICADO DE PATENTE COMERCIAL
B8: NOMBRE DEL NEGOCIO: | I8: =' FMT 104 TOMA DATOS'!H28 -> 0
B9: UBICACIÓN: | F9: =' FMT 104 TOMA DATOS'!H38 -> 150 este CCSS
B10: ACTIVIDADES COMERCIALES AUTORIZADAS POR LA MUNICIPALIDAD DE TILARÁN:
B11: 1 | C11: ='CALCULO LICENCIA'!H14 -> ELABORACIÓN DE PRODUCTOS EMULSIFICADOS
B12: =1+B11 -> 2 | C12: ='CALCULO LICENCIA'!H15 -> NINGÚN OTRA
B13: =1+B12 -> 3 | C13: ='CALCULO LICENCIA'!H16 -> NINGÚN OTRA
B14: =1+B13 -> 4 | C14: ='CALCULO LICENCIA'!H17 -> NINGÚN OTRA
B15: NOMBRE DEL PATENTADO: | I15: ='CALCULO LICENCIA'!I10 -> Picado Fernandez Ricardo | AB15: N° CEDULA: | AE15: ='CALCULO LICENCIA'!W10 -> 501450912
B16: REPRESENTANTE LEGAL: | H16: ='CALCULO LICENCIA'!H11 -> 0 | AB16: =+AB15 -> N° CEDULA: | AE16: ='CALCULO LICENCIA'!W11 -> 0
B17: EL PORTADOR DE LA CÉDULA NÚMERO: | L17: =AE15 -> 501450912 | R17: HA CUMPLIDO CON LOS REQUISITOS NECESARIOS PARA OTORGARLE LA(S)
B18: LICENCIA(S) MUNICIPALES HASTA EL 31 DE DICIEMBRE DEL AÑO: | R18: 2022 | U18: ////Colóquese en lugar visible////
B20: Certificado Veterinario de Operaciones | K20: 212018-01 | N20: DEL | O20: 25 | P20: DE | Q20: ENERO | U20: DE | V20: 2022 | Y20: emitido por el Ministerio de Agricultura y Ganaderia
B21: debiendo renovarse el | H21: =+O20 -> 25 | I21: de | J21: =+Q20 -> ENERO | O21: del | P21: =1+V20 -> 2023
B26: =+'[6]RESOLUCION COMERCIAL'!N48 -> María Cecilia Prendas Martínez
B27: ASISTENTE TÉCNICO
B28: OBSERVACIONES:
